Workbook

Sheet OVERVIEW
B3: Description and Guide to the RNG (Renewable Natural Gas) Database
B5: A. PURPOSE
B7: The RNG database was developed to provide a comprehensive list of biogas projects that are upgrading gas for pipeline injection or use as vehicle fuel (whether locally or at the end of a pipeline).
B8: It includes projects that are known to have been in operation or under construction prior to December 31, 2023, along with previously operational projects now shut down.
B9: It also includes projects that are projected to be under construction or operational by December 31, 2023.
B10: Because the size and scope of projects that do not have a “shovel in the ground” are often in flux, the database excludes planned projects.
B11: The database is an Excel.xls format spreadsheet and is compatible with any version of Misrosoft Excel. Although a handful of Canadian projects deliver RNG into the US, all projects listed in the database are in the United States.
B13: B. ACKNOWLEDGEMENTS
B15: This spreadsheet was developed by staff of Argonne National Laboratory ("Argonne") and Energy Vision. Argonne is a U.S. Department of Energy laboratory managed by UChicago Argonne, LLC under contract DE-AC02-06CH11357. | S15: DE-AC02-06CH11357.
B16: Energy Vision is a 501 (c)(3) environmental research group. Energy Vision’s work was conducted under Argonne Contract No. 0F-60161.
B17: This spreadsheet was prepared as an account of work sponsored by an agency of the United States Government. Neither the United States Government nor any agency thereof, nor UChicago Argonne, LLC, nor any of their employees or officers,
B18: makes any warranty, express or implied, or assumes any legal liability or responsibility for the accuracy, completeness, or usefulness of any information, apparatus, product, or process disclosed, or represents that its use would not infringe privately owned rights.
B19: Reference herein to any specific commercial product, process, or service by trade name, trademark, manufacturer, or otherwise, does not necessarily constitute or imply its endorsement, recommendation, or favoring by the United States Government
B20: or any agency thereof. The views and opinions of document authors expressed herein do not necessarily state or reflect those of the United States Government or any agency thereof, Argonne National Laboratory, or UChicago Argonne, LLC.
B22: C. STRUCTURE AND DEFINITION OF TERMS
B24: This workook updates earlier work by Argonne and Energy Vision. It focuses on revising the operational status (operational, under construction, planned, cancelled/shut down) of previously documented projects.
B25: Updates are based primarily on press accounts and other public information. Outreach to project contacts was conducted primarily when other sources of information were unavailable or inconclusive.
B28: Excluding this Overview tab, the workbook contains eight tabs: four tabs summarizing projects by feedstock, and four tabs providing summaries, definitions and other notes.
B30: Projects tabs: List RNG projects by the feedstock from which they derive biogas.
B32: 1. Food waste: Projects using commercial or post-consumer food waste as the main feedstock.
B34: 2. Landfills: Projects collecting and upgrading gas from existing landfills.
... B71: F. DATABASE HIGHLIGHTS FOR RNG PROJECTS FULLY OR PARTIALLY GOING TO TRANSPORTATION (PROJECTED AS OF 12/31/23)
B73: · Total projects, all statuses: | F73: =TOTALS!E22 -> 541 | G73: (excluding shut down, canceled, suspended)
B74: · Total confirmed operational projects: | F74: =TOTALS!B22 -> 305
B75: · Total operational production: | F75: =TOTALS!C45 -> 1.0843954e+08 | G75: MMBTU, | H75: =TOTALS!D45 -> 9.6653599e+08 | I75: GGEs or | J75: =TOTALS!E45 -> 8.4266433e+08 | K75: DGEs, up | L75: =TOTALS!C47 -> 0.22034197 | M75: from 12/31/2022
B76: · Total under construction production: | F76: =TOTALS!C58 -> 35494780 | G76: MMBTU, | H76: =TOTALS!D58 -> 3.1636968e+08 | I76: GGEs or | J76: =TOTALS!E58 -> 2.7579464e+08 | K76: DGEs, up | L76: =TOTALS!C60 -> 0.7426933 | M76: from 12/31/2022
B80: G. CITATION AND CONTACT INFORMATION
B82: The spreadsheet may be cited as follows:
B83: Mintz, M. and Lerner, M.. Database of Renewable Natural Gas (RNG) Projects: 2023 Update, Argonne National Laboratory, July 2024, https://www.anl.gov/es/reference/renewable-natural-gas-database.
B85: For further information, please contact:
B86: Marianne Mintz | D86: mmintz@anl.gov | F86: or
B87: Matt Tomich | D87: Tomich@energy-vision.org

Sheet Food Waste
A1: Key: | B1: Project added 2023 | F1: Color coding generally applies to numeric values only.
B2: Information provided or confirmed by contact | F2: Individual values are often drawn from different sources, and so may appear inconsistent-- e.g., gas going for upgrading may be more than total amount of gas collected
B3: Value calculated based on other info provided
B4: Value from press/website
A6: GENERAL INFORMATION | F6: PROJECT INFORMATION | J6: INPUTS | N6: OUTPUTS | V6: ADDITIONAL INFORMATION
A7: Waste Conversion Facility Name | B7: Projected status 12/31/2023 | C7: Facility Owner | D7: County | E7: State | F7: Project Start Date | G7: Project Developer | H7: Project Description | I7: Digester Type | J7: Amount of Waste Delivered | K7: Capacity (tons per day) | L7: Waste Type | M7: Waste Provider | N7: Raw Biogas Produced, SCFD | O7: Upgraded SCFD | P7: Upgraded MMBTU/yr. | Q7: Upgraded Fuel Type Produced | R7: If producing vehicle fuel, public filling station? | S7: GGE/yr. | T7: Capacity (GGE/yr.) | U7: Electricity Produced | V7: Annual CO2 Emissions Eliminated | X7: RIN Registrant? | Y7: References
A8: OPERATIONAL AS OF 12/31/2023
A9: Blue Line Biogenic CNG Facility | B9: OPERATIONAL | D9: San Francisco | E9: CA | F9: 2015 | G9: Blue Line Transfer, Inc.; Zero Waste Energy, LLC; South San Francisco Scavenger Co. | H9: Converts food and green waste into CNG fuel for 27 vehicles, during the weekdays they use a mix of CNG and NG, on the weekends when they have more fill time they use all CNG. Appears to be activated carbon upgrading system. | I9: 8 dry anaerobic digesters, thermophilic | J9: 11,200 tons/yr. | K9: 11200 tons/year | L9: Commercial and residential organics | M9: Customer base | N9: 73300 | O9: =N9*0.6 -> 43980 | P9: =O9*0.001*365*0.9 -> 14447.43 | Q9: VEHICLE FUEL (LOCAL) | R9: Private | S9: =P9/0.112194 -> 128771.86 | U9: N/A | X9: Yes | Y9: http://www.americanbiogascouncil.org/projectprofiles/southsanfranciscoca.pdf http://zerowasteenergy.com/our-projects/blue-line-biogenic-cng-facility/ https://www.biocycle.net/2016/07/14/biogas-fleet-fuel-south-san-francisco/ https://energy-vision.org/wp-content/uploads/2016/01/South-SF-Scavenger-BlueLine-Profile.pdf https://www.biocycle.net/second-food-scraps-to-rng-project-certified-under-california-lcfs-greet-3-0/ https://www.greencarcongress.com/2021/03/20210309-ssfsc.html
A10: CR&R Perris Transfer Station and MRF | B10: OPERATIONAL | C10: CR&R | D10: Riverside | E10: CA | F10: 2016 | G10: CR&R Waste and Recycling Services | H10: Will create high BTU RNG derived from MSW using two state anaerobic digestion; CNG fueling station is currently fueling 320 of CR&R's collection vehicles, eventually to be expanded to 900. Excess CNG will feed into a natural gas pipeline distribution system; digestate will be utilized as a soil amendment | I10: Eisenmann mixed plug flow. Upgrading technology Greenlane Biogas (water wash) | J10: As of 2021, with phases 1 & 2 complete, they are accepting about 100,000 tons per year. | K10: With phase 2 complete, approx. 470 tpd. With competion of phase 4, this will increase to ~900 tpd | L10: Commercial food scraps, green waste, FOG. | M10: Customer base | N10: =O10/0.6 -> 569223.74 | O10: =P10/(0.001*365*0.9) -> 341534.25 | P10: =S10*0.112194 -> 112194 | Q10: BOTH | R10: No | S10: 1000000 | T10: 4,000,000 GGE by 2021 | U10: N/A | V10: =11548*2 -> 23096 | X10: Yes | Y10: http://biomassmagazine.com/articles/10641/crr-breaks-ground-on-california-ad-facility http://www.prnewswire.com/news-releases/socalgas-and-crr-environmental-announce-construction-of-pipeline-to-provide-carbon-neutral-renewable-natural-gas-300399808.html http://www.fleetsandfuels.com/fuels/cng/2017/02/sogalgas-and-crr-for-rng-pipeline/ http://crrwasteservices.com/sustainability/anaerobic-digestion/
A11: Escondido Disposal RNG | B11: OPERATIONAL | C11: Escondido Disposal, Inc. | D11: San Diego | E11: CA | F11: Project expected to become operational Q3/Q4 2021 | G11: Escondido Disposal Inc., Hitachi Zoven Innova | H11: EDI will use RNG produced from area food waste to fuel its fleet. As of July one digester is up and running, on tail end of commissioning, have to Cx second. This is potentially a two phase project, with 2 more digesters being installed if EDI's flow increases enough to justify it. | I11: Dry thermophilic, plug flow | J11: ~250 TPD. | L11: Commercial and residential food scraps | M11: Customer base | N11: =O11/0.6 -> 730593.61 | O11: =P11/(0.001*365*0.9) -> 438356.16 | P11: 144000 | Q11: BOTH | R11: Private | S11: =P11/0.112194 -> 1283491.1 | Y11: https://www.times-advocate.com/articles/escondido-ad-facility-is-first-in-county/ https://www.escondidodisposal.com/commercial-waste-services/commercial-services/organic-recycling/# https://dpw.lacounty.gov/epd/tf/Attachments/Minutes_Attachments/2021_Attachments/Hitachi_Zosen_INOVA_Presentation_3-11-2021.pdf https://www.hz-inova.com/renewable-gas/anaerobic-digestion/
A12: Northstate Rendering Anaerobic Digester (formerly Biogas Energy, now Republic Services) | B12: OPERATIONAL | C12: North State Rendering | D12: Butte | E12: CA | F12: 2015 | G12: North State Rendering; Biogas Energy, Inc. | H12: Biogas-to-CNG upgrading produces biomethane that is then compressed and distributed in a CNG fueling station to fuel North State Rendering's truck fleet, which is being converted to duel-fuel CNG/diesel; biomethane is pipeline-quality and can also be injected into the pipeline for sale to other customers (awaiting approval); some biogas pre-upgrading used for combined heat and power generator to produce 100% of the electricity used on site as well as heat to operate the plant. On site fueling facility for vehicles. Update - March 2023 California Energy Commission report has lots of details.- ex. Use of the biogas: • 120-150 standard cubic feet per minute to combined heat and power generator unit to generate 500kW electricity & heat for digesters • 150 standard cubic feet per minute to CNG production to generate 750 DGE per day, or 273,864 DGE per year | J12: 100tpd | K12: Proprietary | L12: Post consumer food waste, FOG, agriculture waste, food processing waste | M12: Residential, commercial, food processors | O12: 108000 | P12: 35478 | Q12: BOTH | R12: Private | S12: 314122 | T12: Proprietary | X12: Unknown | Y12: Feb. 2017 http://www.chicoer.com/article/NA/20170219/NEWS/170219682 https://www.facebook.com/pg/LBGGroupPurchasing/photos/?tab=album&album_id=437696499616003 http://www.biogas-energy.com/site/index.html https://www.landiainc.com/case-studies/north-state-rendering-california https://www.wastetodaymagazine.com/news/republic-services-acquires-anaerobic-digestion-faciloity-california/ https://www.energy.ca.gov/sites/default/files/2023-03/CEC-600-2023-007.pdf
A13: Rialto Bioenergy Facility | B13: OPERATIONAL | C13: Rialto Bioenergy Facility, LLC | D13: San Bernardino | E13: CA | F13: 43435 | G13: Anaergia | H13: Project to begin production in 2020. 700 tpd of food waste and 300 tpd of biosolids. Using Anaergia’s advanced anaerobic digestion technology to extract energy from the organic material, this facility will produce the equivalent of 13 megawatts of clean energy per year. The net carbon dioxide emissions reduction will be approximately 220,000 metric tons annually, which is the equivalent of taking 47,500 cars off the road. Anaergia is building the RBF in collaboration with Waste Management, Republic Services, Southern California Edison, Anaheim Public Utility, Southwest Gas Utility, City of Rialto, the Sanitation Bureau of the City of Los Angeles, and the Sanitation Districts of Los Angeles County, and of Orange County. The RBF is co-funded by the California Energy Commission, U.S. Department of Energy, CalRecycle, State of California and significant private investment. Contact says up to 2.88 MMSCFD upgraded gas injected. Average of 2.02 MMSCFD with onsite power generation. Assuming 2MM SCFD in calculations Pipeline Injection of RNG and onsite power generation for export | I13: Wet Continuously Mixed Anaerobic Digester | J13: 300000 tons per year | K13: 1080 | L13: Food Waste and Biosolids | M13: Waste Management, Republic Services, City of Rialto, Sanitation Districts of LA and Orange Counties | N13: 4.9 MMSCFD | O13: 2000000 | P13: =O13*(0.001*365*0.9) -> 657000 | Q13: PIPELINE (For vehicle/other) | R13: No | S13: =P13/0.112194 -> 5855928.1 | T13: 9.05 Million GGE/year | U13: Up to 4.6 MW | V13: 220,000 MT | X13: Unknown | Y13: https://www.anaergia.com/construction-begins-at-north-america-s-largest-organic-waste-to-energy-facility-anaergia-s-rialto-bioenergy-facility https://www.prnewswire.com/news-releases/first-state-investments-acquires-stake-in-anaergia-services-rialto-bioenergy-facility-301036763.html https://www.kpvi.com/news/national_news/renewable-natural-gas-produced-by-anaergia-from-diverted-landfill-waste-now-flowing-through-socalgas-system/article_569a4bfc-6c96-53d5-a011-ded34bfc2709.html
A14: Archer Daniels Midland corn processing facility | B14: OPERATIONAL | C14: Archer Daniels Midland | D14: Macon | E14: IL | F14: 42856 | G14: Archer Daniels Midland/Ameren Illinois | H14: Renewable natural gas, produced as a byproduct at ADM’s corn processing facility in Decatur, will be distributed by Ameren Illinois into the nation’s natural gas infrastructure. When construction of the project is complete, ADM will purify this methane into pipeline quality natural gas and transport it to an Ameren Illinois’ gas pipeline. Ameren Illinois will then distribute the gas into the interstate pipeline system where it will be available for use as a clean, affordable transportation fuel. ADM will benefit from capitalizing on environmental credits. | L14: Waste from corn processing | M14: Archer Daniels Midland | O14: =P14/(0.001*365*0.9) -> 1155290.7 | P14: 379513 | Q14: PIPELINE (For vehicle/other) | R14: No | S14: Proprietary | T14: Proprietary | X14: Unknown | Y14: https://www.adm.com/news/news-releases/adm-announces-innovative-project-to-provide-renewable-natural-gas http://biomassmagazine.com/articles/14135/biogas-advances-in-the-us http://www.4-traders.com/ARCHER-DANIELS-MIDLAND-CO-11533/news/Archer-Daniels-Midland-ADM-Ameren-partnering-to-provide-renewable-natural-gas-23525746/ http://herald-review.com/business/energy/adm-ameren-partnering-to-provide-renewable-natural-gas/article_8f13c92f-d224-5279-a2a2-99b4de1a2f0f.html
A15: BioEnergy Devco Jessup | B15: OPERATIONAL | C15: BioEnergy Devco | D15: Howard | E15: MD | F15: Q3 2022 | G15: BioEnergy Devco | H15: 110,000 ton per year facility located at the Maryland Food Center, a wholesale hub in Jessup, MD. System to go into commissioning Q4 2021, RNG production expected Q2 2022. | I15: BTS Biogas CSTR and membrane separation upgrading | J15: 110,000 tons per year | K15: 300 (based on 110,000 TPY) | L15: Food waste from wholesale market | M15: Maryland Food Center Authority | N15: =O15/0.6 -> 1582952.8 | O15: =P15/(0.001*365*0.9) -> 949771.69 | P15: 312000 | Q15: PIPELINE (For vehicle/other) | R15: Unknown | S15: =P15/0.112194 -> 2780897.4 | X15: Pending | Y15: https://www.wastedive.com/news/bioenergy-devco-newlight-partners-anaerobic-digesters/560495/ https://www.bioenergy-news.com/news/bts-biogas-bioenergy-devco-join-forces-on-us-ad-projects/ https://bioenergydevco.com/gov-hogan-joins-state-officials-at-ribbon-cutting-for-bioenergy-devcos-anaerobic-digester/ https://bioenergydevco.com/maryland-bioenergy-center/
A16: NW Natural/Tyson Foods RNG, Lexington NE | B16: OPERATIONAL | C16: NW Natural | D16: Dawson | E16: NE | F16: Construction began Q1 2021 | G16: NW Natural , BioCarbN, Cross River Infrastructure Partners | H16: The first of four potential projects under the NW Natural/Tyson joint venture will be in Lexington, Neb., next to a Tyson Fresh Meats beef packaging plant and will use anaerobic digester technology to convert the plant's animal waste and other byproducts into RNG, which will be processed to pipeline quality specifications. The RNG will be injected into Black Hills Energy's local distribution system, and the associated renewable thermal certificates will be used to meet targets under Oregon Senate Bill 98, enacted in 2019, which supports renewable energy procurement and investment by natural gas utilities. | L16: Animal waste, wastewater, food processing by products | M16: Tyson plant | N16: =O16/0.6 -> 963977.68 | O16: =P16/(0.001*365*0.9) -> 578386.61 | P16: 190000 | Q16: PIPELINE (For vehicle/other) | S16: =P16/0.112194 -> 1693495.2 | Y16: https://www.newsdata.com/clearing_up/courts_and_commissions/nw-natural-proposes-rng-project-in-nebraska-for-tyson-foods/article_d2afec2e-520a-11eb-9ac3-5f99aa0fc0d8.html https://www.naturalgasintel.com/nw-natural-taking-partners-for-more-u-s-rng-production/ https://www.biocarbn.com/wp-content/uploads/2021/01/NW-Natural-and-BioCarbN-Form-Innovative-Renewable-Natural-Gas-Partnership-with-Tyson-Foods-2021.pdf
A17: Central Ohio BioEnergy (Equilibrium Capital) | B17: OPERATIONAL | C17: Equilibrium Capital | D17: Franklin | E17: OH | F17: 2010 | G17: quasar energy group; Solid Waste Authority of Central Ohio (SWACO); Kurtz Bros., Inc. | H17: Processes biosolids from the City of Columbus to generate electricity and CNG for an on-site fueling station; also uses regional food waste and FOG (fats, oil and grease). According to presentation, 3600 GGE/day | I17: Complete Mix? | J17: 90,000 tons/yr. | L17: Food waste, FOG and manure from farms | M17: City of Columbus | N17: =O17/0.6 -> 747960 | O17: =P17/(0.001*365*0.9) -> 448776 | P17: =S17*0.112194 -> 147422.92 | Q17: BOTH | R17: Public | S17: =3600*365 -> 1314000 | U17: 8,760 MWh/yr. | X17: Yes | Y17: https://www.bioohio.com/item/quasar-energy-group-llc-central-ohio-bioenergy/ https://www.americanbiogascouncil.org/projectProfiles/columbus_oh.pdf https://energy-vision.org/case-studies/columbus-bioenergy/ https://ideas.uncc.edu/sites/ideas.uncc.edu/files/media/mel-kurtz-bioenergy-symposium-for-distribution-0.pdf
A18: Zanesville Energy (Quasar) | B18: OPERATIONAL | C18: Quasar | D18: Muskingum | E18: OH | F18: 2010 | G18: quasar energy group, Ohio State University | H18: Generates on-site electricity, heat and RNG through both liquid and solid state anaerobic digestion; on-site CNG fueling station. Feedstock includes food waste, FOG and biosolids. Centralized/regional facility | I18: Complete Mix | J18: 35000 tons/year | L18: Food waste, FOG, biosolids | N18: =O18/0.6 -> 336581.67 | O18: 201949 | P18: 66340 | Q18: BOTH | R18: Private | S18: 657000 | U18: 8760 MWh year | V18: 4623 (methane) | X18: Yes | Y18: https://www.bioohio.com/item/quasar-energy-group-llc-zanesville-energy/ http://www.greenenergyohio.org/page.cfm?pageID=2949 http://quasareg.com/New/locations/
A19: Seaboard Foods/High Plains Bioenergy | B19: OPERATIONAL | C19: High Plains Bioenergy | D19: Texas | E19: OK | F19: 42948 | G19: High Plains Bioenergy | H19: High Plains Bioenergy produces biogas from the Seaboard Foods' waste water system, which is then scrubbed to pipeline quality using a pressure swing adsorption system and delivered to the interstate pipeline network to be used by the public as a renewable energy source. According to company website, there is a CNG filling station located across the road from the plant, which provides fuel to some of the company's 180 CNG vehicles, is also open to public. | I19: Lagoons | L19: Waste water from pork processing plant | M19: Seaboard Foods | N19: =O19/0.6 -> 1111111.1 | O19: =P19/(0.001*365*0.9) -> 666666.67 | P19: =600*365 -> 219000 | Q19: BOTH | R19: Public | S19: =P19/0.112194 -> 1951976 | U19: None | X19: Yes | Y19: https://highplainsbioenergy.com/Biogas.aspx https://www.bloomberg.com/profiles/companies/0537045D:US-high-plains-bioenergy-llc https://seaboardfoods.com/About/Pages/Facts_Figures_Bioenergy.aspx https://www.wattagnet.com/articles/32044-high-plains-bioenergy-starts-operations-of-expanded-biogas-recovery-plant
A20: Wasatch Resource Recovery | B20: OPERATIONAL | C20: Through PPP co-owned by ALPRO Energy and Water and South Davis Sewer District | D20: Davis | E20: UT | F20: 2018 | G20: Wasatch Resource Recovery | H20: WRR is a public-private partnership between ALPRO Energy & Water (ALPRO) and the South Davis Sewer District (SDSD). The facility will be using state-of-the-art equipment, much of which is supplied by GE-Monsal, a strategic partner in the project. The WRR is sited right next to the existing South Plant wastewater treatment facility and will use much of the existing plants’ facilities to support the project. In the first phase of construction, two 2.5-million gallon tanks will be built to be used at the WRR facility for digestion. In this public-private partnership, the SDSD will operate the WRR facility and ALPRO will manage the feed stock and the energy and fertilizer offtakes. Original project plan involved 4 digesters, a row of greenhouses, a boiler building, a chemical & dewatering building, and a depackaging facility.Two of four planned digesters are in place, units three and four are several years down the road as of 2021. Planned greenhouses for site have been deferred. | I20: Wet, complete mix | J20: 500-700 tpd | K20: 1400 tpd | L20: Prepared and packaged foods, fruits and vegetables, meat and dairy, fats, oils, grease, expired beverages, screened curbside wastes and liquid organics from major food processors | M20: Local supermarkets, restaurants, food processors. Bulk of waste will be from manufacturing. Delivered by local haulers. 2021, started accepting limited amounts of residential waste via dropoff, will be doing a pilot for curbside pick up with local hauler. | N20: =O20/0.6 -> 5000000 | O20: 3000000 | P20: =O20*(0.001*365*0.9) -> 985500 | Q20: PIPELINE (For vehicle/other) | R20: No | S20: =P20/0.112194 -> 8783892.2 | X20: Unknown | Y20: https://www.wastetodaymagazine.com/article/utah-wasatch-resource-recovery-chooses-ge/ https://www.boisestatepublicradio.org/post/digesting-thanksgiving-leftovers-one-utah-facility-turning-food-waste-energy#stream/0 https://www.waste360.com/business/wasatch-resource-recovery-s-olsen-bowerman-finds-hope-waste http://wasatchresourcerecovery.com/ https://www.ksl.com/article/46680173/how-this-north-salt-lake-plant-will-turn-table-scraps-into-natural-gas-for-europe https://www.facebook.com/WasatchResourceRecovery/
A21: Impact Bioenergy Vashon Island | B21: OPERATIONAL | C21: Impact Bioenergy | D21: King | E21: WA | F21: 43556 | G21: Impact Bioenergy | H21: Project processes waste from a tofu factory. Small scale project, as of July 2020 providing fuel for single vehicle. | I21: CSTR? | J21: 8000 lbs/day | K21: 4 | L21: Okara and whey | M21: Island Spring Organics | N21: 21500 | O21: =N21*0.6 -> 12900 | P21: =O21*(0.001*365*0.9) -> 4237.65 | Q21: BOTH | R21: Private | S21: =P21/0.112194 -> 37770.736 | T21: =365*125 -> 45625 | Y21: https://www.vashonbeachcomber.com/news/island-anaerobic-digester-unveiled/ https://www.vashonbeachcomber.com/news/island-based-impact-bioenergy-fuels-up-car-with-food-waste/ https://impactbioenergy.com/wp-content/uploads/2019/06/Vashon-Bioenergy-Farm-Island-Spring-Organics-NAUTILUS-overview.pdf
A22: UNDER CONSTRUCTION AS OF 12/31/2023
A23: [Divert Project] | B23: UNDER CONSTRUCTION | C23: Divert, Inc. | D23: Stanislaus | E23: CA | F23: early 2024 | G23: Divert, Inc. | H23: October 2022 announcement of offtake agreement with bp. April 2023 announcment of greoundbreaking of Turlock facility, with estimated completion early 2024. Reached interconnection agreement with PG&E for RNG to enter PG&E’s on-site transmission line, replacing fossil gas with a carbon negative renewable fuel to supply homes and businesses. | J23: 100,000 tons per year | K23: 274 tons of wasted food per day (based on 100,000 TPY) | V23: 23,000 metric tons of carbon dioxide a year | Y23: https://www.bloomberg.com/press-releases/2022-10-06/divert-inc-announces-renewable-natural-gas-offtake-agreement-with-bp https://www.wastedive.com/news/divert-bp-offtake-agreement-rng-food-digestion/633564/ https://finance.yahoo.com/news/divert-inc-breaks-ground-wasted-165900807.html?guce_referrer=aHR0cHM6Ly93d3cucm5nY29hbGl0aW9uLmNvbS8&guce_referrer_sig=AQAAAD7TMJ2aWb0ydq0QlOzb71OH3fSuGWU-xuuIvhXOTEf5RbXM0fC3uTesPB9jGuETf1HRy97-mp-5glst0OjEO7ZRDG9GK6v9MaiGVTpANY5vgHQJbz9lcjl2k58w8H2k0kpYR04T9Y_ymvWjsNxDJ9URuBpcvMuYxkA9McwbAn89&guccounter=2 https://www.turlockjournal.com/news/local/new-turlock-facility-looks-to-tackle-nations-food-waste-problem/
A24: Green Era Urban Farming Campus, Chicago | B24: UNDER CONSTRUCTION | C24: Green Era Sustainability? | D24: Cook | E24: IL | F24: Construction to Start Q3 2020 | G24: Green Era; Greater Auburn-Gresham Development Corp; BP? | H24: "Green Era is developing a renewable energy facility in South Chicago. The project will be located on a vacant brownfield site in an area with urgent need for cleanup and economic development. Using anaerobic digestion, Green Era will divert inedible food waste from landfills to produce clean, renewable energy and nutrient-rich soil, which will be used as a critically needed input in the expansion of fresh local food production. The end result will have positive social and environmental impacts, while also creating jobs, sustainable neighborhoods and healthier lifestyles." Project will produce compost for an urban farming component that will grow ~26,000 lbs of food annually; area is considered food desert. | J24: 85,000 tons per year | K24: 230 (based on 85,000 TPY) | L24: "Recycled food and waste" | P24: 112194 | Q24: UNKNOWN | T24: 1000000 | V24: 42500 | Y24: https://www.bioenergy-news.com/news/green-era-bp-partner-to-sell-rng-produced-via-chicago-ad-project/ https://www.waste360.com/food-waste/chicago-green-campus-plans-turn-food-waste-energy-and-grow-more-food https://www.greenerachicago.com/ https://www.wastedive.com/news/chicago-green-era-urban-farm-anaerobic-digester/583764/ http://www.gagdc.org/news/3740 https://www.renewableenergymagazine.com/biogas/urban-farming-campus-on-chicago-s-south-20200824
A25: Linden Renewable Energy (LRE) Project | B25: UNDER CONSTRUCTION | C25: RNG Energy Solutions | D25: Union | E25: NJ | F25: Construction began December 2023; target completion date in Q1 2026 | G25: RNG Energy Solutions in partnership with SJI and Captona | H25: The LRE Project will accept a wide range of feedstock, including food waste from industrial, commercial, and institutional entities, as well as grease waste from restaurants and other food service establishments. It will convert up to 1,475 tons of waste to produce up to 3,783 MMBtu/day of RNG— the energy equivalent value of 30,200 gallons of gasoline per day. The LRE Project includes development and construction of multiple off-site food waste pre-processing and depackaging operations in New York City, New York State and New Jersey. Work was slated to begin in December 2023, with a target completion date in Q1 2026. The LRE Project earlier received approval from the NJ Economic Development Authority for $214 million in Industrial Development Revenue Bonds. | K25: 1475 | L25: food waste (SSO) and fats, oils, grease (FOG) | M25: industrial, commercial, and institutional entities, as well as restaurants and other food service establishments | P25: 1380795 | Q25: PIPELINE (For vehicle/other) | S25: 11023000 | Y25: https://www.rngenergysolutions.com https://njbiz.com/major-food-waste-to-renewable-natural-gas-facility-set-for-linden/ https://www.globenewswire.com/news-release/2023/12/20/2799284/0/en/SJI-and-Captona-Announce-Construction-of-one-of-the-Largest-Food-Waste-to-RNG-Facilities-in-the-US.html https://ucnj.org/wp-content/uploads/2020/07/UCUA-Linden-Renewable-Energy-LLC-Plan-Amendment.pdf https://www.mycentraljersey.com/story/news/local/union-county/2022/02/15/renewable-energy-plant-linden-ready-construction/6784189001/
A26: American Organic Energy | B26: UNDER CONSTRUCTION | C26: American Organic Energy | D26: Suffolk | E26: NY | F26: Groundbreaking April 2022. | H26: American Organic Energy is a project by the owners of Long Island Compost. Food waste from Long Island will be collected, separated, pre-processed, broken down and ultimately transformed into electrical energy, renewable natural gas, fertilizer and nutrient-rich water. | I26: CSTR | J26: 180,000 tons per year | K26: ~500 | L26: Food waste, green waste, FOG | N26: =O26/0.6 -> 942916.4 | O26: =P26/(0.001*365*0.9) -> 565749.84 | P26: =S26*0.112194 -> 185848.82 | Q26: PIPELINE (For vehicle/other) | R26: Unknown | S26: =1900000/1.147 -> 1656495.2 | U26: 2MW | Y26: https://www.wastetodaymagazine.com/article/american-organic-energy-anaerobic-digester-yaphank-new-york/ https://libn.com/2022/04/11/anaerobic-digester-facility-coming-to-yaphank/ https://www.newsday.com/long-island/politics/compost-energy-lipa-renewable-natural-gas-xxkbg6ea
A27: Synthica St. Bernard | B27: UNDER CONSTRUCTION | C27: Hamilton RNG, a JV of UGI Energy Services and Synthica Energy. | D27: Hamilton | E27: OH | F27: Groundbreaking July 2023, commercial operation Q4 2024 | G27: Hamilton RNG | H27: The digester is expected to be completed in late calendar 2024 and will process approximately 190,000 annual tons of food waste from nearby food manufacturers in an anaerobic digester. The project is expected to generate approximately 250,000 MMBTUs (million BTUs) of pipeline-quality RNG each year that will be injected into a local natural gas pipeline on the regional distribution system. Digester will be complete mix, upgrading will be water wash, no vendors selected yet. Gas most likely destined for transportation markets | I27: CSTR | J27: ~190,000 tons annually | K27: ~500 TPD | L27: Food from nearby manufacturers | M27: Nearby manufacturers | N27: =O27/0.6 -> 1268391.7 | O27: =P27/(0.001*365*0.9) -> 761035.01 | P27: 250000 | Q27: PIPELINE (For vehicle/other) | S27: =P27/0.112194 -> 2228283.2 | X27: Pendiong | Y27: https://www.businesswire.com/news/home/20210804006006/en/UGI-and-Synthica-Energy-Partner-to-Develop-Renewable-Natural-Gas https://synthica.com/synthica-energy-st-bernard/ https://biomassmagazine.com/articles/20260/ugi-energy-services-synthica-energy-break-ground-on-rng-project
A28: Port of Morrow, Boardman, Oregon | B28: UNDER CONSTRUCTION | C28: Port of Morrow | D28: Morrow | E28: OR | F28: Digster construction starting Fall 2021; full project operational 2024. | G28: Port of Morrow; partners being identified. | H28: As of September 2021, Port is going ahead with 3 anaerobic digester project, will add gas upgrading later. Hoping to have all in place by 2024. Digester would use process water from food processing businesses at port to produce renewable natural gas, organic fertilizer and clean water; primary feedstocks being proposed consist of produce waste including onion and potato waste solids, cheese, FOG. Anticipate producing ~1750 MMBTU/day. November 2022, they are begining construction on three lagoon digesters, which are feasible in their climate because they will be getting warm process water from the food manufacturers. Once one of them is complete, they will test gas volume and quantity, then work on identifying upgrading parter. Still foresee all operational by late 2024. | I28: Covered lagoons | J28: ?? | K28: ?? | L28: Leftover potato peelings and onion skins, cheese, FOG from local food processors. | M28: Local food processors, local dairy farm | N28: =O28/0.6 -> 3240740.7 | O28: =P28/(0.001*365*0.9) -> 1944444.4 | P28: =1750*365 -> 638750 | Q28: PIPELINE (For vehicle/other) | S28: =P28/0.112194 -> 5693263.5 | T28: 7665000 | U28: N/A | V28: 8400 | X28: Pendiong | Y28: http://biomassmagazine.com/articles/11178/novus-pacific-to-build-full-scale-oregon-renewable-energy-plant http://www.novus-energy.com/project-highlights/novus-pacific-llc-at-port-of-morrow/ https://www.rd.usda.gov/files/Novus_Pacific_EA_Supplemental.pdf
A29: Rhode Island Bioenergy Facility (formerly Orbit Energy) | B29: UNDER CONSTRUCTION | C29: Anaergia, which bought former bought former Orbit Energy AD electricity facility summer 2021 | D29: Providence | E29: RI | F29: Construction underway in 2023, expected completion later in 2023 | G29: Anaergia | H29: Anaergia recently acquired the facility, which is currently producing renewable electricity, and is upgrading the plant using its BUG biogas upgrading system to produce RNG. The facility will divert over 100,000 tons per year of food waste from landfills and convert the waste to renewable fuel. RIBF is expected to produce over 300,000 MMBtu of carbon-negative RNG starting later in 2023, which will make it New England’s largest anaerobic digestion-to-RNG facility. In addition, the plant will recycle the nutrient-rich solid residual left over after anaerobic digestion to enrich New England soils and reduce the use of fossil fuel-derived fertilizers. | I29: CSTR | J29: 100,000 TPY | K29: ~270 | L29: Food waste from area supermarkets, schools and food manufacturers | M29: Area businesses and institutions | N29: =O29/0.6 -> 1623541.3 | O29: =P29/(0.001*365*0.9) -> 974124.81 | P29: 320000 | Q29: PIPELINE (For vehicle/other) | V29: 41,000 metric tons of CO2e | Y29: https://www.wastetodaymagazine.com/article/anaergia-acquires-rhode-island-bioenergy-facility/ http://www.dem.ri.gov/programs/wastemanagement/facilities/OrbitEnergymonitoringplans.pdf https://www.wastedive.com/news/rhode-island-first-anaerobic-digester/539063/ https://www.businesswire.com/news/home/20230118005363/en/Canadian-Owned-Irving-Oil-Selects-Anaergia-Inc.-as-a-Supplier-of-Carbon-Negative-Renewable-Natural-Gas-for-its-Operations-Including-the-Saint-John-Refinery#:~:text=The%20RNG%2C%20which%20is%20made,are%20transformed%20into%20renewable%20fuel. https://www.wastedive.com/news/anaergia-earnings-rialto-bioenergy-los-angeles-organics/647305/ https://www.anaergia.com/the-40-million-ton-gold-mine/
A30: McCall Farms | B30: UNDER CONSTRUCTION | C30: McCall Farms | D30: Florence | E30: SC | F30: First RNG produced 2022 but expansion underway to double capacity | G30: GreenGasUSA and Guild Associates | H30: Cannery waste to pipeline RNGz. GreenGasUSA will be doubling the digester gas production capacity, as two lagoons will soon be operational at the site. Guild Associates will provide a second Molecular Gate™ CO2 removal Pressure Swing Adsorption (PSA) system for this expansion in addition to the equipment under construction currently. This project, with Duke University as an RNG consumer (95,000 MMBTUs), will convert biogas methane from agricultural waste into Renewable Natural Gas for injection into the natural gas pipeline. A Mercedes-Benz plant in SC has also signed a contract to buy RNG from the plant. RNG Coalition notes that ened uses will be transportation, thermal. | I30: Covered lagoons | Q30: PIPELINE (For vehicle/other) | V30: 184000 metric tons of CO2e | Y30: https://www.guildassociates.com/guild-associates-and-greengasusa-to-expand-mccall-farms-project/ https://www.today.duke.edu/2021/07/novel-renewable-natural-gas-partnership-will-move-duke-toward-carbon-neutrality https://greengasusa.com/greengasusa-announces-rng-project-from-food-and-agricultural-waste-in-sc/?ss_source=sscampaigns&ss_campaign_id=600de1a315b73f591e6ce748&ss_email_id=600e053508f3860a07fd67b4&ss_campaign_name=GreenGasUSA%20Announces%20RNG%20Project%20from%20Food%20and%20Agricultural%20Waste%20in%20SC&ss_campaign_sent_date=2021-01-24T23%3A39%3A51Z https://charlestonbusiness.com/news/manufacturing/82062/ https://www.wbtw.com/news/pee-dee/florence-county/south-carolina-companies-team-up-for-renewable-energy-project-at-mccall-farms/ https://agriculture.sc.gov/greengasusa-mercedes-benz-mccall-farms-expand-carbon-friendly-commitment-in-sc/
A31: 3 Rivers Jack Daniel's | B31: UNDER CONSTRUCTION | C31: 3 Rivers Energy Partners | D31: Moore | E31: TN | F31: Construction underway as of June 2023, with May 2024 estimated completion | G31: 3 Rivers Energy, BIOFerm | H31: The facility will utilize spent distiller’s grains from the Jack Daniel Distillery to produce renewable natural gas (RNG) and a low-carbon natural fertilizer able to support tens of thousands of acres of farmland. Will supply pipeline; end-use unclear as of Sep 2023. The new process is also expected to reduce the distillery’s energy use by around 30%. | L31: Distillery mash from Jack Daniel's whiskey production. | N31: =O31/0.6 -> 5580923.4 | O31: =P31/(0.001*365*0.9) -> 3348554 | P31: 1100000 | Q31: PIPELINE (For vehicle/other) | Y31: https://www.globenewswire.com/news-release/2022/11/01/2545827/0/en/3-Rivers-Energy-Partners-Announces-Project-With-Jack-Daniel-s-to-Convert-Spent-Distillers-Grains-Into-Renewable-Natural-Gas-and-Natural-Commercial-Fertilizer.html https://www.tullahomanews.com/news/local/3-rivers-energy-partners-with-jack-for-renewable-energy/article_1ecb9102-b466-11ed-a565-b3bac3bb84e3.html https://www.biofermenergy.com/bioferm-selected-by-3-rivers-energy-partners-for-revolutionary-renewable-energy-project-near-the-jack-daniel-distillery/ https://captimes.com/news/business/jack-daniels-whiskey-waste-becomes-natural-gas-thanks-to-madison-firm/article_14e98d46-94cd-5b3b-9c39-9627cce37670.html
A32: Divert Longview | B32: UNDER CONSTRUCTION | C32: Divert, Inc. | D32: Cowlitz | E32: WA | F32: 45176 | G32: Divert, Inc. | H32: $100 million facility to bring in food waste from 650 WA and OR grocery stores. October 2022 announcement of offtake agreement with bp. Groundbreaking ceremony September 2023, estimated completion in 2024. RNG from food waste will be injected into a nearby Cascade Natural Gas pipeline. | J32: 100,000 tons per year | V32: 23,000 metric tons of greenhouse gas emissions annually | Y32: https://tdn.com/news/local/business/renewable-biogas-plant-planned-for-longview-could-be-first-of-its-kind-in-washington-state/article_95db7b23-cbe4-5a7e-8386-e99ecd0bb8e3.html http://www.divertinc.com/ https://www.bloomberg.com/press-releases/2022-10-06/divert-inc-announces-renewable-natural-gas-offtake-agreement-with-bp https://www.wastedive.com/news/divert-bp-offtake-agreement-rng-food-digestion/633564/ https://globalnews.ca/news/9945552/enbridge-divert-break-ground-renewable-fuel-facility-washington/ https://www.eastoregonian.com/news/agriculture/washington-plant-will-convert-food-waste-into-renewable-natural-gas/article_15c75f6a-5fd6-556f-aea1-bf1b678a1e62.html https://tdn.com/news/local/business/divert-biogas-biofuel-jobs-longview-mint-farm/article_96aa406c-3b78-11ee-bc09-efefe20fde3d.html
A33: CONFIRMED CANCELLED/SHUTDOWN AS OF 12/31/2023
A34: Colony Energy Partners Tulare LLC | B34: CANCELLED | D34: Tulare | E34: CA | G34: Colony Energy Partners, LLC | H34: Divert waste from California’s landfills in order to produce renewable biomethane, which will be fed directly into the natural gas grid via a SoCalGas transmission line adjacent to the property. The biomethane will also be supplied as a diesel alternative to San Joaquin Valley’s on-road truck market through a public access Bio-CNG fueling station located on the property. The facility will integrate combined heat and power (CHP) cogeneration modules, a portion of which can run on the biogas to generate electric and thermal energy for the facility. Any excess thermal energy will be exported to heat the adjacent City of Tulare Industrial Wastewater Treatment Plant’s digester. California Energy Commission awarded $5 million grant for this $25 million project | J34: 500 tons/day | L34: Dairy manure, food and agricultural processing residuals, restaurant and cafeteria food scraps, restaurant grease trap residuals, and organic municipal solid waste | N34: =O34/0.6 -> 2222222.2 | O34: =P34/(0.001*365*0.9) -> 1333333.3 | P34: 438000 | Q34: BOTH | S34: =P34/0.112194 -> 3903952.1 | U34: 1,200 kW | V34: 41,850 tons/yr. | Y34: http://www.colonyenergypartners.com/tulare-bio-gas/ http://biomassmagazine.com/articles/11418/california-energy-commission-awards-biogas-project-5-million http://www.sandiegouniontribune.com/news/sd-tm-0729-digester-20170719-story.html
A35: Mendota Advanced Bioenergy Beet Cooperative | B35: SHUT DOWN | D35: Fresno | E35: CA | G35: Mendota Advanced Bioenergy Beet Cooperative; Mendota Bioenergy, LLC; California Energy Commission | H35: A large system to produce electricity, CNG for pipeline/vehicle fuel, and ethanol production from beets. The demonstration plant came on line in December 2014 and will operate through the summer of 2015 when efforts will shift to the development, construction, and operation of Advanced Bioenergy Center—Mendota (ABC-M), the first of several California-based full-scale commercial 15-MGY integrated biorefineries. ABC-M is targeted for a late 2017 or early 2018 startup. | J35: 4,000 tons/day | L35: Beets | N35: =O35/0.6 -> 7333.3333 | O35: 4400 | P35: =O35*(0.001*365*0.9) -> 1445.4 | Q35: BOTH | S35: =P35/0.112194 -> 12883.042 | U35: 6.3 MW | Y35: https://www.arb.ca.gov/fuels/lcfs/workgroups/lcfssustain/tisher.pdf
A36: Sacramento Biodigester/Incline Clean Energy (formerly Clean World) | B36: SHUT DOWN; FUTURE POTENTIAL? | C36: Fueling station, Atlas ReFuel; digester and upgrading facility, Incline Clean Energy | D36: Sacramento | E36: CA | F36: December 2012 | G36: BioCNG; CleanWorld; Atlas Disposal | H36: Converts food waste from area food processing companies, restaurants and supermarkets into RNG, electricity and soil-amendment products; RNG fuels waste disposal vehicles, school buses and fleet vehicles throughout the Sacramento region via an on-site fueling station. Currently 100% of gas goes to vehicle fueling, in the future 85% will go to vehicle fueling and 15% to on-site electricity use. | I36: Thermophilic, three stage, complete mix | J36: 2016, 24,000 tons/yr.; Jan. 2017, running at between 60% and 100% capacity (100 tpd) | K36: 100 | L36: Food waste | M36: Atlas Disposal | N36: =O36/0.6 -> 145493.59 | O36: =P36/(0.001*365*0.9) -> 87296.153 | P36: =S36*0.112194 -> 28676.786 | Q36: VEHICLE FUEL | R36: Yes | S36: 255600 | T36: 657000 | U36: 3,170 kWh/yr., goes toward powering station, digester, upgrading | V36: 18,250 tons/yr. | X36: Yes | Y36: http://www.cleanworld.com/news/cleanworlds-sacramento-biodigester-named-international-bioenergy-project-of-the-year/ http://biocng.us/wp-content/uploads/2015/06/CleanWorld-Fact-Sheet-2015.pdf https://refuelenergypartners.com/
A37: Santa Rosa, CA FARMS to FUEL Project | B37: CANCELLED | D37: Sonoma | E37: CA | G37: BioStar Systems, LLC; Sonoma County Water Agency; Sonoma Country Transit | H37: Create pipeline quality gas for vehicle fuel; used to fuel Sonoma County Transit fleet, with excess sent to nearby fueling stations | I37: Thermophilic (50-55C) | J37: 75,000 gal/day dairy waste; 66,000 gal/day food waste | L37: Dairy and food waste | O37: 240,000 (148,000 SCFD used by Sonoma County Transit fleet) | P37: =2400008*(0.001*365*0.9) -> 788402.63 | Q37: PIPELINE | S37: =P37/0.112194 -> 7027137.2 | U37: 5.2 MWh | V37: 41,300 tons/year | X37: Unknown | Y37: http://www.northbaybusinessjournal.com/csp/mediapool/sites/NBBJ/IndustryNews/story.csp?cid=4179855&sid=778&fid=181 http://www.sonoma-county.org/prmd/b-c/pcbza/act_20110526.pdf
A38: UC Davis Renewable Energy Anaerobic Digester (READ) | B38: PROJECT SUSPENDED | C38: UC Davis | D38: Yolo | E38: CA | F38: 2014 | G38: UC Davis; CleanWorld | H38: 3 anaerobic reactor tanks. Thermophilic. Total volume of 450,000 gallons. 4 microturbines. Currently produces heat and electricity; additional capability may be added to purify and compress the biogas for producing compressed or liquefied fuels; also produces ethanol from food waste such as sugar beets | I38: Thermophilic, three stage, complete mix | J38: 20000 tons/yr. | K38: 50 | L38: Food waste from dining halls, commercial restaurants, retail produce waste. food scraps from commercial food supply companies, mouse bedding from lab, horse manure | M38: UC Davis dining halls, local food processors | N38: 222000 | O38: =N38*0.6 -> 133200 | P38: =O38*(0.001*365*0.9) -> 43756.2 | Q38: OTHER | S38: =P38/0.112194 -> 390004.81 | T38: N/A | U38: 925 kW | V38: 13,500 tons | X38: N/A | Y38: http://www.energy.ca.gov/2017publications/CEC-500-2017-021/CEC-500-2017-021.pdf https://www.ucdavis.edu/news/biodigester-turns-campus-waste-campus-energy https://americanbiogascouncil.org/projectProfiles/ucdavis_to_print.pdf
A39: Heartland Biogas | B39: SHUT DOWN | D39: Weld | E39: CO | G39: Heartland Renewable Energy LLC, EDF Renewable Energy | H39: 6 Bio Reactors (Tanks and Lagoons) produce the biogas which is then passed through a Sulfur Scrubber and a DeOxo unit so that it can be injected into a pipeline and sent to the Sacramento Municipal Utility District (SMUD) | L39: Organic Feedstock and dairy cow manure | M39: A1 organics | N39: =O39/0.6 -> 8000 | O39: 4800 | P39: =O39*0.001*365*0.9 -> 1576.8 | Q39: PIPELINE | S39: =P39/0.112194 -> 14054.227 | Y39: http://www.greeleytribune.com/news/local/heartland-biogas-says-shut-down-ongoing-amid-court-battle-with-weld-county/ http://www.boulderweekly.com/boulderganic/requiem-for-a-digester/ https://www.facebook.com/greeleytribune/posts/10155535036633077 http://www.rewmag.com/article/heartland-biogas-edf-renewable-partnership/ http://bizwest.com/a1-organics-heartland-biogas-complete-3-5m-facility-expansion/ http://www.npr.org/sections/thesalt/2016/04/05/472673127/how-colorado-is-turning-food-waste-into-electricity
A40: BioEnergyDevCo Principio Business Park | B40: CANCELLED; FUTURE POTENTIAL? | C40: BioEnergy Dev Co | D40: Cecil | E40: MD | G40: BioenergyDevCo? | H40: Taking ag waste from area poultry processors and food waste from area producers. Project is going in at business park, initial plan is to provide RNG for campus fleet, looking at pipeline injection later | J40: 70-100,000 tons mixed food and ag waste annually | L40: Mixed food and ag (poultry farmers) | Q40: BOTH | Y40: https://www.waste360.com/anaerobic-digestion/bioenergy-devco-advances-expansion-plans https://www.prnewswire.com/news-releases/bioenergy-devco-to-purchase-perdue-agrirecycle-organic-soil-composting-facility-in-delaware-300962924.html
A41: Michigan State University South Campus Anaerobic Digester | B41: SHUT DOWN; FUTURE POTENTIAL? | C41: MSU | D41: Ingham | E41: MI | G41: Michigan State University | H41: Biogas is used to power a 400 kW combined heat and power unit. Upgrading biogas to CNG for the campus vehicle fleet is a future consideration. Gases cleaned using a series of filters (water vapor via chiller, H2S via iron sponge, siloxanes and volatile organic carbons via carbon filter) prior to going to microturbines. CHP | I41: Single tank complete mix, 25 day retention time | J41: 66 tpd | L41: Manure, Food processing waste, FOG, Cafeteria food waste | M41: Michigan State University and local food processors/service | N41: 177000 | O41: =N41*0.6 -> 106200 | P41: =O41*0.001*365*0.9 -> 34886.7 | Q41: VEHICLE FUEL | U41: 2600 MWh/yr. via 380 kW CHP unit | Y41: https://www.egr.msu.edu/bae/adrec/feature/south-campus-anaerobic-digester http://ipf.msu.edu/green/practices/anaerobic-digester.html
A42: Collinwood BioEnergy (Quasar) | B42: CANCELLED; FUTURE POTENTIAL? | D42: Cuyahoga | E42: OH | F42: 2012 | G42: quasar energy group; Forest City Enterprises | H42: Digests biosolids, FOG, and food waste to generate electricity and produce CNG fuel | J42: 75,000 tons/yr. | L42: Food waste, biosolids, and FOG | O42: =P42/(0.001*365*0.9) -> 381459.6 | P42: =S42*0.112194 -> 125309.48 | Q42: VEHICLE FUEL | S42: =3400*0.9*365 -> 1116900 | U42: 1.3 MW/day | Y42: https://www.bioohio.com/item/quasar-energy-group-llc-collinwood-bioenergy/ http://www.crainscleveland.com/article/20130304/NORTECH13/303049980/quasar-energy-group-collinwood-bioenergy
A43: Lime Lakes Energy | B43: CANCELLED | D43: Summit | E43: OH | F43: 2012 | G43: Lime Lakes Energy, LLC; quasar energy group; PPG Industries, Inc. | H43: Codigests food waste, FOG and sewage sludge to produce electricity. It is anticipated that the lime lakes reclamation activities to be completed in half of the original schedule, by the end of 2016. | I43: 42000 | J43: 17,500 tons/yr. | N43: =O43/(0.001*365*0.9) -> 373980 | O43: =T43*0.112194 -> 122852.43 | Q43: OTHER | T43: 1095000 | V43: 810kW | Y43: https://www.bioohio.com/item/quasar-energy-group-llc-lime-lakes-energy/ http://quasareg.com/New/wp-content/uploads/2016/10/Lime-Lakes-2016.pdf
A44: Wilsonville food scrap digester (Sustainable Organics Recycling Technology, SORT) | B44: CANCELLED | D44: Washington | E44: OR | F44: 2016 | G44: Sustainable Organics Recycling Technology (SORT) Bioenergy | H44: SORT Bioenergy proposed to build this plant near a Republic Services' garbage transfer center. It will collect waste from the center and produce methane to power some of Republic Services' truck fleet. | J44: 50,000 to 70,000 tons/yr. | L44: Commercial food scraps | M44: Republic Services | Q44: VEHICLE FUEL | Y44: http://www.sortbioenergy.com/ https://www.oregonmetro.gov/sites/default/files/2017/04/18/SORT_F-173-17_staffrpt.pdf
A45: Point Breeze Renewable Energy | B45: CANCELLED | E45: PA | G45: RNG Energy Solutions, Philadelphia Energy Solutions | H45: RNG Energy will develop and construct the $120 million anaerobic digester facility to produce renewable natural gas, which will be injected into the Interstate Pipeline and sold as a transportation fuel for bus and truck fleets. Permitting and construction of the project is estimated to take two to three years. Organic waste consisting of grocery, restaurant, and food processing wastes will be processed at offsite locations and delivered in fully enclosed tanker trucks to the PBRE facility. The facility will be designed to process up to 1,100 tons per day of diverted organic waste in eight bioreactors visually similar to the surrounding refinery tankage. The PBRE facility will be one of the largest carbon reduction, renewable and sustainable resource projects constructed in Pennsylvania. The City of Philadelphia and the broader metropolitan region will be able to manage their organic waste streams by collecting and sending their processed organic material to the PBRE facility, thereby avoiding disposal in landfills and assisting the City in achieving its sustainability goals. | I45: Complete mix | K45: 1100 tpd | L45: Food waste from restaurants, grocery stores, food processing. Food waste will be slurried at separate sites and brought to digesters. | M45: Various | N45: =O45/0.6 -> 5580923.4 | O45: =P45/(0.001*365*0.9) -> 3348554 | P45: 1100000 | Q45: VEHICLE FUEL | R45: No | T45: 9804446 | U45: N/A | V45: ~55,000 MT | X45: D5 | Y45: https://www.businessinsider.com/philadelphia-refiner-machine-turns-food-scraps-into-natural-gas-2018-8 https://www.inquirer.com/business/energy/philly-refinery-pes-renewable-gas-plans-scrapped-20200211.html#:~:text=Point%20Breeze%20Renewable%20Energy%2C%20which,renewable%20natural%20gas%2C%20or%20RNG. http://pes-companies.com/newsroom/press-release/rng-energy-solutions-and-philadelphia-energy-solutions-partner-to-form-point-breeze-renewable-energy/ http://www2.philly.com/philly/business/energy/philadelphia-energy-solutions-food-waste-digester-methane-gas-fuel-20180828.html https://stateimpact.npr.org/pennsylvania/2020/05/07/planned-120m-renewable-energy-plant-at-south-philly-refinery-site-is-not-dead-2/
A46: Divert Integrated Diversion and Energy Facility (at Mint Farm Industrial Park) | B46: CANCELLED | C46: Divert Inc. | D46: Cowlitz | E46: WA | Y46: https://globalnews.ca/news/9945552/enbridge-divert-break-ground-renewable-fuel-facility-washington/ https://www.eastoregonian.com/news/agriculture/washington-plant-will-convert-food-waste-into-renewable-natural-gas/article_15c75f6a-5fd6-556f-aea1-bf1b678a1e62.html https://tdn.com/news/local/business/divert-biogas-biofuel-jobs-longview-mint-farm/article_96aa406c-3b78-11ee-bc09-efefe20fde3d.html https://www.thestar.com/business/enbridge-divert-break-ground-on-renewable-fuel-facility-in-washington/article_44c615ee-219c-59b3-b5bb-c3546fd8049d.html
A47: Yahara Hill Food Waste Digester | B47: CANCELLED; FUTURE POTENTIAL? | D47: Dane | E47: WI | F47: Sometime in the 2030s. | H47: April 2021, Madison WI is looking to cut costs on its golf courses, and also has a landfill capacity problem. Closing the Yahara Hills golf course, which is located across from the landfill with its existing injection point, and building a digester there is one of the suggestions | Q47: UNKNOWN | Y47: https://madison.com/ct/news/local/govt-and-politics/report-food-scraps-digester-project-could-be-feasible-at-yahara-hills-golf-course/article_15bf2574-450b-5d52-9b92-4cfc12bfa4fc.html
A48: Synthica Dayton | B48: CANCELLED | E48: OH | F48: Groundbreaking targeted for late 2023, operations to begin in Sapring 2025 | G48: Synthica | H48: Planned to accept approx. 150,000 tons of feedstock. Depackaging System for Plastic, Paper and Metal Packaged Food/Beverage Waste | I48: CSTR | J48: 150,000 TPY | K48: ~410TPD | L48: "Food-derived feedstock" | Y48: https://synthica.com/projects/
A49: Synthica Fort Worth | B49: CANCELLED | E49: TX | F49: Groundbreaking Q4 2023, operational mid-2025 | G49: Synthica | H49: Planned to accept approx. 190,000 tons of food-derived feedstock. Depackaging System for Plastic, Paper and Metal Packaged Food/Beverage Waste | I49: CSTR | J49: 190,000 TPY | K49: ~500TPD | L49: "Food-derived feedstock" | Y49: https://synthica.com/projects/
A50: Synthica Miami Valley | B50: CANCELLED | E50: OH | F50: Groundbreaking Summer 2022 | G50: Synthica | H50: Commercial operation planned for summer 2023 | I50: CSTR? | J50: 190,000 TPY | K50: ~500 TPD | L50: "Food-derived feedstock" | N50: =O50/0.6 -> 1268391.7 | O50: =P50/(0.001*365*0.9) -> 761035.01 | P50: 250000 | Q50: PIPELINE (For vehicle/other) | S50: =P50/0.112194 -> 2228283.2 | Y50: https://synthica.com/projects/
A51: Forest County Potawatomi Community Renewable Generation - Biogas Facility | B51: SHUT DOWN; FUTURE POTENTIAL? | E51: WI | F51: 2011 | G51: Greenfire Management Services LLC*, Miron Construction Co., Inc., Symbiont Science, Engineering and Construction, Inc., Biothane, LLC, Veolia Water Solutions*, Natural Systems Utilities, LLC* | H51: At 2MW, the merchant plant has 5 feedstock tanks to sort supply, an equalization tank to mix and hold, and two 1.3M gallon anaerobic digesters. Digesters are continuously stirred and can process 132,000 gal./day. The two 1MW engines, unloading bays, gas skid, heat exchangers and solids processing are all enclosed with biological odor control. When fueling system is installed, will be initially for use by FCPC, then available under contract to local government and private fleets. Current upgrading process upgrading gas knocks particulates out, keep H2S down and drops out water vapor. No CO2 reduction, minimal volume change. | I51: Continuous stir | J51: 45,000 gpd | L51: Liquid food waste + organic byproducts of food processing industries, including beverage, dairy, meat, processed food + other byproducts of industrial food crop processing | M51: Potawatomi Hotel and Casino | O51: 720000 | P51: =0.001*365*O51*0.9 -> 236520 | Q51: VEHICLE FUEL | S51: =P51/0.112194 -> 2108134.1 | U51: 2MW | V51: 20,000 tonnes/year | Y51: https://www.americanbiogascouncil.org/projectProfiles/milwaukee_to_print.pdf http://greenfire.com/fcpc-renewable-generation-biodigester-facility/ https://energy.gov/eere/technology-to-market/renewable-energy-deployment-projects-forest-county-potawatomi-community http://www.renewwisconsin.org/pdf/PotoProfile.pdf https://www.biocycle.net/2014/05/15/from-casino-kitchens-to-on-site-digester/
A54: FOOD WASTE PROJECTS: STATUS | B54: Projected 12/31/2023
A55: Operational | B55: =COUNTA(A9:A21) -> 13
A56: Under construction | B56: =COUNTA(A23:A32) -> 10
A57: Planned | B57: 20
A60: FOOD WASTE PROJECTS: CAPACITY (MMBTU) | B60: Projected 12/31/2023
A61: Operational | B61: =SUM(P9:P21) -> 3267133
A62: Under Construction | B62: =SUM(P23:P32) -> 3987587.8

Sheet Landfills
A1: KEY: | B1: Project added 2023 | G1: Color coding generally applies to numeric values only.
B2: Information provided or confirmed by contact | G2: Individual values are often drawn from different sources, and so may appear inconsistent-- e.g., gas going for upgrading may be more than total amount of gas collected
B3: Value calculated based on other info provided
B4: Value from LMOP
B5: Value from website/press
A6: GENERAL INFORMATION | H6: PROJECT INFORMATION | K6: INPUTS | N6: OUTPUTS | U6: ADDITIONAL INFORMATION
A7: Landfill/Project Name | B7: Projected status 12/31/2023 | C7: Owner | D7: Waste In Place (tons) | E7: Daily intake, tons | F7: County | G7: State | H7: Upgrading Start Date | I7: Developer(s) | J7: Description | K7: LFG Flow to Upgrading Project (mmscfd) | L7: Total LFG Collected (mmscfd) | M7: LFG Flared (mmscfd) | N7: Upgraded gas, SCFD | O7: Upgraded MMBTU/yr | P7: RNG Disposition | Q7: If producing vehicle fuel, public filling station? | R7: GGE/yr | S7: Capacity (GGE/yr) | T7: Electricity | U7: Annual metric tonnes CO2e eliminated | W7: RIN Registrant? | X7: References
A8: OPERATIONAL AS OF 12/31/2023
A9: City of Fort Smith Landfill (Morrow Renewables) | B9: OPERATIONAL | C9: Fort Smith Department of Sanitation | D9: 10034620 | F9: Sebastian | G9: AR | H9: 38848 | I9: Morrow Renewables, LLC, Cambrian Energy Development, LLC | J9: Physical solvent process with patented enhancements and catalytic oxygen removal - removes CO2, H2O, H2S, siloxanes, and other impurities from LFG. Creates high BTU RNG injected into the pipeline infrastructure. Gas used down the pipeline for vehicle fuel. | K9: 2.7 | L9: 4.387 | M9: 0.297 | N9: =O9/(0.9*0.001*365) -> 1627397.3 | O9: 534600 | P9: PIPELINE (For vehicle/other) | Q9: No | R9: =O9/0.112194 -> 4764960.7 | T9: N/A | U9: .35 MMT | W9: Yes | X9: https://morrowrenewables.com/portfolio/ https://talkbusiness.net/2021/04/fort-smith-board-approves-cng-fueling-station-plans-for-conversion-of-sanitation-trucks/
A10: Eco Vista | B10: OPERATIONAL | C10: Waste Management Renewable Energy | D10: 9509704 | F10: Conway | G10: AR | H10: 45108 | J10: The Eco Vista facility spans 14,430 square feet. It is expected to recover and distribute approximately 750,000 metric million British thermal units (mmBtu) per year of RNG, which could serve the equivalent of 25,000 households annually or 650 heavy-duty vehicles. WM will allocate a portion of the RNG for its U.S. fleet of compressed natural gas (CNG) vehicles. The RNG facility at Eco Vista processes the increasing volumes of biogas collected from the landfill — generated during the decomposition of organic material — into pipeline-quality gas to be delivered to Energy Transfer’s Enable Gas Transmission pipeline system. According to communication with WMI, project will push 2500 SCFM of raw gas for upgrading. Upgrading technology Adsorption Research Inc. PSA system. | K10: =(2500*60*24)/1000000 -> 3.6 | L10: 2.457 | M10: 0 | N10: =(K10*1000000*0.55) -> 1980000 | O10: 750,000 | P10: PIPELINE (For vehicle/other) | Q10: NO | R10: =750000/0.112194 -> 6684849.5 | T10: 3.8 MW | U10: 40,000 tons per year | W10: Yes | X10: https://www.wmsolutions.com/locations/details/id/168 https://www.adeq.state.ar.us/sw/permits/p_facil_report.aspx#Display https://talkbusiness.net/2023/07/waste-management-launches-35-million-rng-facility-in-springdale/ https://mediaroom.wm.com/wm-unveils-new-35-million-dollar-eco-vista-renewable-natural-gas-facility
A11: Altamont Landfill (Waste Management) | B11: OPERATIONAL | C11: Waste Management, Inc. | D11: 63798959 | F11: Alameda | G11: CA | H11: 40057 | I11: The Linde Group; High Mountain Fuels | J11: Creates LNG to fuel 300 garbage trucks; WM delivers it to their locations in the SF Bay Area mostly - Oakland, Livermore and San Leandro - with occasional deliveries to Castroville; generates electricity from landfill gas powered turbines and windmills. System's multi-step process includes compression, chilling, adsorption, and membranes to remove impurities, cleaned LFG is then cooled to -260 deg F to create 13,000 gal/day LNG for garbage trucks. | K11: 3.47 | L11: 6.504 | N11: =O11/(0.9*0.001*365) -> 611004.77 | O11: =R11*0.112194 -> 200715.07 | P11: VEHICLE FUEL (LOCAL) | Q11: Private | R11: 1789000 | S11: 4927500 | T11: Enough to "power LNG plant and 8000 homes annually". | U11: 221400 | W11: Yes | X11: https://www.wm.com/documents/pdfs-for-services-section/Case-studies-municipal/PSS_CsStdyAltamLndfllREVISE_rFjjg.pdfhttp://www.energy.ca.gov/2014publications/CEC-500-2014-054/CEC-500-2014-054.pdf http://altamontlandfill.wm.com/index.jsp http://energy-vision.org/case-studies/WM-Altamont-Profile.pdf https://sustainability.wm.com/downloads/WM_2020_SR_Executive_Summary.pdf
A12: New River RNG Project (New River Solid Waste Association, Fortistar Energy Group) | B12: OPERATIONAL | C12: Landfill, New River Solid Waste Association; upgrading, Fortistar; fuel distribution Opal (Fortistar subsidiary) | D12: 5408895 | F12: Union | G12: FL | H12: Summer 2022 | I12: Fortistar, New River Solid Waste Association | J12: 2500 SCFM LFG to RNG project | K12: =(2500*60*24)/1000000 -> 3.6 | L12: 1.92 | M12: 1.92 | N12: =K12*1000000*0.55 -> 1980000 | O12: =N12*(0.001*365*0.9) -> 650430 | P12: BOTH | Q12: Private | R12: =O12/0.112194 -> 5797368.8 | S12: 5100000 | U12: 35000 | W12: Yes | X12: https://nrswa.org/new-river-rng-project/#:~:text=The%20project%2C%20formally%20known%20as,Energy%2C%20a%20Fortistar%20portfolio%20company., https://www.epa.gov/sites/production/files/2019-05/documents/full-rfp_18-01_nrrl_lfg-to-cng.pdf , https://www.naturalgasintel.com/fortistar-partnering-on-florida-rng-project-to-fuel-ngvs/ https://www.environmentalleader.com/2020/12/florida-first-construction-begins-on-facility-that-will-convert-landfill-methane-to-renewable-natural-gas/ https://nrswa.org/new-river-rng-project/https://www.businesswire.com/news/home/20220810005219/en/OPAL-Fuels-Reports-Year-to-Date-2022-Results
A13: Live Oak Landfill | B13: OPERATIONAL | C13: Landfill, Waste Management, Inc. Upgrading System, AIr Liquide | D13: 16745404 | F13: DeKalb | G13: GA | H13: 39873 | I13: Jacoby Energy Development, Inc.; Atlanta Gas Light Company; Air Liquide; Energy Systems Group | J13: Creates high BTU RNG injected into the pipeline infrastructure. Also fuels 14 CNG sanitation trucks. Air Liquide process for upgrade to 2,300 scfm of high Btu gas; uses combination of pressure swing adsorption and membrane technology. "generating up to 1,500 MWh of renewable natural gas daily to be transported via pipeline" | K13: 2.38 | N13: =K13*0.55*1000000 -> 1309000 | O13: =N13*(0.001*365*0.9) -> 430006.5 | P13: PIPELINE (For vehicle/other) | Q13: No | R13: =O13/0.112194 -> 3832705 | U13: 618400 | W13: Yes | X13: http://www.renewableenergyworld.com/articles/2007/09/atlantas-live-oak-landfill-to-become-source-of-renewable-energy-50025.html http://jacobydevelopment.com/energy17.html https://industry.airliquide.us/air-liquide-acquires-renewable-natural-gas-plant-jacoby-energy https://www.energy.gov/sites/prod/files/2014/03/f10/june2012_biogas_workshop_anderson.pdf
A14: Dubuque Metro Landfill | B14: OPERATIONAL | C14: Dubuque Metropolitan Area Solid Waste Agency | D14: 4223369 | E14: 455 | F14: Dubuque | G14: IA | H14: Pipeline injection began Q4 2021. | I14: Dubuque Metropolitan Area Solid Waste Agency, Enerdyne | J14: Landfill gas capture system is being upgraded in 2019 from flaring to upgrading, for injection into interstate pipeline. Based on press releases on solid waste agency website, an agreement with Trillium fell through, the project is now being done by Enerdyne. Project to begin construction in Q4 2020 RNG production should begin Q3 2021, LFG flow to project ~750cfm. | K14: =(N14/0.55)/1000000 -> 1.2121212 | N14: =O14/(0.001*365*0.9) -> 666666.67 | O14: =600*365 -> 219000 | P14: PIPELINE (For vehicle/other) | R14: =O14/0.112194 -> 1951976 | X14: https://www.telegraphherald.com/news/tri-state/article_1894f2e2-0523-5340-9caf-9ed22979c8cd.html http://landfillgroup.com/projects/dubuque-gas-producers-llc/
A15: Loess Hills Regional Sanitary Landfill | B15: OPERATIONAL | C15: Iowa Waste Services | D15: 4849617 | E15: ~1780 | F15: Mills | G15: IA | H15: 45170 | I15: Waste Connections, ESI | J15: Landfill gas from 76 gas wells scattered across the landfill is processed on-site, then goes through an interconnect station owned by Kinder Morgan and on to a BP gas pipeline. Initially, the facility will process 1,500 cfm landfill gas into RNG. Landfill officials estimate that within 15 years, the production rate will increase to 4,000 cfm, generating enough renewable energy to meet the needs of nearly 14,000 Iowa homes per year. Project was $35 million and two years in the making. | K15: 2.16 | N15: 1188000 | O15: 390258 | P15: PIPELINE (For vehicle/other) | X15: https://www.opinion-tribune.com/news/mills-county-landfill-gas-being-processed-renewable-energy https://www.iawaste.com https://www.linkedin.com/posts/energyneeringsolutions_esi-landfill-biogas-activity-7084881980730863616-0Ksg?trk=public_profile_like_view
A16: Milam Recycling and Disposal Facility (Waste Management) | B16: OPERATIONAL | C16: Waste Management, Inc. | D16: 29903905 | F16: St. Clair | G16: IL | H16: 42073 | I16: WM Renewable Energy, LLC, Air Liquide | J16: Facility designed to process 3,500 cfm LF. Gas is transported via natural gas pipelines to WM’s CNG fueling stations and CNG trucks. Upgrading equipment: CO2/siloxane: Air Liquide membrane with carbon polisher. Nitrogen/Oxygen: ARI PSA. | K16: 3.6 | L16: 4.556 | M16: 1.186 | N16: 1600000 | O16: 576000 | P16: PIPELINE (For vehicle/other) | Q16: No | R16: =O16/0.112194 -> 5133964.4 | S16: 5486000 | T16: 2.4 MW for RNG plant demand, none exported to grid. Three Cat 3516 engines running on natural gas | U16: 310000 | W16: Yes | X16: https://www.wmsolutions.com/locations/details/id/31 https://waste-management-world.com/a/waste-management-opens-19m-landfill-gas-grid-injection-facility-in-illinois https://sustainability.wm.com/downloads/WM_2020_SR_Executive_Summary.pdf
A17: Will County Renewable Natural Gas Facility at Prairie View Landfill | B17: OPERATIONAL | C17: Will County (WM Operating landfill, maybe not the RNG facility) | D17: 10510812 | F17: Will | G17: IL | H17: October 2022 | I17: Will County; (WM may operate, or a different third party, unknown as of July 2021) | J17: Conversion of LFG to electricity project to RNG. County has 10 year agreement with US Venture to buy RNG from the facility to sell as vehicle fuel. Estimated costs of upgrading system and pipeline $46 million. | K17: 4.252 | L17: 4.252 | M17: 2.102 | N17: =(O17/5.5)*10 -> 1766545.5 | O17: 971600 | P17: PIPELINE (For vehicle/other) | Q17: No | R17: =7700000*1.14 -> 8778000 | U17: 40,000-61,500 | X17: http://biomassmagazine.com/articles/17747/agreement-signed-for-illinois-rng-project https://www.wjol.com/will-county-board-approves-renewable-natural-gas-plant/ http://willcountyil.iqm2.com/Citizens/FileOpen.aspx?Type=1&ID=3814 https://www.wjol.com/will-county-celebrates-ribbon-cutting-at-new-renewable-natural-gas-plant/
A18: WM Twin Bridges Landfill | B18: OPERATIONAL | C18: Landfill Waste Mangement; upgrading project, Kinder Morgan | D18: 28621989 | F18: Hendricks | G18: IN | H18: 45107 | I18: Kinetrex | J18: Project converts approximately 8.64 mmscfd of landfill gas to pipeline quality. The construction also included a 5-mile pipeline lateral to transport the RNG to the to a nearby third-party transmission pipeline. Begin monetizing RINs in Q3 2023. | L18: 8.64 | N18: =(L18*1000000)*0.55 -> 4752000 | O18: =N18*(0.001*365*0.9) -> 1561032 | P18: PIPELINE (For vehicle/other) | R18: =O18/0.112194 -> 13913685 | X18: https://www.wmsolutions.com/pdf-tracker/index/id/63/campaignType/28 http://s24.q4cdn.com/126708163/files/doc_presentations/2021/09/September-2021-Investor-Presentation-old.pdf https://www.nasdaq.com/articles/kinder-morgan-kmi-affiliate-starts-3-rng-plants-construction-2021-10-05 https://www.kindermorgan.com/Operations/Projects/Kinetrex-Landfill-Based-RNG-Facilities-Project
A19: Indy High BTU/Southside | B19: OPERATIONAL | C19: Indy High BTU LLC owned by Kinetrex Energy, South Side Landfill and EDL Energy) | D19: 23957886 | F19: Marion | G19: IN | H19: Q1 2020 | I19: EDL Energy, Kinetrex | J19: Iron redox scrubber for hydrogen sulfide removal, membranes for carbon dioxide removal and pressure swing adsorption for nitrogen removal. Indy High BTU supplies Kinetrex Energy with RNG, which Kinetrex turns into liquefied natural gas (LNG) and sells to Midwest transportation fleets. Air Liquide CO2 removal and Guild Associates nitrogen removal. | K19: 5.76 | L19: 7.2 | M19: 0 | N19: =K19*1000000*0.55 -> 3168000 | O19: =R19*0.112194 -> 897552 | P19: PIPELINE (For vehicle/other) | Q19: Unknown | R19: 8000000 | S19: 9120000 | U19: 41000 | W19: Yes | X19: https://www.globenewswire.com/news-release/2019/09/05/1911345/0/en/SCS-Energy-Breaks-Ground-on-Indy-Landfill-Gas-to-RNG-Plant.html https://www.wishtv.com/news/inside-indiana-business/ribbon-cutting-set-for-indy-rng-plant/ https://www.wfyi.org/news/articles/construction-complete-at-indy-high-btu-states-largest-renewable-natural-gas-plant https://www.environmentalleader.com/2020/03/indiana-plant-to-convert-methane-into-8-million-gallons-of-renewable-natural-gas-each-year/ https://edlenergy.com/project/indy-high-btu-renewable-natural-gas-plant/
A20: Randolph Farms Landfill | B20: OPERATIONAL | C20: Randolph Farms Landfill | D20: 9199343 | F20: Modoc | G20: IN | H20: Summer 2018 | I20: Randolph Farms Inc. | J20: Relatively small scale project, upgrading about 15% of landfill gas. Doing single pass upgrading, only capturing about 40% of the gross volume of gas. Not a 24/7 operation, but capturing about 1500 MMBTU/month. Gas being used to fuel part of collection fleet, about 8 trucks out of 40. Any project expansion will be based on expansion of CNG portion of fleet. Upgrading skid installed by Unison Solutions, using Air Liquide membrane separation technology. | K20: 0.288 | L20: 1.438 | M20: 1.15 | N20: =O20/(0.001*365*0.9) -> 54794.521 | O20: 18000 | P20: VEHICLE FUEL (LOCAL) | Q20: Private | R20: =O20/0.112194 -> 160436.39 | T20: N/A | U20: 27500 | W20: Yes | X20: http://www.biomassmagazine.com/articles/12345/hoosier-energy-to-build-fourth-landfill-gas-to-energy-plant https://www.waste360.com/gas-energy/waste-energy-firms-partner-indiana-landfill-gas-project
A21: Rumpke Medora Landfill | B21: OPERATIONAL | C21: Landfill, Rumpke Waste and Recycling | D21: 6154495 | F21: Jackson | G21: IN | H21: Q4 2021 | I21: Rumpke, Archaea Energy | J21: 1800 MMBtus/day for regional pipeline distribution | K21: =N21/(0.55*1000000) -> 3.2727273 | N21: =O21/(0.001*365*0.9) -> 1800000 | O21: =1800*365*0.9 -> 591300 | P21: PIPELINE (For vehicle/other) | Q21: No | R21: =O21/0.112194 -> 5270335.3 | X21: https://www.waste360.com/landfill/rumpke-archaea-energy-break-ground-landfill-gas-energy-plant-indiana-landfill https://www.waste360.com/landfill-operations/archaea-coo-benham-talks-high-btu-renewable-gas-growing-markets https://www.archaeaenergy.com/projects
A22: WM Liberty Landfill | B22: OPERATIONAL | C22: Landfill Waste Management; upgrading project, Kinder Morgan | D22: 21905462 | F22: White | G22: IN | H22: 45200 | I22: Kinetrex | J22: This project includes the development of a facility that will produce 8.64 mmscfd, along with the construction of the Liberty RNG Lateral - an approximately 12-mile, 4 inch-diameter pipeline lateral, to transport RNG captured from the Liberty Landfill near Monticello, White County, Indiana to an interconnect with an existing third-party pipeline in Cass County, Indiana. Capacity 1.5 bcf per year. | K22: =(6000*60*24)/1000000 -> 8.64 | L22: 5.767 | N22: =L22*1000000 -> 5767000 | O22: 1558500 | P22: PIPELINE (For vehicle/other) | R22: =O22/0.112194 -> 13891117 | X22: http://s24.q4cdn.com/126708163/files/doc_presentations/2021/09/September-2021-Investor-Presentation-old.pdf https://www.nasdaq.com/articles/kinder-morgan-kmi-affiliate-starts-3-rng-plants-construction-2021-10-05 https://www.kindermorgan.com/Operations/Projects/Kinetrex-Landfill-Based-RNG-Facilities-Project https://www.kindermorgan.com/ETV/KM-RNG/Leaders-in-RNG-Development/Renewable-Gas-Assets/Liberty
A23: WM Prairie View Recycling and Disposal | B23: OPERATIONAL | C23: Landfill Waste Management; upgrading project, Kinder Morgan | D23: 12914889 | F23: St. Joseph | G23: IN | H23: 45261 | I23: Kinetrex | J23: This facility is being constructed at Waste Management’s Prairie View Landfill in St. Joseph County, Indiana. It will be the smallest of the three projects, with the proposed facility processing only half as much landfill gas compared to its sister sites, meaning 4.32 mmscfd. Once the gas is processed, the RNG will be delivered via pipeline to the nearby third-party transmission pipeline. Capacity 0.8 bcf per year. | K23: 4.32 | L23: 2.27 | N23: =L23*1000000 -> 2270000 | O23: 831200 | P23: PIPELINE (For vehicle/other) | R23: =O23/0.112194 -> 7408595.8 | X23: http://s24.q4cdn.com/126708163/files/doc_presentations/2021/09/September-2021-Investor-Presentation-old.pdf https://www.nasdaq.com/articles/kinder-morgan-kmi-affiliate-starts-3-rng-plants-construction-2021-10-05 https://www.kindermorgan.com/Operations/Projects/Kinetrex-Landfill-Based-RNG-Facilities-Project https://www.kindermorgan.com/ETV/KM-RNG/Leaders-in-RNG-Development/Renewable-Gas-Assets/Prairie-View
A24: Hamm Sanitary Landfill/Renewable Power Producers | B24: OPERATIONAL | C24: RNG project, Renewable Power Producers LLC Landfill: Hamm Inc. | D24: 10867646 | F24: Douglas | G24: KS | H24: Q3 2017 | I24: Renewable Power Producers | J24: Renewable Power Producers is a landfill gas to pipeline quality natural gas processing facility located at the Hamm Sanitary Landfill in Lawrence, KS. The project became operational in 2017. All planning, permitting, engineering, contracts and installation were completed by Enerdyne Power Systems. Gas collection system has over 150 gas collection points. CO2 removal equipment uses Evonik membrane systems. 7.2 mile pipeline to interconnect to Southern Star Central Gas Pipeline. Nameplate design processing of 4000 SCFM of raw landfill gas. Enerdyne website estimates production at 4.5 million gallons annually. | K24: =(N24/0.55)/1000000 -> 2.988792 | M24: 0.313 | N24: =O24/(0.001*365*0.9) -> 1643835.6 | O24: =45000*12 -> 540000 | P24: PIPELINE (For vehicle/other) | Q24: Unknown | R24: =O24/0.112194 -> 4813091.6 | U24: 247200 | W24: Yes | X24: http://www2.ljworld.com/news/2016/sep/28/hamm-landfill-construct-methane-gas-plant-and-pipe/ https://www.epa.gov/sites/default/files/2019-10/documents/fenton_rngworkshop_2019.pdf https://www.atmosenergy.com/esg/environment/renewable-natural-gas https://www.epa.gov/sites/default/files/2018-03/documents/2_william_brinker_lmop.pdf https://assets.lawrenceks.org/assets/agendas/cc/2016/09-20-16/pw_rpp_description.pdf http://www2.ljworld.com/news/2017/sep/26/editorial-methane-plant-positive/?opinion http://www.rngcoalition.com/news/2017/9/22/enerdyne-power-systems-commissions-rng-project-in-lawrence-ks
A25: Johnson County Landfill (formerly Deffenbaugh) (WM, Archaea) | B25: OPERATIONAL | C25: Landfill, Waste Management; upgrading operation, Archaea Energy | D25: 43185541 | F25: Johnson | G25: KS | H25: 37135 | I25: Energy Investors Funds Group; Enpower Corp.; Aria (formerly Landfill Energy Systems); SouthTex Treaters, LLC | J25: Creates high BTU RNG injected into the pipeline infrastructure; uses a modified Selexol-type scrubbing system | K25: 7 | L25: 8.856 | M25: 1.905 | N25: 2733158 | O25: 1000000 | P25: PIPELINE (For vehicle/other) | Q25: No | R25: =O25/0.112194 -> 8913132.6 | U25: 668000 | W25: Yes | X25: http://www.wm.com/location/missouri/deffenbaugh/index.jsp https://www.wastetodaymagazine.com/article/waste-management-johnson-county-landfill/
A26: Big Run Project at Boyd County Sanitary Landfill | B26: OPERATIONAL | C26: Archaea accuired upgrading facility and gas rights from Ultra Capital-owned Big Run Power Producers. Rumpke of Ohio acquired landfill in 2019. WM operates it | D26: 10392413 | E26: 727 | F26: Boyd | G26: KY | H26: Facility construction began April 2018, LMOP 2021 Project start date 9/13/20 | I26: Archaea (latest), Big Run Power Producers (original) | J26: All gas going into pipeline to earn enviro attributes. Waste 360 6/10/21 Revamped by Rumpke and Archaea in 2019-2020 | K26: 3.1 | L26: 4.065 | N26: =(K26*1000000)*0.55 -> 1705000 | O26: =N26*0.001*365*0.9 -> 560092.5 | P26: PIPELINE (For vehicle/other) | Q26: No | R26: =O26/0.112194 -> 4992178.7 | S26: 7482574 | T26: No | U26: 25000 | X26: http://www.dailyindependent.com/news/clean-energy-project-set-for-big-run-landfill/article_429588e2-29ca-11e5-8076-e7af04fb1cee.html https://www.dailyindependent.com/news/big-run-landfill-to-provide-company-with-energy-source/article_1e4a781c-1d9c-11e8-aabe-1bf8f8127988.html https://www.waste360.com/waste-energy/archaea-and-rumpke-building-more-landfill-gas-energy-projects https://www.naturalgasintel.com/aria-archaea-merger-looks-to-create-largest-commercial-rng-platform-in-u-s//
A27: Benson Valley Landfill | B27: OPERATIONAL | C27: Republic Services, landfill; Ameresco, RNG facility | D27: 6272096 | F27: Franklin | G27: KY | H27: 45139 | I27: Ameresco | J27: Facility is capable of processing 2,000 standard cubic feet per minute of raw LFG. Construction began in June 2022 and plant went operational in August 2023. Transportation is the end-use, as indicated by Republic Services VP of innovation and business development Tim Oudman and as noted in LMOP. | O27: 483552 | P27: PIPELINE (For vehicle/other) | Q27: Unknown | U27: 27440 | X27: https://www.wastetodaymagazine.com/news/ameresco-landfill-gas-to-rng-plant-starts-operations-at-republic-landfill/ https://www.businesswire.com/news/home/20231019240572/en/Ameresco-Landfill-Gas-to-Renewable-Natural-Gas-Plant-Operations-Begin-at-Republic-Services’-Benson-Valley-Landfill https://www.ameresco.com/portfolio-item/benson-valley-landfill-gas-plant-case-study-ameresco/ https://www.spglobal.com/commodityinsights/es/market-insights/latest-news/natural-gas/110923-strong-renewable-fuel-standard-targets-drive-interest-in-rng-projects
A28: Outer Loop | B28: OPERATIONAL | C28: Landfill, Waste Management | D28: 36812118 | F28: Jefferson | G28: KY | H28: 43191 | I28: WM Renewable Energy, LLC | J28: Creates high BTU RNG injected into the pipeline infrastructure. Capacity 5000 scfm LFG. | K28: =(N28/0.55)/1000000 -> 4.5522623 | L28: 5.964 | M28: 0.41 | N28: =O28/(0.001*365*0.9) -> 2503744.3 | O28: 822480 | P28: PIPELINE (For vehicle/other) | Q28: No | R28: =O28/0.112194 -> 7330873.3 | S28: =((5000*60*24*365*0.9)*0.55*0.001)/0.112194 -> 11594738 | U28: 531000 | W28: Yes | X28: https://www.wmsolutions.com/locations/details/id/145 http://www.courier-journal.com/story/tech/science/environment/2017/02/09/louisville-landfill-capture-sell-its-methane/97656292/ https://www.bizjournals.com/louisville/news/2018/06/05/waste-management-makes-a-power-play-with-30.html
A29: Jefferson Davis Parish Landfill | B29: OPERATIONAL | C29: Jefferson Davis Parish Sanitary Landfill Commission | D29: 11078324 | F29: Jefferson Davis | G29: LA | H29: 39539 | I29: Morrow Renewables, LLC | J29: Physical solvent process with patented enhancements and catalytic oxygen removal - removes CO2, H2O, H2S, siloxanes, and other impurities from LFG. Creates high BTU RNG injected into the pipeline infrastructure for use as vehicle fuel | K29: =(N29/0.55)/1000000 -> 2.2654601 | L29: 4.22 | M29: 1.45 | N29: =O29/(0.001*365*0.9) -> 1246003 | O29: 409312 | P29: PIPELINE (For vehicle/other) | Q29: No | R29: =O29/0.112194 -> 3648252.1 | T29: N/A | U29: 281500 | W29: Yes | X29: http://www.countyoffice.org/welsh-landfill-welsh-la-1b7/ https://wastebits.com/locator/location/jefferson-davis-parish-sanitary-landfill
A30: Keithville (Republic, Element Markets) | B30: OPERATIONAL | C30: Landfill, Republic Services | D30: 11538212 | F30: Caddo | G30: LA | H30: 2018 | I30: Mas Energy, University of California | J30: Uses pressure swing adsorption upgrading technology. Gas is injected into common carrier for use in vehicle fuels market | K30: 2.95 | L30: 2.95 | M30: 0 | N30: =O30/(0.001*365*0.9) -> 1622499.2 | O30: 532991 | P30: PIPELINE (For vehicle/other) | Q30: No | R30: =O30/0.112194 -> 4750619.5 | S30: 6000000 | T30: N/A | U30: 281500 | W30: Yes | X30: https://www.shreveportla.gov/487/Landfills
A31: River Birch & Jefferson Parish Landfills | B31: OPERATIONAL | C31: River Birch, Inc. | D31: 23412942 | F31: Jefferson | G31: LA | H31: 6/1/2010, expansions 2014 and 2017, began assipting gas form neighboring Jefferson Parish LF 2019-2020. | I31: River Birch, Inc.; Keystone Renewable Energy, LLC | J31: Air-Liquide membrane separation produces 2,000 MMBtu/day of 950 Btu/scf gas, biological sulfur removal system named Thiopak. Creates high BTU RNG injected into the pipeline infrastructure. WIth 2014 upgrade, 3400 MMBTU day. Started processing gas from nearby Jefferson Parish Landfill in 2019-2020. 2021, combined otal form two projects 6000 dekatherms per day. | K31: 6.72 | L31: 7.484 | N31: =O31/(0.001*365*0.9) -> 6666666.7 | O31: 2190000 | P31: PIPELINE (For vehicle/other) | Q31: No | R31: =O31/0.112194 -> 19519760 | U31: 604700 | W31: Yes | X31: http://riverbirchlandfill.com/energy.asp. https://www.arb.ca.gov/fuels/lcfs/2a2b/apps/sdm-rvb-cng-rpt-123015.pdf https://www.eventscribe.com/2020/ACEVIRTUAL/fsPopup.asp?efp=SlJUWEJSWkExMTIwMw&PresentationID=737063&rnd=0.9898586&mode=presinfo https://www.atmosenergy.com/esg/environment/renewable-natural-gas
A32: St. Landry Parish Landfill | B32: OPERATIONAL | C32: St. Landry Parish Solid Waste Disposal District | D32: 2622567 | F32: St. Landry | G32: LA | H32: 41012 | I32: BioCNG; St. Landry Parish Solid Waste Disposal District | J32: Produces CNG vehicle fuel for an on-site fueling station used to power Sheriff’s Department cars, light duty trucks and a light duty van, and the solid waste district’s utility trucks. Membrane removes CO2, silica medium removes silica, volatile organic compaunds removed by charcoal-like compound, coconut based medium to remove other VOCs, Sulfatreat to remove H2S. 50 cfm LFG produces 250 gallons of gasoline equivalent (GGE)/day; convert LFG to bioCNG vehicle fuel for 1 passenger van, 5 sedans & 10 fleet pick-up trucks. 2018, have upgraded compressors, no impact on production levels, just makes production a bit easier. | K32: 0.3024 | L32: 0.3096 | M32: 0.22 | N32: 82800 | O32: 180000 | P32: VEHICLE FUEL (LOCAL) | Q32: Private | R32: 172000 | S32: 262800 | T32: N/A | U32: 24179 | W32: Yes | X32: http://biocng.us/projects/st-landry-parish-landfill-gas-energy-project/ http://www.tetratech.com/en/projects/st-landry-parish-landfill-biocng-project-louisiana https://www.epa.gov/sites/production/files/2016-05/documents/05_k_martin_presentation.pdf https://wasteadvantagemag.com/st-landry-parish-solid-waste-disposal-district-turning-landfill-gas-into-biofuel/ https://www.csmonitor.com/Environment/2021/0712/Trash-talk-Are-waste-to-energy-plants-a-sustainable-solution
A33: Waste Connections Timberlane | B33: OPERATIONAL | C33: Waste Connections | D33: 3741382 | F33: Allen | G33: LA | H33: April 2019? | I33: Waste Connections, AIr Liquide | J33: Membrane technology. | K33: 1.12 | L33: 0.856 | M33: 0 | N33: =(K33*1000000)*0.55 -> 616000 | O33: =N33*(0.001*365*0.9) -> 202356 | P33: PIPELINE (For vehicle/other) | Q33: Unknown | R33: =O33/0.112194 -> 1803625.9 | U33: 106900 | W33: Yes | X33: http://www.rngcoalition.com/rng-industry-celebrates-new-2019-production-facilities-to-open-rng-2019-conference https://www.wasteconnections.com/timberlane-landfill/
A34: Granger Wood Road | B34: OPERATIONAL | C34: Granger Waste Management Corp. | D34: 13405252 | F34: Clinton | G34: MI | H34: Q2 2022? | I34: Granger Waste Management, EDL | J34: Output estimates based on LMOP collection/flared numbers | L34: 3.382 | N34: =L34*0.5*1000000 -> 1691000 | O34: =N34*0.001*365*0.9 -> 555493.5 | P34: PIPELINE (For vehicle/other) | R34: =O34/0.112194 -> 4951187.2 | X34: https://www.deq.state.mi.us/aps/downloads/SRN/N5997/N5997_SAR_20200819.pdf https://www.youtube.com/watch?v=0ramNSn5SjQ https://www.biofuelsdigest.com/bdigest/2022/02/27/lansing-michigans-first-waste-to-energy-facility-opens/
A35: Richfield Landfill ("Blue Sky") (Blue Skies Energy) | B35: OPERATIONAL | C35: Richfield Landfill, Inc. | D35: Not available | F35: Genesee | G35: MI | H35: 39022 | I35: Blue Skies Energy, LLC | J35: Uses UOP Separex Membrane Technology to create pipeline quality natural gas from LFG. Aria Energy buying all output. | K35: =(N35/0.55)/1000000 -> 2.0090909 | L35: 2.03 | N35: 1105000 | O35: 360000 | P35: PIPELINE (For vehicle/other) | Q35: No | R35: =O35/0.112194 -> 3208727.7 | U35: 193700 | W35: Yes | X35: http://www.nthconsultants.com/richfield-sanitary-landfill.html http://www.mlive.com/news/flint/index.ssf/2014/04/potential_buyer_of_richfield_l.html http://www.mlive.com/news/flint/index.ssf/2012/11/state_deq_official_says_new_ri.html
A36: Riverview Land Preserve | B36: OPERATIONAL | C36: City of Riverview | D36: 22996089 | F36: Wayne | G36: MI | H36: May 2013 | I36: BioCNG | J36: BioCNG system fuels 7 city vehicles and an AT&T fleet.100 cfm LFG yields 450-500 GGE/day CNG for City vehicles | K36: 0.14 | L36: 6.12 | M36: 1.08 | N36: =K36*0.55*1000000 -> 77000 | O36: =N36*0.001*365*0.9 -> 25294.5 | P36: VEHICLE FUEL (LOCAL) | Q36: Private | R36: =500*365 -> 182500 | S36: 200750 | T36: 6.4 MW | U36: 134000 | W36: Yes | X36: http://biocng.us/wp-content/uploads/2015/06/Riverview-Fact-Sheet-2015.pdf https://riverviewlandpreserve.com/ https://riverviewlandpreserve.com/2020/05/27/renewable-natural-gas-produced-daily-at-riverview-land-preserve/
A37: Sauk Trail Hills Landfill (Republic Services, Archaea) | B37: OPERATIONAL | C37: Landfill, Republic Services, Inc. Gas upgrading, Archaea Energy & BP | D37: 23862571 | F37: Wayne | G37: MI | H37: 41487 | I37: Clean Energy Fuels | J37: (2) Totara+ LFG upgrading systems ("water wash"). Creates high BTU RNG injected into the pipeline infrastructure and distributed by DTE Gas; RNG also distributed for vehicle fuel use to Republic Services natural gas fleets. When fully operational project should supply 6 million diesel GGE per year | K37: 2.44 | L37: 4.425 | M37: 2.4 | N37: =O37/(0.001*365*0.9) -> 1341108.1 | O37: 440554 | P37: PIPELINE (For vehicle/other) | Q37: Private | R37: =O37/0.112194 -> 3926716.2 | T37: N/A | U37: 439000 | W37: Yes | X37: http://www.michigan.gov/deq/0,4561,7-135-3312_4123-197993--,00.html https://www.waste360.com/landfill-gas-energy-lfgte/utility-converting-landfill-gas-natural-gas-detroit https://investors.cleanenergyfuels.com/news-releases/news-release-details/republic-services-and-clean-energy-sign-renewable-biomethane
A38: Waste Management Woodland Meadows (WM, Ameresco) | B38: OPERATIONAL | C38: Landfill: Waste Management of Michigan; Upgrading system, Ameresco Woodland Meadows Romulus | D38: 56080525 | F38: Wayne | G38: MI | H38: Q1 2019 | I38: Ameresco | J38: LFG collection system is pulling gas from three adjoining landfills, including one that is closed. Ameresco upgrading operation using PSA technology to upgrade gas to pipeline quality. Put into pipeline for ultimate use by vehicles. Producing 3500 MMBTU per day. | K38: 6.57 | L38: 11.718 | M38: 5.14 | N38: =O38/(0.001*365*0.9) -> 3500000 | O38: =3500*365*0.9 -> 1149750 | P38: PIPELINE (For vehicle/other) | Q38: No | R38: =O38/0.112194 -> 10247874 | T38: N/A | U38: 706200 | W38: Yes | X38: http://biomassmagazine.com/articles/14873/rng-coalition-celebrates-new-projects-launches-video https://www.ameresco.com/amerescos-woodland-meadows-landfill-state-of-the-art-gas-to-energy-facility-now-open/
A39: Westside Recycling and Disposal Facility (WM, DTE Biomass Energy) | B39: OPERATIONAL | C39: Landfill, Waste Management; biogas and upgrading operations, DTE Biomass Energy | D39: 13574734 | E39: 1400 | F39: St. Joseph | G39: MI | H39: 36161 | I39: DTE Biomass Energy, Waste Management | J39: Creates High Btu RNG that’s injected into the Consumers Energy pipeline and sold to a third party to be dispensed into CNG/LNG vehicles. Uses Kryosol upgrading process. | K39: =(N39/0.55)/1000000 -> 2.3636364 | L39: 2.024 | N39: 1300000 | O39: =R39*0.112194 -> 466880.18 | P39: PIPELINE (For vehicle/other) | Q39: No | R39: 4161365 | S39: 6402100 | T39: N/A | U39: 167000 | W39: Yes | X39: https://dtevantage.com/project/westside-gas-producers/ https://legislature.mi.gov/documents/2009-2010/CommitteeDocuments/Senate/ Energy%20Policy%20and%20Public%20Utilities/Testimony/2009-SCT-ENERGY-10-21-1-01.PDF https://www.egle.state.mi.us/aps/downloads/ROP/pub_ntce/N1216/N1216%20Staff%20Report%2003-24-17.pdf
A40: Eagle Ridge Landfill | B40: OPERATIONAL | C40: Meridian Waste | F40: Pike | G40: MO | H40: 45147 | I40: Vision RNG | J40: Landfill began operations August 2023; generates enough RNG to heat approximately 8,800 homes per year. The RNG is injected into a nearby interstate natural gas pipeline and used by various customers across the U.S. for transportation fuel and other sustainability purposes. | N40: 2160000 | O40: 375000 | P40: PIPELINE (For vehicle/other) | X40: https://www.businesswire.com/news/home/20230809819469/en/Vision-RNG-and-Meridian-Waste-Announce-Landfill-Gas-to-Renewable-Natural-Gas-Project-First-in-Missouri
A41: Fortistar Pine Bend Landfill | B41: OPERATIONAL | C41: Landfill. Republic Services; RNG project, OPAL (Fortistar company) | D41: 22013015 | F41: Dakota | G41: MN | H41: 44835 | I41: Fortistar, Republic | J41: Project will replace former LFG to electricity project that is being retired. Gas at landfill currently being burned off as flare. Will collect 32000 scfm LFG and produce 6 mil GGE RNG/year to be used for fueling vehicles | K41: 4.8 | L41: 3.694 | M41: 3.694 | N41: =O41/(365*0.001*0.9) -> 2453068.5 | O41: 805833 | P41: PIPELINE (For vehicle/other) | Q41: No | R41: 6300000 | U41: 43900 | W41: Yes | X41: https://www.startribune.com/renewable-natural-gas-plant-planned-for-landfill-in-inver-grove-heights/600045459/ https://www.prnewswire.com/news-releases/opal-and-nextera-energy-marketing-announce-plans-to-build-minnesotas-first-renewable-natural-gas-facility-301278648.html https://biomassmagazine.com/articles/19460/minnesota-landfill-gas-to-rng-project-begins-operations https://www.businesswire.com/news/home/20221025005262/en/OPAL-Fuels-NextEra-Energy-Marketing-and-Republic-Services-Begin-Operations-at-Minnesota%E2%80%99s-First-Landfill-Gas-to-Renewable-Natural-Gas-Facility https://www.environmentalleader.com/2022/10/minnesotas-first-renewable-natural-gas-facility-now-operational/
A42: North East Mississippi Regional Landfill (Air Liquide) | B42: OPERATIONAL | C42: Landfill, Northeast Mississipi Solid Waste Mangement Authority; upgrading operation, Air Liquide | D42: 6036153 | E42: 950 | F42: Tippah | G42: MS | I42: Air Liquide | J42: Using gas separation membrane technology. 1300 mmbtu/day with plans to expand. | K42: 2.664 | L42: 1.961 | N42: 1498500 | O42: 497355 | P42: PIPELINE (For vehicle/other) | Q42: Unknown | R42: =O42/0.112194 -> 4432991.1 | T42: None | U42: 25382 | W42: Yes | X42: http://www.djournal.com/news/business/walnut-to-get-air-liquide-biogas-purification-plant/article_4c84637e-f8e3-5a19-acd4-67977d08f1cb.html https://www.airliquide.com/group/press-releases-news/2018-04-19/air-liquide-doubles-its-biomethane-production-capacity https://www.waste360.com/gas-energy/air-liquide-build-its-first-landfill-biogas-purification-plant-us https://ngtnews.com/air-liquide-cuts-ribbon-on-landfill-gas-to-rng-plant-in-mississippi
A43: Billings Regional Landfill | B43: OPERATIONAL | C43: City of Billings | D43: 8069019 | E43: 1150 | F43: Yellowstone | G43: MT | H43: 40519 | I43: Montana-Dakota Utilities Co.; LFG Technologies, Inc. | J43: Creates high BTU RNG injected into the pipeline infrastructure. Also fuels 14 CNG sanitation trucks. Air Liquide process for upgrade to 2,300 scfm of high Btu gas; uses combination of pressure swing adsorption and membrane technology. Guild PSA Stage #1 system removes water vapor, H2S, siloxanes, non-methane hydrocarbons, organic halides, and CO2; Molecular Gate PSA Stage #2 system removes nitrogen; tail gas is 46% CH4 and used in a genset to provide power to the facility | K43: 0.895 | L43: 1.053 | N43: =K43*0.55*1000000 -> 492250 | O43: =N43*0.001*365*0.9 -> 161704.13 | P43: BOTH | Q43: Private | R43: =O43/0.112194 -> 1441290.3 | T43: N/A | U43: 85400 | W43: Yes | X43: http://billingsgazette.com/news/local/billings-aims-to-boost-landfill-gas-collection-buy-trucks-run/article_13593e4f-9441-50a1-8408-15989ff34209.html https://billingsgazette.com/news/local/government-and-politics/capturing-methane-at-landfill-a-prosperous-venture-for-billings/article_b0910eb6-3676-5b9e-8c58-4bfdc6b82111.html http://lfgtech.com/rng/
A44: Foothills Renewables | B44: OPERATIONAL | C44: Owner Caldwell County; managed by Republic Services | D44: 6006762 | F44: Caldwell | G44: NC | H44: 45175 | I44: Republic Services, Energyneering, Evensol, Pacolet Milliken | J44: As of April 2022 Duke Energy became an investor in this project. The RNG will provide clean transportation fuel to commercial fleet vehicles. The project will initially produce up to 500,000 MMBTU of RNG each year. | K44: 3.96 | L44: 2.135 | M44: 2.135 | N44: =O44/(0.001*365*0.9) -> 1522070 | O44: 500000 | P44: PIPELINE (For vehicle/other) | Q44: No | R44: =O44/0.112194 -> 4456566.3 | X44: http://edocs.deq.nc.gov/WasteManagement/0/edoc/1215656/1403_INSP_20180627.pdf https://files.nc.gov/ncdeq/Air%20Quality/permits/2019_public_notice_documents/permit_reviews/20190520_Republic_rev.pdf https://news.duke-energy.com/releases/duke-energy-announces-investment-in-two-new-renewable-natural-gas-projects-in-north-carolina https://www.energytech.com/energy-efficiency/article/21259128/duke-partners-plan-converting-north-carolina-landfill-gas-to-rng https://evensol.com/evensol-project-partners-commission-the-state-of-north-carolinas-first-two-landfill-gas-to-renewable-natural-gas-production-facilities/
A45: Republic Upper Piedmont Environmental Landfill | B45: OPERATIONAL | C45: Republic Services | D45: 5202699 | F45: Person | G45: NC | H45: 45170 | I45: Republic Services, Energyneering, Evensol, Pacolet Milliken | J45: Project will produce ~500,000 MMBTU per year. As of April 2022 Duke Energy became an investor in this project. In January 2023, sustainability investment firm Pacolet Milliken completed a joint venture (JV) investment with renewable biogas assets developer Evensol with Duke Energy. Went operational in September 2023, providng fuel to commercial fleet vehicles. | L45: 1.946 | M45: 1.946 | N45: =O45/(0.001*365*0.9) -> 1522070 | O45: 500000 | P45: PIPELINE (For vehicle/other) | X45: https://evensol.com/projects/ https://www.prnewswire.com/news-releases/greater-commercial-lending-completes-financing-for-two-landfill-gas-to-renewable-natural-gas-projects-in-north-carolina-301479627.html https://news.duke-energy.com/releases/duke-energy-announces-investment-in-two-new-renewable-natural-gas-projects-in-north-carolina https://www.youtube.com/watch?v=z4wlLLuygp0 https://www.energytech.com/energy-efficiency/article/21259128/duke-partners-plan-converting-north-carolina-landfill-gas-to-rng
A46: Butler County (Waste Connections, Archaea) | B46: OPERATIONAL | C46: Landfill, Waste Connections; upgrading system, Archaea Energy | D46: 7790728 | E46: 1900 | F46: Butler | G46: NE | H46: 2018 | I46: Aria Energy (as TImerlane Energy) | J46: 1000 SCFM LFG to RNG project. Gas piped to boilers at Henningsen Foods and to Constellation vehele fueling stations. | K46: 1.44 | L46: 1.301 | N46: =O46/(365*0.001*0.9) -> 529680.37 | O46: 174000 | P46: PIPELINE (For vehicle/other) | Q46: Unknown | R46: =O46/0.112194 -> 1550885.1 | U46: 101000 | W46: Yes | X46: http://journalstar.com/news/state-and-regional/nebraska/butler-county-board-hears-support-opposition-to-landfill-expansion/article_aadc543f-34de-57e4-a675-bfce43cb16e0.html http://biomassmagazine.com/articles/14873/rng-coalition-celebrates-new-projects-launches-video http://butlercountylandfill.com/Resources_Local/files/ButlerLandfillGasPDF.pdf https://www.dmt-cgs.com/project/butler-county-landfill-rng/ https://www.constellationenergy.com/newsroom/2019/constellation-to-distribute-renewable-natural-gas-produced-from-.html
A47: Douglas County Landfill-- State Street (BioResource Development) | B47: OPERATIONAL | C47: Douglas County Environmental Services | D47: 5224710 | F47: Douglas | G47: NE | I47: BioResource Development | J47: Cleans LFG so that the methane can be injected into a natural gas pipeline. Using proprietary gas upgrading technology. 3-mile, 2-inch polyamide 11 (PA11) pipeline made of a thermoplastic resin (derived from a bio-renewable source) to withstand pressure of up to 200 psi, transports LFG to utility’s 12-inch gas main in Omaha that feeds its liquefaction facility | K47: 0.92 | L47: 0.817 | N47: =K47*1000000*0.55 -> 506000 | O47: =N47*(0.001*365*0.9) -> 166221 | P47: PIPELINE (For vehicle/other) | Q47: Unknown | R47: =O47/0.112194 -> 1481549.8 | T47: N/A | U47: 87800 | W47: Yes | X47: http://www.omaha.com/news/metro/company-wants-to-refine-sell-methane-gas-at-old-state/article_4759dc06-602b-5aa1-84ea-878cd2bdd7ff.html
A48: Sarpy County Landfill, BioResource Development N1 | B48: OPERATIONAL | C48: Landfill, Sarpy County; gas upgrading, BioResource Development | D48: 3914719 | E48: LANDFILL CLOSED | F48: Sarpy | G48: NE | H48: Q2 2018 | I48: BioResource Development LLC; US GAIN? | J48: Renewable natural gas plant designed to remove H2S, VOCs, Siloxanes, moisture, CO2 and N2 prior to injecting process gas directly into the local utility 200psi natural gas pipeline. | K48: 1.12 | L48: 1.117 | M48: 0 | N48: =K48*0.55*1000000 -> 616000 | O48: =N48*(0.001*0.9*365) -> 202356 | P48: BOTH | Q48: No | R48: =O48/0.112194 -> 1803625.9 | S48: Proprietary | T48: Proprietary | U48: 200610 | W48: Yes | X48: http://www.sierraclub.org/sites/www.sierraclub.org/files/sce-authors/u2978/Sierra%20Club%27s%20%20Omaha%20Metropolitan%20Area%20SWM%20Study%20%20March%2013%20%202017.pdf https://www.blackhillsenergy.com/services/natural-gas-services/renewable-natural-gas/our-renewable-natural-gas-projects https://www.blackhillsenergy.com/node/1223 https://www.omaha.com/money/company-will-collect-gases-from-sarpy-landfill-to-turn-into/article_05ad4cf9-d8e2-542c-8336-841189cfbc6a.html https://www.csrwire.com/press_releases/41841-expediting-development-supply-of-renewable-natural-gas
A49: Chautauqua Green Energy Landfill RNG Project | B49: OPERATIONAL | C49: Chautauqua Green Energy LLC (formed by EmKey Gathering LLC and Vireo Energy) | D49: 7789015 | F49: Chautauqua | G49: NY | H49: Q2 2022 | I49: Chautauqua Green Energy LLC | J49: Privately owned LFG upgrading facility on county landfill land, RNG for pipeline injection to vehicle fuel. 2500 scfm LFG | K49: 2.16 | L49: 2.16 | M49: 0 | N49: =K49*1000000*0.55 -> 1188000 | O49: 500000 | P49: PIPELINE (For vehicle/other) | Q49: No | R49: =500000/0.112194 -> 4456566.3 | X49: https://www.observertoday.com/news/local-region/2020/06/new-private-facility-proposed-at-county-landfill-to-convert-natural-gas-to-electricity/ , https://chqgov.com/sites/default/files/document-files/2020-06/6-24-20%20Agenda%20LEG.pdf
A50: Fresh Kills Landfill (Montauk) | B50: OPERATIONAL | C50: New York City Department of Sanitation | D50: 135450945 | E50: Landfill closed | F50: Richmond | G50: NY | H50: 1982 | I50: Montauk Energy Capital, Air Products | J50: Creates high BTU RNG injected into the National Grid pipeline infrastructure; uses Selexol technology | K50: 3 | L50: 3.182 | M50: 0.095 | N50: 1500000 | O50: 474119 | P50: PIPELINE (For vehicle/other) | Q50: No | R50: =O50/0.112194 -> 4225885.5 | T50: N/A | U50: 288560 | W50: Yes | X50: http://freshkillspark.org/landfill-engineering/monitoring http://freshkillspark.org/the-park/landfill-engineering http://freshkillspark.org/landfill-engineering/collection-and-processing
A51: Seneca Meadows SWMF (Progressive, Archaea) | B51: OPERATIONAL | C51: Progressive Waste Solutions Ltd. | D51: 47161988 | F51: Seneca | G51: NY | H51: 41701 | I51: Archaea Energy; Innovative Energy Systems, LLC | J51: LFG-to-RNG plant; initially 3,000 cfm LFG inlet / 1,425 cfm RNG outlet; design capacity is 6,000 cfm LFG inlet; uses Air Liquide-MEDAL system; end uses of piped gas include electricity generation at NG power plant and by fuel cells, CNG production. | K51: =(3000*60*24)/1000000 -> 4.32 | L51: 18.451 | N51: =K51*0.55*1000000 -> 2376000 | O51: =N51*0.001*365*0.9 -> 780516 | P51: PIPELINE (For vehicle/other) | Q51: No | R51: =O51/0.112194 -> 6956842.6 | S51: =(((6000*24*60)*0.55)*0.001*365*0.9)/0.112194 -> 13913685 | T51: 18.5MW via reciprocating engines | U51: 669000 | W51: Yes | X51: https://senecameadows.com/gas-to-energy/ https://www.naturalcapitalpartners.com/projects/project/seneca-meadows-landfill-gas
A52: American (WM) | B52: OPERATIONAL | C52: WM Renewable Energy | D52: 35259696 | E52: 920 | F52: Stark | G52: OH | H52: 2014 | I52: Waste Management | J52: 2000 MMBTU/day RNG to pipeline project | K52: 4 | L52: 4.066 | M52: 0.803 | N52: 2016000 | O52: =N52*0.001*365*0.9 -> 662256 | P52: PIPELINE (For vehicle/other) | Q52: No | R52: =O52/0.112194 -> 5902775.5 | U52: 391300 | W52: Yes | X52: http://americanlandfill.wm.com/facility-information/index.jsp http://americanlandfill.wm.com/facility-information/landfill-gas-to-energy.jsp http://blog.cleveland.com/business/2008/12/roadell_hickman_the_plain_deal.html https://www.wmsolutions.com/pdf/factsheet/AmericanLandfill.pdf
A53: APEX Sanitary Landfill (Apex, Montauk) | B53: OPERATIONAL | C53: Landfill, APEX Environmental, LLC. Upgrading, Montauk Energy | D53: 22847163 | F53: Jefferson | G53: OH | H53: Q2 2018 | I53: Element Markets, LLC | J53: Creates high BTU RNG injected into the pipeline infrastructure. Uses membrane separation technology. Capacity 2670 MMBtu/day. 8/31/22, Montauk announces plans to construct second upgrading facility, projected 40% increase in processing capacity or additional 2100 MMBTU per day. Expansion expected to complete in 2024 (LMOP says 12/31/24), $25-$30MM, driven by inceases in projected biogas production. | K53: 2.9 | L53: 3.632 | N53: 2680000 | O53: 855290 | P53: PIPELINE (For vehicle/other) | Q53: No | R53: 6842300 | S53: =(2670*365*0.9)/0.112194 -> 7817664 | U53: 276800 | W53: Yes | X53: http://biomassmagazine.com/articles/6108/ohio-landfill-gas-to-pipeline-project-underway http://montaukenergy.com/operations/apex/ https://seekingalpha.com/news/3879161-montauk-renewables-to-build-new-renewable-natural-gas-plant-in-ohio https://biomassmagazine.com/articles/19307/montauk-renewables-announces-second-apex-rng-facility
A54: Republic Carbon Limestone | B54: OPERATIONAL | C54: Republic Services | D54: 37695461 | F54: Mahoning | G54: OH | J54: Facility nearly $100 million investment. Under an agreement signed in February 2022, Pennant Midstream will transport up to six million cubic feet of renewable natural gas per day through its existing system from the landfill, redelivering the gas to EDL’s downstream markets. | O54: 2268840 | P54: PIPELINE (For vehicle/other) | R54: =O54/0.112194 -> 20222472 | X54: https://businessjournaldaily.com/edl-launches-100m-renewable-energy-plant-in-poland/
A55: Franklin County Sanitary Landfill (Archaea) | B55: OPERATIONAL | C55: Solid Waste Authority of Central Ohio | D55: 25610176 | F55: Franklin | G55: OH | H55: 41671 | I55: Archaea Energy | J55: High BTU-LFG is injected into the NG pipeline with a contract to Sacramento Municipal Utility District. 300 cfm LFG is cleaned via CO2 Wash® equipment to create 800-1,000 gasoline gallon equivalents per day of CNG for use in SWACO & other area fleets. | K55: 8.64 | L55: 7.827 | M55: 0 | N55: =K55*0.55*1000000 -> 4752000 | O55: =N55*0.001*365*0.9 -> 1561032 | P55: BOTH | Q55: Public | R55: =O55/0.112194 -> 13913685 | U55: 740440 | W55: Yes | X55: https://www.epa.gov/sites/default/files/2018-06/documents/rngwebinar_20180614.pdf http://www.dispatch.com/article/20150422/news/304229729
A56: Noble Road Landfill | B56: OPERATIONAL | C56: Landfill, Rumplke; upgrading project, Fortistar/Opal | D56: 15322161 | F56: Richland | G56: OH | H56: October 2021; commercial operations announced March 2022. | I56: Fortistar, Rumpke, Chesapeake Utilities Corp. | J56: The project will extract and capture waste methane from the Noble Road landfill in Ohio and transform it into RNG, which will be distributed through Chesapeake Utilities Corporation affiliate Aspire Energy’s pipelines. The fuel will be dispensed at natural gas fueling stations via Trustar Energy, a Fortistar company. Project will capture the equivalent of 49,940 tons of carbon dioxide, per year and produce RNG and will produce the equivalent of 6.9 million gallons of gasoline per year. WIll use membrane upgrading technology provided by Air Liquide. Overall project cost $33 million. | K56: =(N56/0.55)/1000000 -> 4.2847024 | L56: 1.943 | M56: 1.943 | N56: =O56/(0.001*365*0.9) -> 2356586.3 | O56: =R56*0.112194 -> 774138.6 | P56: PIPELINE (For vehicle/other) | Q56: Not at this time | R56: 6900000 | U56: 49940 | W56: Yes | X56: https://www.businesswire.com/news/home/20200917005237/en/New-Ohio-based-Renewable-Fuel-Project-Aims-to-Capture-the-Equivalent-of-Nearly-50K-Tons-of-Carbon-to-Displace-Diesel-and-Fuel-725-Biofuel-Trucks https://www.nsenergybusiness.com/news/fortistar-rumpke-to-begin-noble-road-landfill-rng-project-in-ohio/ https://www.businesswire.com/news/home/20220303005156/en/OPAL-Fuels-Commences-Commercial-Operation-of-Noble-Road-Renewable-Natural-Gas-Facility-at-Rumpke-Waste-Recycling-Landfill-in-Shiloh-Ohio
A57: Pinnacle Road Landfill (North Sanitary Landfill) (WM, DTE Biomass Energy) | B57: OPERATIONAL | C57: Landfill, Waste Management, Inc.; upgrading project, DTE BIomass Energy | D57: 6150000 | E57: 650 tpd | F57: Montgomery | G57: OH | H57: 37742 | I57: Waste Management, DTE Biomass Energy, Inc. | J57: Creates high BTU RNG injected into the pipeline infrastructure; uses Kryosol (methanol) technology; combined facility with Stony Hollow, with Pinnacle Road Landfill providing about 30% LFG flow to project. Total, 4.5 MMCFD LFG. All figures on this project based on 30%. Gas processing equipment removes CO2 to produce methane meeting NG pipeline quality specifications; uses Kyrosol Solvent technology | K57: =4.5*0.3 -> 1.35 | N57: =K57*0.55*1000000 -> 742500 | O57: =N57*0.001*365*0.9 -> 243911.25 | P57: PIPELINE (For vehicle/other) | Q57: No | R57: =O57/0.112194 -> 2174013.3 | T57: N/A | U57: 127500 | W57: Yes | X57: https://dtevantage.com/project/pinnacle-gas-producers/
A58: Rumpke Sanitary Landfill | B58: OPERATIONAL | C58: Rumpke Consolidated Companies | D58: 63285314 | F58: Hamilton | G58: OH | H58: 1986, expansions in 1995 and 2007 | I58: GSF Energy; Montauk Energy Capital | J58: All RNG goes into Duke Energy Pipeline, though some of it is immediately re-directed back to site for use by 125 trucks of various types in Rumpke fleet. Adding about 20 trucks per year. Have added fast-fill station to existing time-fill station. GSF energy manages gas recovery. LFG blended with NG for delivery to NG customers; Pretreatment: non-methane hydrocarbon removal via chilling & activated carbon absorption, 2 compressors driven by 700 HP electric motors, uses QuestAir pressure swing absorption technology | K58: 15 | L58: 17.6 | M58: 2.6 | N58: =O58/(0.001*365*0.9) -> 4717677.3 | O58: 1549757 | P58: PIPELINE (For vehicle/other) | Q58: Private | R58: =O58/0.112194 -> 13813190 | S58: =(7270*365*0.9)/0.112194 -> 21286299 | U58: 1431500 | W58: Yes | X58: https://www.rumpke.com/docs/default-document-library/rslfactsheet.pdf https://www.rumpke.com/newsroom/article/2011/10/04/rumpke-fuels-fleet-with-garbage https://www.egovlink.com/public_documents300/colerain/published_documents/Rumpke/Gas-to-pipeline%20fact%20sheet_Jan10.pdf http://montaukenergy.com/operations/rumpke-sanitary-landfill/
A59: Stony Hollow Landfill (WM, DTE Biomass Energy) | B59: OPERATIONAL | C59: Landfill, Waste Management, Inc.; upgrading project, DTE Biomass Energy | D59: 11938043 | E59: 650 | F59: Montgomery | G59: OH | H59: 37742 | I59: Waste Management, DTE Biomass Energy, Inc. | J59: Creates high BTU RNG injected into the pipeline infrastructure; uses Kryosol (methanol) technology; combined facility with Pinnacle Road Landfill, with Stony Hollow Landfill providing about 70% LFG flow to project. All figures on this project based on 70%. Gas processing equipment removes CO2 to produce methane meeting NG pipeline quality specifications; uses Kryosol Solvent technology | K59: =4.5*0.7 -> 3.15 | L59: 4.283 | N59: =K59*0.55*1000000 -> 1732500 | O59: =N59*0.001*365*0.9 -> 569126.25 | P59: PIPELINE (For vehicle/other) | Q59: No | R59: =O59/0.112194 -> 5072697.7 | U59: 138400 | X59: http://stonyhollowlandfill.com/ http://www.mitchellwilliamslaw.com/landfill-gas-emissions/common-law-action-us-district-court-addresses-motion-to-dismiss
A60: East Oak Landfill | B60: OPERATIONAL | C60: Landfill, Waste Management | D60: 20993621 | F60: Oklahoma | G60: OK | H60: Q4 2021 | I60: WM Renewable Energy, LLC | J60: Site is being redeveloped for RNG injected into the pipeline infrastructure. Based on coummunication with WMI, project will push 3000SCFM of raw gas for upgrading. Upgrading technology will be Selexol via Morrow Renewables, combined with Air Liquide cryogenic nitrogen rejection. | K60: =(3000*60*24)/1000000 -> 4.32 | L60: 4.821 | M60: 4.821 | N60: =K60*0.55*1000000 -> 2376000 | O60: =N60*(0.001*365*0.9) -> 780516 | P60: PIPELINE (For vehicle/other) | Q60: No | R60: =O60/0.112194 -> 6956842.6 | S60: ?? | W60: Yes | X60: http://www.waste360.com/operations/breaking-down-gtl-project-oklahoma-landfill-0 https://applications.deq.ok.gov/permitspublic/storedpermits/5655.pdf
A61: Oklahoma City Landfill (Waste Connections, Archaea) | B61: OPERATIONAL | C61: Landfill: Waste Connections, Inc. Gas and upgrading projects: Archaea Energy | D61: 14120663 | F61: Oklahoma | G61: OK | H61: April 2008 | I61: Timberline Energy (rolled up into Aria Energy) | J61: Creates high BTU RNG compressed and delivered to the Southern Star pipeline. 3 MMSCFD facility removes water, H2S, and organic compounds from the LFG, then removes CO2 in a 2-stage Air Liquide membrane separator. Flow to project, ~2000 SCFM. | K61: =2015*60*24/1000000 -> 2.9016 | L61: 2.636 | N61: =K61*0.55*1000000 -> 1595880 | O61: =N61*0.001*365*0.9 -> 524246.58 | P61: PIPELINE (For vehicle/other) | Q61: No | R61: =O61/0.112194 -> 4672679.3 | U61: 302300 | W61: Yes | X61: http://oklahomacitylandfill.com/ http://biomassmagazine.com/articles/14873/rng-coalition-celebrates-new-projects-launches-video https://www.epa.gov/sites/default/files/2019-12/documents/landfillgasenergyproject_chaseedmiston.pdf http://www.locicontrols.com/perch/resources/fieldnote10increasesmmbtuofsales061319.pdf
A62: Southeast Oklahoma City (Republic, Archaea) | B62: OPERATIONAL | C62: Landfill, Republic Services; upgrading operation, Archaea Energy | D62: 18709425 | E62: 1500 | F62: Oklahoma | G62: OK | H62: 2018 | I62: Aria Energy (through our Mavrix JV) | J62: 3000 SCFM LFG to RNG project. RNG to pipeline, with BP promising to use equivilent amount of NG for vehicles, claim renewable fuels tax credits. Capacity 624,150 MMBtu/year | K62: 3.77 | L62: 5.432 | M62: 0.956 | N62: =K62*0.55*1000000 -> 2073500 | O62: =N62*0.001*365*0.9 -> 681144.75 | P62: PIPELINE (For vehicle/other) | Q62: No | R62: =O62/0.112194 -> 6071133.5 | S62: =624150/0.112194 -> 5563131.7 | U62: 348000 | W62: Yes | X62: https://applications.deq.ok.gov/permitspublic/storedpermits/4199.pdf https://www.oklahoman.com/article/5609233/oklahoma-city-landfill-waste-used-to-power-cars-and-trucks https://www.esisolutions.com/case-studies
A63: Southern Oklahoma Regional Disposal Landfill | B63: OPERATIONAL | C63: Southern Oklahoma Regional Disposal | D63: 4262210 | F63: Carter | G63: OK | H63: 43282 | I63: Lynx Renewable Energy | J63: CO2 scrubbers, oxygen removal, activated carbon. | K63: 0.68 | L63: 1.6 | M63: 0.92 | N63: =K63*1000000*0.55 -> 374000 | O63: =N63*0.001*365*0.9 -> 122859 | P63: PIPELINE (For vehicle/other) | Q63: No | R63: =O63/0.112194 -> 1095058.6 | U63: 65400 | X63: http://www.lynxrenewableenergy.com/ https://applications.deq.ok.gov/permitspublic/storedpermits/4455.pdf
A64: Advanced Disposal Services Greentree Landfill, LLC (Advanced Disposal, Fortistar) | B64: OPERATIONAL | C64: Advanced Disposal Services owns landfill, Fortistar owns upgrading facility (baught from EDF Renewables) | D64: 24402801 | E64: 2200 | F64: Elk | G64: PA | H64: 39264 | I64: enXco LFG Holdings, LLC; American Exploration; Beacon Generating, LLC | J64: Plant capacity is 15.12 mmscfd, cleaning: Air Liquide membrane technology, PSA and activated carbon pretreatment system Fortistar to take upgraded gas, use it for vehicle fuel through TruStar. With their other new aquisition Greentree Landfill Gas, the company can produce 1.5 million mmbtu of RNG per year. Greentree provides 55% of total production. Together, an extra 107,485 metric tons of CO2 per year avoided from use in vehicles. | K64: 5.04 | L64: 10.08 | N64: =K64*1000000*0.55 -> 2772000 | O64: =N64*0.001*365*0.9 -> 910602 | P64: VEHICLE FUEL (Local) | Q64: Public | R64: =O64/0.112194 -> 8116316.4 | U64: 808000 | W64: Yes | X64: https://www.countyoffice.org/kersey-landfill-kersey-pa-2db/ https://frs-public.epa.gov/ords/ frs_public2/fii_query_detail.disp_program_facility?p_registry_id=110001060618 https://kupperengineering.com/project/greentree-landfill-rng-facility/ https://www.waste360.com/mergers-and-acquisitions/fortistar-acquires-two-rng-facilities-pennsylvania
A65: Assai at Keystone Sanitary Landfill (Archaea) | B65: OPERATIONAL | C65: Landfill, Keystone Sanitary Landfill, Inc.; gas upgrading project, Archaea (Meadowbrook Energy project fell through) | D65: 47526030 | F65: Lackawanna | G65: PA | H65: Q3 2021 | I65: Archaea | J65: Largest RNG Project in the world. Process LFG into 16,000 mcf per day of pipeline-ready gas and inject into UGI's high-pressure NG pipeline nearby. No mention of vehicle fuel in current project plan, but it is possible if UGI supplies any fueling stations. | K65: =(N65/0.55)/1000000 -> 29.090909 | L65: 20.261 | N65: 16000000 | O65: 4380000 | P65: BOTH | Q65: No | R65: =O65/0.112194 -> 39039521 | U65: 314000 | X65: https://wnep.com/2018/01/31/proposed-renewable-natural-gas-production-facility-would-reduce-landfill-biogas-emission/ https://www.meadowbrookenergy.com/ https://www.pahomepage.com/news/plans-unveiled-for-100-million-biogas-processing-facility/94742444 https://www.archaeaenergy.com/projects https://renewablesnow.com/news/spac-to-create-listed-us-renewable-natural-gas-platform-with-usd-115bn-ev-737292/
A66: Imperial Sanitary Landfill (Republic, Fortistar) | B66: OPERATIONAL | C66: Republic Services, Inc. owns landfill; Fortistar owns upgrading facility (bought from EDF Renewables) | D66: 23317918 | F66: Allegheny | G66: PA | H66: 39326 | I66: enXco LFG Holdings, LLC | J66: Fortistar to take upgraded gas, use it for vehicle fuel through TruStar. With their other new aquisition Greentree Landfill Gas, the company can produce 1.5 million mmtbu of RNG per year. Imperial provides 45% of total production. Together, an extra 107,485 metric tons of CO2 per year avoided from use in vehicles. | K66: 4.2 | L66: 10.3 | M66: 6.1 | N66: =K66*0.55*1000000 -> 2310000 | O66: =N66*0.001*365*0.9 -> 758835 | P66: VEHICLE FUEL (Local) | Q66: Public | R66: =O66/0.112194 -> 6763597 | T66: All exported for electricity. | U66: 403980 | W66: Yes | X66: https://www.waste360.com/mergers-and-acquisitions/fortistar-acquires-two-rng-facilities-pennsylvania https://www.countyoffice.org/imperial-landfill-imperial-pa-2a6/ https://www.businesswire.com/news/home/20190402005372/en/Fortistar-Acquires-Two-Renewable-Natural-Gas-RNG-Facilities-in-Pennsylvania
A67: Laurel Highlands Landfill (WM, Montauk Energy) | B67: OPERATIONAL | C67: Waste Management, Inc. Upgrading operation: Montauk Energy | D67: 7737813 | E67: 7 | F67: Cambria | G67: PA | H67: 38899 | I67: Keystone Renewable Energy, LLC (original); Leaf Clean Energy; Air Liquide-MEDAL | J67: Creates high BTU RNG injected into the pipeline infrastructure without contract. All ouput being purchased by Aria | K67: 1.4 | L67: 2.93 | N67: =K67*0.55*1000000 -> 770000 | O67: =N67*0.001*365*0.9 -> 252945 | P67: PIPELINE (For vehicle/other) | Q67: No | R67: =O67/0.112194 -> 2254532.3 | T67: N/A | U67: 133600 | W67: Yes | X67: https://www.wmsolutions.com/locations/details/id/219 http://www.dep.pa.gov/Business/Land/Waste/SolidWaste/MunicipalWaste/MunicipalWastePermitting/Pages/MW-Landfills-and-Resource-Recovery-Facilities.aspx
A68: Monroeville Landfill (WM) | B68: OPERATIONAL | C68: Waste Management, Inc. | D68: 19759441 | F68: Allegheny | G68: PA | H68: 38289 | I68: Montauk Energy Capital | J68: Creates high BTU RNG injected into the pipeline infrastructure using membrane technology. Capacity: 2370 MMBtu/day | K68: 2.17 | L68: 3.87 | N68: =O68/(365*0.001*0.9) -> 1091336.4 | O68: 358504 | P68: PIPELINE (For vehicle/other) | Q68: No | R68: =O68/0.112194 -> 3195393.7 | S68: =(23708*365*0.9)/0.112194 -> 69416172 | U68: 200400 | W68: Yes | X68: https://www.wmsolutions.com/locations/details/id/220 https://www.dep.pa.gov/Business/Land/Waste/SolidWaste/MunicipalWaste/MunicipalWastePermitting/Pages/MW-Landfills-and-Resource-Recovery-Facilities.aspx https://www.epa.gov/sites/default/files/2019-12/documents/monroevillelandfill_danbonk.pdf
A69: Seneca Landfill | B69: OPERATIONAL | C69: Vogel Holdings, Inc. | D69: 11618297 | E69: 3000 | F69: Butler | G69: PA | H69: 40575 | I69: Keystone Renewable Energy, LLC; RenewCo | J69: Creates high BTU RNG injected into the pipeline infrastructure committed to fueling CNG and LNG vehicles. Landfill currently operating 35 CNG collection trucks, will be auditioning CNG tractor trailers to bring material from transfer stations to landfill. Have built fast-fill station at the landfill, which complements slow-fill station at the main yard. Is open to public. ~1.5 mile pipeline to NG transmission line, Air Liquide membrane technology, delivers 970 Btu/scf gas. As of 2021, pushing about 1500-1600 dekatherms daily. | K69: 1.25 | L69: 3.267 | N69: =O69/(365*0.001*0.9) -> 1666666.7 | O69: =1500*365 -> 547500 | P69: BOTH | Q69: Public | R69: =O69/0.112194 -> 4879940.1 | T69: 300kW on-site generation | U69: 261500 | W69: Yes | X69: http://www.senecalandfill.com/ http://www.senecalandfill.com/about-seneca-landfill http://www.dep.pa.gov/Business/Land/Waste/SolidWaste/MunicipalWaste/Landfill-Methane-Outreach-Program/Pages/PA-Landfill-Methane-Projects.aspx
A70: Shade Landfill (WM, Montauk) | B70: OPERATIONAL | C70: Waste Management, Inc., Montauk Energy Capital | D70: 8487347 | E70: Landfill closed | F70: Somerset | G70: PA | H70: 39326 | I70: Keystone Renewable Energy, LLC (original); Leaf Clean Energy; RenewCo | J70: Creates high BTU RNG injected into the pipeline infrastructure. 12-mi pipeline from Shade LF and 2.5-mi pipeline from Southern Alleghenies LF deliver 970 Btu gas; uses membrane technology; total delivery to pipeline from both landfills is 650,000 MMBtu/yr. Has capacity to process 1120 MMBTU/day of RNG | K70: 2.49 | M70: N/A | N70: =O70/(365*0.001*0.9) -> 1120000 | O70: =1120*365*0.9 -> 367920 | P70: PIPELINE (For vehicle/other) | Q70: No | R70: =O70/0.112194 -> 3279319.7 | T70: N/A | U70: 118800 | W70: Yes | X70: http://www.dep.pa.gov/Business/Land/Waste/SolidWaste/MunicipalWaste/Landfill-Methane-Outreach-Program/Pages/PA-Landfill-Methane-Projects.aspx https://www.ccpa.net/DocumentCenter/View/17513 http://montaukenergy.com/operations/johnstown-regional-energy-shade/
A71: Green Rock Energy South Hills RNG | B71: OPERATIONAL | C71: Landfill, Waste Management, Inc; upgrading, Green Rock Energy Partners as of Q4 2022. | D71: 7191938 | F71: Allegheny | G71: PA | H71: ?? | I71: PSA South Hills Landfill Gas Venture, Green Rock | J71: According to LMOP, this project was shsut down in 2013, but press accounts of purchase are from 2022. New RNG facility being built and expected to start production in mid-2023. The facility is expected to produce one million gallons/year of renewable fuel. Caluclations based on 1 million GGE/yr. | K71: 1.18 | L71: 0.889 | O71: 112194 | P71: PIPELINE (For vehicle/other) | R71: 1000000 | X71: https://www.businesswire.com/news/home/20221208005100/en/Green-Rock-Energy-Partners-Acquires-Pennsylvania-Renewable-Natural-Gas-Production-Facility https://southhillsrng.com/colorado-energy-trading-company-joins-landfill-natural-gas-project/
A72: Southern Alleghenies Landfill (WM, Montauk) | B72: OPERATIONAL | C72: Montauk Energy Capital, Waste Management, Inc. | D72: 9800711 | F72: Somerset | G72: PA | H72: 39326 | I72: Keystone Renewable Energy, LLC; Leaf Clean Energy | J72: Creates high BTU RNG injected into the pipeline infrastructure. 12-mi pipeline from Shade LF and 2.5-mi pipeline from Southern Alleghenies LF deliver 970 Btu gas; uses Air Liquide membrane separation technology; total delivery to pipeline from both landfills is 650,000 MMBtu/yr. Based on Shade capcity, facilty produces 858 MMBTU/day RNG | K72: 2.34 | L72: 2.88 | N72: =O72/(365*0.001*0.9) -> 858000 | O72: =858*365*0.9 -> 281853 | P72: PIPELINE (For vehicle/other) | Q72: No | R72: =O72/0.112194 -> 2512193.2 | T72: N/A | U72: 111600 | W72: Yes | X72: https://www.dep.pa.gov/Business/Land/Waste/SolidWaste/MunicipalWaste/Landfill-Methane-Outreach-Program/Pages/PA-Landfill-Methane-Projects.aspx https://www.facebook.com/Waste-Management-Southern-Alleghenies-Landfill-1609478579063642/ https://gflenv.com/our-facilities/landfills/
A73: Valley Landfill | B73: OPERATIONAL | C73: Landfill, Waste Management; Upgrading System, Valley LFG LLC | D73: 9122502 | F73: Westmoreland | G73: PA | H73: 2003 | I73: Montauk Energy Capital | J73: Creates high BTU RNG injected into the pipeline infrastructure. Capacity fro 2370 MMBTU/day | K73: 1.18 | L73: 2.026 | M73: 0.699 | N73: =O73/0.55 -> 374156.36 | O73: 205786 | P73: PIPELINE (For vehicle/other) | Q73: No | R73: =O73/0.112194 -> 1834197.9 | S73: =(2370*365*0.9)/0.112194 -> 6939274.8 | U73: 110700 | W73: Yes | X73: http://www.buzzfile.com/business/Montauk-Energy-Capital-412-823-6296 https://www.wmsolutions.com/locations/details/id/224 http://montaukenergy.com/operations/valley/
A74: Westmoreland County Sanitary Landfill | B74: OPERATIONAL | C74: Noble Environmental | D74: 6401503 | F74: Westmoreland | G74: PA | H74: Q1 2020 | I74: Noble Environmental, LLC | J74: Uses PSA upgrading technology. Injected into Common Carrier for use in the Vehicle Fuels Market. Some gas also being used to fuel refuse trucks on site. | K74: 2.01 | L74: 2.23 | N74: =K74*1000000*0.55 -> 1105500 | O74: =N74*(0.001*365*0.9) -> 363156.75 | P74: BOTH | Q74: Private | R74: =O74/0.112194 -> 3236864.3 | T74: None | U74: 500000 | W74: Yes | X74: https://pittsburgh.cbslocal.com/2020/10/22/trash-to-gas-its-happening-in-westmoreland-county/ http://www.wwllcgroup.com/ http://www.westmorelandslf.com/ https://usgasvehicles.com/en/westmoreland-sanitary-landfill-to-produce-vehicle-fuel-from-renewable-sources/
A75: Twin Chimneys | B75: OPERATIONAL | C75: Twin Chimneys Power Producers | D75: 3932084 | F75: Greenville | G75: SC | H75: 45016 | I75: Enerdyne/Advance One | J75: RNG is injected into the local natural gas system, which is owned and operated by the Greenwood Commissioners of Public Works (Greenwood CPW). According to the EPA, the environmental benefits associated with this project at full build out will be equivalent to reducing the CO2 emissions of more than 66 million gallons of gasoline each year. | L75: 1.88 | M75: 1.88 | N75: =O75/(0.001*365*0.9) -> 1222222.2 | O75: =1100*365 -> 401500 | P75: PIPELINE (For vehicle/other) | Q75: No | R75: =O75/0.112194 -> 3578622.7 | W75: Yes | X75: https://www.greenvillecounty.org/solidwaste/Landfill.aspx http://www.scdhec.gov/library/OR-1151.pdf https://greenvillejournal.com/news/landfill-looking-convert-gas-energy/ https://upstatebusinessjournal.com/news/new-composting-facility-unveiled-at-twin-chimneys-landfill/ http://landfillgroup.com/twin-chimneys-landfill-receiving-renewable-natural-gas-project/ https://www.kpvi.com/news/national_news/the-landfill-group-and-ls-power-announce-state-of-the-art-renewable-natural-gas-project/article_05382d7c-76d7-5d59-8db5-9624c81c1427.html https://www.bioenergy-news.com/news/the-landfill-group-announces-commercial-operation-of-the-first-rng-project-in-south-carolina/ https://landfillgroup.com/the-landfill-group-announces-commercial-operation-of-the-first-rng-project-in-south-carolina/
A76: Carter Valley Landfill | B76: OPERATIONAL | C76: Landfill, Republic Services. Based on EPA Part 80 documents, facility is owned by US Venture, owner of US GAIN natural gas fueling | D76: 12723765 | F76: Hawkins | G76: TN | H76: 39904 | I76: Tengasco | J76: Creates high BTU RNG injected into the pipeline infrastructure. 2.5-mile pipeline to existing NG pipeline; uses membrane technology. | K76: 1.728 | L76: 2.35 | N76: =K76*1000000*0.55 -> 950400 | O76: =N76*(0.001*365*0.9) -> 312206.4 | P76: PIPELINE (For vehicle/other) | Q76: No | R76: =O76/0.112194 -> 2782737 | U76: 164900 | W76: Yes | X76: http://www.timesnews.net/News/2008/09/25/Carters-Valley-landfill-in-line-for-16-million-in-upgrades http://archive.knoxnews.com/business/tengasco-signs-5-year-gas-contract-with-houston-company-ep-409627085-359229161.html/ http://biomassmagazine.com/articles/16142/us-gain-brings-sixth-rng-development-project-online
A77: Meadow Branch Landfill (Waste Connections) | B77: OPERATIONAL | C77: Landfill, Waste Connections, Inc.; upgrading, Southern Company Gas | D77: 9912013 | F77: McMinn | G77: TN | H77: 40814 | I77: Renewco LLC; Keystone Renewable Energy, LLC | J77: Creates high BTU RNG injected into the pipeline infrastructure with end user contracts. 9.5-mile, 4-inch steel pipeline delivers ~1,000 MMBtu/day initially; refrigeration, PSA, carbon filtration, membrane separation, Air Liquide-Medal Biogaz System clean LFG to pipeline quality standards. 340,000 MMBTU/year in 2020. Gas to go to SCG customers through pipeline, and to SCG's fleet. | K77: 1.96 | N77: =O77/(365*0.001*0.9) -> 1035007.6 | O77: 340000 | P77: BOTH | Q77: No | R77: =O77/0.112194 -> 3030465.1 | U77: 238600 | W77: Yes | X77: https://www.wasteconnections.com/meadowbranch-landfill/ https://www.waste360.com/waste-energy/southern-company-gas-assumes-control-meadow-branch-renewable-natural-gas-facility
A78: North Shelby Landfill (Republic, Archaea) | B78: OPERATIONAL | C78: Landfill, Republic Services, Inc. Gas upgrading, Archaea Energy & BP | D78: 15145099 | F78: Shelby | G78: TN | H78: 9/20/2014 | I78: Clean Energy Fuels | J78: High-BTU plant, with product to be injected into the natural gas grid, some contracts but there is some that gets to transportation throught two MLGW CNG fueling stations. Plant is anticipated to produce ~4 million DGE of renewable natural gas fuel annually, steadily increasing to more than 5.7 million DGE annually during the first 10 years of operations. Uses pressure swing adsorption (PSA) upgrading technology. | K78: 2.53 | N78: =K78*1000000*0.55 -> 1391500 | O78: =N78*(0.001*365*0.9) -> 457107.75 | P78: PIPELINE (For vehicle/other) | Q78: No | R78: =O78/0.112194 -> 4074262 | S78: =4000000*1.147 -> 4588000 | T78: N/A | W78: Yes | X78: https://www.cleanenergyfuels.com/release-archive/republic-services-clean-energy-sign-renewable-biomethane-recovery-agreement-for-tennessee-landfill/ https://comptroller.tn.gov/content/dam/cot/energy-policy-council/documents/ SEPC_2020_Assessment_Final.pdf
A79: South Shelby (Republic, Archaea) | B79: OPERATIONAL | C79: Landfill, Republic Services; upgrading, Archaea Energy | D79: 33221124 | E79: 1200 | F79: Shelby | G79: TN | H79: Q3 2020 | I79: Aria Energy (through our Mavrix JV) | J79: 6000 SCFM LFG to RNG project. Accroding to Wste Today, can produce 33250 GGE daily, selling to BP who will take it to California market, also selling to utilities who want to offer their customers options. | K79: 8.64 | L79: 5.185 | N79: =O79/(365*0.001*0.9) -> 2776255.7 | O79: 912000 | P79: BOTH | Q79: No | R79: =O79/0.112194 -> 8128776.9 | X79: https://www.dailymemphian.com/article/1270/Renewable-gas-firm-files-33M-permit-for-facility-near-Memphis-landfill https://www.wastetodaymagazine.com/article/republic-services-aria-energy-bp-landfill-gas-rng/ https://www.biofuelsdigest.com/bdigest/2020/08/20/tennessee-landfill-gas-rng-project-commissioned-by-bp-and-partners/ https://bioenergyinternational.com/republic-services-aria-energy-and-bp-partner-on-new-landfill-gas-to-rng-project/
A80: Atascocita/Humble (WM, Montauk) | B80: OPERATIONAL | C80: Landfill, Waste Management; upgrading, Montauk Energy | D80: 37827294 | E80: 3835 | F80: Harris | G80: TX | H80: Q2 2019 | I80: Montauk Energy Capital | J80: Using membrane separation upgrading technology | K80: 10.8 | L80: 9.046 | M80: 2.96 | N80: =O80/(0.001*365*0.9) -> 6188888.9 | O80: =5570*365 -> 2033050 | P80: PIPELINE (For vehicle/other) | Q80: No | R80: =O80/0.112194 -> 18120844 | S80: 12054784 | T80: N/A | W80: Yes | X80: http://montaukenergy.com/operations/atascocity-rng/ https://docs.google.com/spreadsheets/d/1CpLTd1Yya4qQzUpWYtKMUGW1BlMmn-Jrj3uErd8lJ7A/edit?usp=sharing http://montaukenergy.com/wp-content/uploads/2019/08/1-Chief-Executive-Officers-Report.pdf
A81: Coastal Plains RNG | B81: OPERATIONAL | C81: Landfill, Waste Management; upgrading facility, Montauk Energy | D81: 22370865 | E81: =419000/310 -> 1351.6129 | F81: Galveston | G81: TX | H81: 43739 | I81: Montauk, Waste Management | J81: Coastal Plains is currently one of Montauk's landfill gas-to-electric facilities in the Houston metropolitan area that they will be converting to a Renewable Natural Gas (RNG) facility. They currently own and operate the landfill gas-to-electric power generation facility on the Coastal Plains, Waste Management landfill. They will be upgrading the plant to design, own and operate the gas processing facility. Using BioFerm two-stage PSA gas upgrading system. Montauk will design, own and operate the gas processing facility. Montauk website says 1857 MMBTU/day. Montauk investor presentation says 1,775 MMBTU/day | K81: =(N81/5.5*10)/1000000 -> 3.2272727 | L81: 2.774 | M81: 2.774 | N81: =O81/(0.001*365*0.9) -> 1775000 | O81: =1775*365*0.9 -> 583087.5 | P81: PIPELINE (For vehicle/other) | S81: =O81/0.112194 -> 5197136.2 | X81: http://montaukenergy.com/operations/coastal-plains-rng/ https://www.biofermenergy.com/milestones https://www.wmsolutions.com/pdf-tracker/index/id/33/campaignType/28 https://ir.montaukrenewables.com/static-files/b75685aa-813b-40fc-b02d-97f620fb2451
A82: Edinburg Landfill (Morrow) | B82: OPERATIONAL | C82: City of Edinburg. TX | D82: 12221415 | F82: Hidalgo | G82: TX | H82: 42491 | I82: Morrow Renewables | J82: Upgrading system is Solexol style modified physical solvent | K82: 2.23 | N82: =K82*1000000*0.55 -> 1226500 | O82: =N82*(0.001*365*0.9) -> 402905.25 | P82: PIPELINE (For vehicle/other) | Q82: No | R82: =O82/0.112194 -> 3591147.9 | T82: None | U82: 212800 | W82: Yes | X82: http://www.wastedive.com/news/morrow-energy-steps-in-to-help-texas-city-get-wte-plant/406302/ https://cityofedinburg.com/departments/solid_waste_management_landfill/landfill_high_btu_project.php
A83: Fort Bend Regional Landfill (DTE Biomass Energy) | B83: OPERATIONAL | C83: Landfill, Waste Corporation of Texas, LLC; gas upgrading, DTE Biomass Energy | D83: 11725348 | E83: 3000 | F83: Fort Bend | G83: TX | H83: Jun-13 | I83: DTE Biomass Energy, Inc.; Enerdyne Power Systems, Inc.; Morrow Renewables, LLC | J83: Treats landfill gas using Selexol technology to be used by GHI Energy in the transportation fuel markets and pumped into a pipeline for public use. Physical solvent process with patented enhancements and catalytic oxygen removal to remove CO2, H2O, H2S, siloxanes, and other impurities. Gas sent down pipeline for use by 3rd party as vehicle fuel. Fall 2017, upgrade to double plant capacity to 8.0 Million SCFD inlet LFG flow. LMOP lists LFG flow to project as 2.54 mmscfd. Project built by Enerdyne, acquired in 2017 by DTE. | K83: 8 | N83: 3700000 | O83: 753000 | P83: PIPELINE (For vehicle/other) | Q83: No | R83: 11843885 | S83: 14404725 | T83: N/A | U83: 242400 | W83: Yes | X83: https://www.epa.gov/sites/production/files/2016-05/documents/10ftbend.pdf https://dtevantage.com/project/fort-bend-power-producers-llc/ https://www.wastetodaymagazine.com/article/dte-biomass-energy-acquires-texas-landfill-to-gas-projects/ https://dailyenergyinsider.com/featured/5481-acquisition-texas-renewable-gas-facilities-dte-biomass-looks-expand-landfill-operations/
A84: Galveston County Landfill | B84: OPERATIONAL | C84: Landfill, Republic Services; upgrading facility, Montauk Energy | D84: 18203314 | F84: Galveston | G84: TX | H84: September 2019 | I84: Montauk Energy, Republic Services | J84: The Galveston landfill is owned and operated by Republic Services in Galveston, Texas. Montauk operate the landfill gas collection system and is the owner and operator of the gas processing facility. Gas upgrading is BioFerm, possible combination of PSA, TSA, activated carbon. 1857 mmbtu/day | K84: 3.6 | L84: 3.79 | M84: 0.109 | N84: =O84/(0.001*365*0.9) -> 2063333.3 | O84: =1857*365 -> 677805 | P84: PIPELINE (For vehicle/other) | Q84: No | R84: =O84/0.112194 -> 6041365.8 | U84: 34600 | W84: Yes | X84: http://montaukenergy.com/operations/galveston/ https://www.biofermenergy.com/milestones
A85: Garland/Charles M. Hinton Jr. Regional Landfill | B85: OPERATIONAL | C85: City of Garland | D85: 7262368 | F85: Dallas | G85: TX | H85: Q4 2021 | I85: City of Garland, Morrow Renewables | J85: According to RFP, landfill has a gas collection system but is flaring everything. Landfill manager foresees construction starting in Q4 2020. Production will start off at about 2000 SCFM of upgraded gas, ramping up to 2500-3500. I've based estimates on 3000. Morrow Renewables won the RFP, are developing gas upgrading system. | L85: 2.614 | M85: 2.614 | N85: =3000*60*24 -> 4320000 | O85: =N85*0.001*365*0.9 -> 1419120 | P85: PIPELINE (For vehicle/other) | R85: =O85/0.112194 -> 12648805 | X85: https://www.bidnet.com/bneattachments?/574986152.pdf https://garlandtx.gov/DocumentCenter/View/7854/May-2020---Garland-City-Press https://www.atmosenergy.com/newsroom/earth-day-2022-delivering-sustainable-solutions-achieve-low-carbon-energy-future
A86: Greenwood Farms Landfill/Tyler (Morrow "East Texas") | B86: OPERATIONAL | C86: Landfill owned by City of Tyler, operated by Republic Services. Energy facility owned by Morrow Renewables | D86: 10818393 | F86: Smith | G86: TX | H86: 39925 | I86: Morrow Renewables, LLC | J86: Creates high BTU RNG injected into the pipeline infrastructure; landfill truck fleet powered by on-site CNG refueling station. Physical solvent process with patented enhancements to remove CO2, H2O, H2S, siloxanes, and other impurities from LFG; gas used down the pipeline for vehicle fuel. | K86: 1.64 | N86: =O86/(0.001*365*0.9) -> 1012374.4 | O86: 332565 | P86: BOTH | Q86: Private | R86: =O86/0.112194 -> 2964195.9 | U86: 156500 | W86: Yes | X86: https://www.cityoftyler.org/government/departments/solid-waste/landfill https://morrowrenewables.com/portfolio/ http://www.globalmethane.org/documents/toolsres_lfg_IBPGAppendixA.pdf
A87: McCarty Road Landfill (Republic, Montauk) | B87: OPERATIONAL | C87: Montauk Renewables | D87: 101097794 | F87: Harris | G87: TX | H87: 31472 | I87: Montauk Energy | J87: Selexol process is used to separate CO2 and CH4. Plant capacity is 9.2 mmscfd inlet. Gas end users are commercial fleet vehicles. | K87: 6.61 | N87: =K87*1000000*0.55 -> 3635500 | O87: =N87*(0.001*365*0.9) -> 1194261.8 | P87: PIPELINE (For vehicle/other) | Q87: Public | R87: =O87/0.112194 -> 10644613 | X87: http://montaukenergy.com/operations/mccarty/
A88: McCarty Road Landfill #2 (Republic, Montauk) | B88: OPERATIONAL | C88: Republic Services, Inc., landfill. U.S. Gain offtaker Ameresco owns upgrading system, operates gas collection system | D88: 101097794 | F88: Harris | G88: TX | H88: 44317 | I88: Ameresco | J88: Ameresco update, facility has nameplate capacity of 4500 scfm of landfill gas. Supply agreement with US Gain who have a public fueling station in Houston. | K88: 1.6 | N88: =O88/(0.001*365*0.9) -> 3348554 | O88: 1100000 | P88: PIPELINE (For vehicle/other) | R88: =O88/0.112194 -> 9804445.9 | U88: 61000 | X88: https://www.businesswire.com/news/home/20210112005747/en/Ameresco-Reaches-Mechanical-Completion-of-Landfill-Gas-to-Renewable-Natural-Gas-Plant https://www.businesswire.com/news/home/20210715005347/en/
A89: McCommas Bluff Landfill (Energy Power Partners) | B89: OPERATIONAL | C89: City of Dallas, Energy Power Partners | D89: 51736229 | F89: Dallas | G89: TX | H89: 39448 | I89: Cambrian Energy Development, Clean Energy Fuels | J89: Creates high BTU RNG injected into the pipeline infrastructure. Original gas cleaning equipment included: SulfaTreat, temperature swing adsorption (TSA), pressure swing adsorption (PSA) for CO2 removal, and thermal oxidizer. Facility capacity: inlet 15.5 mmscfd raw LFG is capable of producing 9,000 MMBtu/day of renewable natural gas; the RNG is predominantly used to produce renewable electric power by a municipal utility in California. | K89: 11.3 | N89: =K89*1000000*0.55 -> 6215000 | O89: =N89*0.001*365*0.9 -> 2041627.5 | P89: PIPELINE (For vehicle/other) | Q89: No | R89: =O89/0.112194 -> 18197297 | U89: 1078400 | W89: Yes | X89: https://www.businesswire.com/news/home/20210715005347/en/
A90: North Texas Municipal Water District, Melissa ("NTMWD") (Morrow) | B90: OPERATIONAL | C90: Landfill, North Texas Water District; upgrading operation, Morrow Renewables | D90: 11704886 | F90: Collin | G90: TX | I90: Morrow Renewables | J90: Physical solvent process with patented enhancements and catalytic oxygen removal - removes CO2, H2O, H2S, siloxanes, and other impurities from LFG; gas is transported 5.5 miles and sold into adjoining natural gas pipeline | K90: 6.17 | N90: =K90*1000000*0.55 -> 3393500 | O90: =N90*(0.001*365*0.9) -> 1114764.8 | P90: PIPELINE (For vehicle/other) | Q90: No | R90: =O90/0.112194 -> 9936046 | U90: 588800 | W90: Yes | X90: http://biomassmagazine.com/articles/14873/rng-coalition-celebrates-new-projects-launches-video https://www.ntmwd.com/ntmwd-celebrates-completion-of-renewable-energy-gas-plant-in-melissa/ https://www.dallasnews.com/news/2017/12/26/turning-trash-into-cash-converting-landfill-gas-to-renewable-natural-gas-creates-new-revenue/
A91: Pine Hill/Longview (Kilgore) (Morrow) | B91: OPERATIONAL | C91: Morrow Renewables | D91: 12818995 | F91: Gregg, Rusk | G91: TX | I91: Morrow Renewables | J91: Plant can generate 404.7 million cubic feet of renewable natural gas per year | K91: 2.45 | N91: =K91*1000000*0.55 -> 1347500 | O91: =N91*(0.001*365*0.9) -> 442653.75 | P91: PIPELINE (For vehicle/other) | Q91: No | R91: =O91/0.112194 -> 3945431.6 | W91: Yes | X91: https://www.longviewtexas.gov/2704/Pine-Hill-Landfill http://biomassmagazine.com/articles/14873/rng-coalition-celebrates-new-projects-launches-video https://issuu.com/bbiinternational/docs/rngmap21_digital https://www.kltv.com/story/36406324/methane-from-pine-hill-landfill-will-now-be-converted-to-renewable-natural-gas/ https://www.waste360.com/gas-energy/republic-unveils-northeast-texas-landfill-renewable-energy-facility
A92: Renovar Arlington | B92: OPERATIONAL | C92: Mas Energy | D92: 26760100 | F92: Tarrant | G92: TX | I92: Mas Energy | J92: Since 1999, the City of Arlington has had an agreement with Renovar Arlington Ltd. to operate and maintain the landfill gas collection and control system. Renovar’s newly-constructed renewable natural gas facility collects biogases in Arlington and Fort Worth to be processed and sold for transportation fuel. Is it taking all the output form both sites? According to LMOP, electricity production at Fort Worth has been shut down, so assuming that all gas from there is flowing to Renovar. 5100 scfm RNG. | K92: =N92/(0.55*1000000) -> 13.352727 | L92: 13.352727 | N92: =5100*24*60 -> 7344000 | O92: =N92*(0.001*365*0.9) -> 2412504 | P92: PIPELINE (For vehicle/other) | Q92: Unknown | R92: =O92/0.112194 -> 21502968 | T92: Stopped electricity production | W92: Yes | X92: https://www.arlingtontx.gov/city_hall/departments/garbage_recycling/garbage_disposal/landfill https://bioenergyinternational.com/biogas/american-biogas-council-announces-2019-biogas-award-winners https://www.businesswire.com/news/home/20210720005989/en/CIM-Group-Invests-in-Affiliate-of-MAS-Energy-Renewable-Natural-Gas-Developer https://www.arlingtontx.gov/news/my_arlington_t_x/news_stories/biogas_honor https://usgasvehicles.com/en/rng-coalition-celebrates-new-2019-production-facilities-to-open-rng-2019-conference/
A93: Republic Services Blue Ridge Landfill ("Houston") (Morrow) | B93: OPERATIONAL | C93: Morrow Renewables | D93: 23494698 | F93: Fort Bend | G93: TX | I93: Morrow Renewables | J93: Physical solvent process with patented enhancements and catalytic oxygen removal - removes CO2, H2O, H2S, siloxanes, and other impurities from LFG; gas is transported and sold into adjoining natural gas pipeline. 2020, according to LMOP a boiler project that was consuming 4.32 MMSCFD was shut down in 2018, increasing gas flow to RNG project. Currently processing 8,0000 scfm LFG with room for a total of 13,000 scfm. Capacity expected to grow each year, final gathering system will have a capacity of 30,000 scfm LFG in 45 years. | K93: =(8000*60*24)/1000000 -> 11.52 | N93: =K93*1000000*0.55 -> 6336000 | O93: =N93*(0.001*365*0.9) -> 2081376 | P93: PIPELINE (For vehicle/other) | Q93: No | R93: =O93/0.112194 -> 18551580 | U93: 935200 | W93: Yes | X93: http://blueridgelandfill.com/ http://site.republicservices.com/corporate/planet/renewableenergy/landfill-gas-energy.aspx https://morrowenergy.com/where-we-operate.html
A94: Seabreeze Environmental Landfill (Seabreeze, DTE Biomass) | B94: OPERATIONAL | C94: Seabreeze Environmental; gas upgrading, DTE Biomass Energy | D94: 24649546 | E94: 4500 | F94: Brazoria | G94: TX | H94: 43908 | I94: DTE Biomass Energy, Inc.,. Waste Connections, Inc. | J94: Biomethane will be sent down the pipeline for use as vehicle fuel by a third party. Upgrading done by physical solvent process with patented enhancements and catalytic oxygen removal to remove CO2, H2O, H2S, siloxanes, and other impurities from LFG | K94: 5.8 | L94: 3.8 | N94: 3400000 | O94: 636000 | P94: PIPELINE (For vehicle/other) | Q94: No | R94: 10883570 | S94: 16645460 | T94: N/A | U94: 334700 | W94: Yes | X94: http://www.seabreezelandfill.com/ http://www.wasteconnectionsangleton.com/landfill http://newsroom.dteenergy.com/2017-05-25-DTE-Biomass-Acquires-Renewable-Natural-Gas-Facilities#sthash.pxgaKaX9.dpbs
A95: Skyline Landfill | B95: OPERATIONAL | C95: Landfill, Waste Management | D95: 25930783 | F95: Ellis | G95: TX | H95: Feb. 2020 | I95: WM Renewable Energy, LLC | J95: Creates high BTU RNG injected into the pipeline infrastructure | K95: 4.47 | N95: =K95*1000000*0.55 -> 2458500 | O95: =N95*(0.001*365*0.9) -> 807617.25 | P95: PIPELINE (For vehicle/other) | Q95: Yes | R95: =O95/0.112194 -> 7198399.6 | W95: Yes | X95: https://ensoplastics.com/theblog/?p=3069 https://www.scsengineers.com/scs-project-case-stu/scs-energy-lfg-to-pipeline-rng-plant-in-texas/
A96: Tessman Road (Coalition database) | B96: OPERATIONAL | C96: Republic Services | D96: 33483064 | F96: Bexar, Medina, Comal | G96: TX | H96: Fall 2021 | I96: Republic Services, EDL | J96: RNG to pipeline with local bus refueling station (VIA) to buy the RINs. Will 'provide' RNG to 75% of the city's 500-bus fleet. All gas collected will go to upgrading project. | K96: 6.59 | L96: 6.59 | M96: 0 | N96: =K96*1000000*0.55 -> 3624500 | O96: =N96*0.001*365*0.9 -> 1190648.3 | P96: BOTH | Q96: No | R96: =O96/0.112194 -> 10612406 | X96: https://wastebits.com/locator/location/tessman-road-landfill https://ofmpub.epa.gov/frs_public2/fii_query_detail.disp_program_facility?p_registry_id=110002371781 https://sanantonioreport.org/waste-gas-from-landfill-will-offset-up-to-75-of-vias-bus-fuel-demand/
A97: Turkey Creek Landfill/Alvarado (Morrow) | B97: OPERATIONAL | C97: IESI | D97: 11022493 | E97: 2000 | F97: Johnson | G97: TX | H97: 40998 | I97: Morrow Renewables, LLC | J97: Physical solvent process with patented enhancements and catalytic oxygen removal - removes CO2, H2O, H2S, siloxanes, and other impurities from LFG. Gas is transported and sold into adjoining natural gas pipeline. According to Morrow website, Turkey Creek producing 3000 SCFM raw (?) gas | K97: 4.32 | N97: =K97*1000000*0.55 -> 2376000 | O97: =N97*(0.001*365*0.9) -> 780516 | P97: PIPELINE (For vehicle/other) | Q97: No | R97: =O97/0.112194 -> 6956842.6 | U97: 116400 | W97: Yes | X97: https://www.wasteconnections.com/turkey-creek-landfill http://www.prweb.com/releases/2012/10/prweb10047799.htm https://morrowenergy.com/landfill-development.html#where-we-have-developed
A98: Twin Oaks | B98: OPERATIONAL | C98: Morrow Renewables | F98: Grimes | G98: TX | H98: 45121 | I98: Morrow Renewables | J98: Figures come from RNG Coalition. Says being used for transportation fuel. | O98: 393479 | P98: UNKNOWN | S98: 6139193 | X98: Went operational in 2023
A99: Corpus Christi Renewables (Cefe Valenzuela Landfill) | B99: OPERATIONAL | C99: City of Corpus Christi, TX | D99: 6273694 | F99: Nueces | G99: TX | H99: 45200 | I99: Morrow Renewables | J99: This facility was commissioned in October 2023 with a capacity of 4,000 SCFM. Calculations of output based on LMOP data. RNG is pipeline injected and used for transportation. | K99: 1.7 | N99: =(K99*1000000)*0.55 -> 935000 | O99: =N99*0.001*365*0.9 -> 307147.5 | P99: PIPELINE (For vehicle/other) | X99: https://morrowenergy.com/about/case-studies/corpus-christi-renewables-transforming-landfill-gas-into-clean-renewable-natural-gas/https://news.cctexas.com/news/landfill-gas-project-expands-to-j-c-elliott-landfill
A100: Swift Creek Renewables (Shoosmith Landfill) | B100: OPERATIONAL | C100: Shoosmith Brothers | D100: 27975091 | F100: Chesterfield | G100: VA | H100: 45170 | I100: Morrow Renewables | J100: This facility was commissioned in September 2023 with a capacity of 10,000 SCFM. Calculations of output based on LMOP data. RNG is pipeline injected and used for transportation. | K100: 7.2 | N100: =(K100*1000000)*0.55 -> 3960000 | O100: =N100*0.001*365*0.9 -> 1300860 | P100: PIPELINE (For vehicle/other) | X100: https://www.chesterfieldobserver.com/articles/proposed-biogas-facility-at-shoosmith-landfill-promises-to-cut-the-smell-and-the-carbon-footprint/ https://www.linkedin.com/posts/morrowenergy_landfills-landfillgas-renewablenaturalgas-activity-7165366708738646017-GpYw/ https://morrowenergy.com/about/case-studies/swift-creek-renewables-transforming-landfill-gas-into-clean-renewable-natural-gas/
...

Sheet Livestock, agriculture
A1: KEY: | B1: Project added 2023 | H1: Color coding generally applies to numeric values only.
B2: Value calculated based on other info provided | H2: Individual values are often drawn from different sources, and so may appear inconsistent-- e.g., gas going for upgrading may be more than total amount of gas collected
B3: Information provided or confirmed by contact
B4: Value from Agstar, EPA Part 80 database
B5: Value from press/website, including CA Dept. of Ag
A7: GENERAL INFORMATION | F7: PROJECT INFORMATION | L7: INPUTS | O7: OUTPUTS | V7: ADDITIONAL INFORMATION
A8: Farm/Project Name | B8: Projected status 12/31/2023 | C8: Farm Type | D8: Farm County | E8: State | F8: Project Start Date | G8: Gas production began/ projected to begin | H8: Project Developer | I8: Digester Type | J8: Baseline System | K8: Project Description | L8: Population Feeding Digester | M8: Input in tons/year | N8: SCFD raw gas to project | O8: SCFD Upgraded gas | P8: MMBTU/yr | Q8: RNG Disposition | R8: If producing vehicle fuel, public filling station? | S8: GGE/yr | T8: Capacity (GGE/yr) | U8: Electricity | V8: CO2E Emissions Eliminated (metric tonnes/yr) | W8: Project Scale | X8: Co-Digestion | Y8: System Vendors | AA8: RIN Registrant? | AB8: References
A9: OPERATIONAL AS OF 12/31/2023
A10: Butterfield Dairy | B10: OPERATIONAL | C10: Dairy | D10: Maricopa | E10: AZ | F10: Construction began 6/29/21 | G10: 3/30/2023 | H10: Avolta, Atlas Global Holdings, DVO, Butterfield Dairy. Facility will be operated and maintained by Nacelle Solutions, of which Avolta is a subsidiary. | I10: Mixed plug flow | K10: With Butterfield Dairy in Buckeye, will accept over 110,000 tons of manure annually. This project produces over 300,000 MMBTU of RNG annually. | L10: 25000 | M10: ~55,000 | P10: 300000 | Q10: PIPELINE (For vehicle/other) | S10: =P10/0.112194 -> 2673939.8 | AB10: https://www.azfamily.com/news/buckeye-dairy-farm-converting-poop-to-power/article_2001a5fa-501c-11e9-97ba-8ba3d4f40913.html https://tucson.com/business/poo-power-renewable-gas-projects-sprout-at-arizona-sewer-plant-dairies/article_56bb567a-b1c9-11eb-98f6-7b59dad30212.html https://www.abc15.com/news/region-west-valley/buckeye/buckeye-dairy-turns-cow-poop-into-power http://biomassmagazine.com/articles/18094/southwest-gas-to-source-rng-from-5-projects https://www.naturalgasintel.com/southwest-gas-readies-five-rng-projects/ https://patch.com/arizona/phoenix/calendar/event/20210629/1085343/avolta-breaks-ground-on-first-of-series-of-biogas-projects-in-az https://www.avoltadevelopment.com/agriculture/ https://nacellesolutions.com/project/dairy-projects/ https://www.swgas.com/en/news/southwest-gas-expands-renewable-natural-gas-interconnects
A11: MIlky Way Dairy, Maricopa | B11: OPERATIONAL | C11: Dairy | D11: Maricopa | E11: AZ | F11: Construction began 6/29/21 | G11: 45015 | H11: Avolta, Atlas Global Holdings, DVO, Butterfield Dairy. Facility will be operated and maintained by Nacelle Solutions, of which Avolta is a subsidiary. | I11: Mixed plug flow | K11: With Butterfield Dairy in Buckeye, will accept over 110,000 tons of manure annually. This project produces over 375,000 MMBTU of RNG annually. | L11: 25000 | M11: ~55,000 | P11: 375000 | Q11: PIPELINE (For vehicle/other) | S11: =P11/0.112194 -> 3342424.7 | AB11: https://tucson.com/business/poo-power-renewable-gas-projects-sprout-at-arizona-sewer-plant-dairies/article_56bb567a-b1c9-11eb-98f6-7b59dad30212.html http://biomassmagazine.com/articles/18094/southwest-gas-to-source-rng-from-5-projects https://patch.com/arizona/phoenix/calendar/event/20210629/1085343/avolta-breaks-ground-on-first-of-series-of-biogas-projects-in-az https://www.naturalgasintel.com/southwest-gas-readies-five-rng-projects/ https://www.avoltadevelopment.com/agriculture/ https://nacellesolutions.com/project/milky-way-dairy-project/
A12: Sunoma Renewable Biofuel Project (Paloma Dairy) | B12: OPERATIONAL | C12: Dairy | D12: Maricopa | E12: AZ | F12: 9.1.2020 | G12: October 2021 | H12: Paloma Dairy; Fortistar; Industrial Services Co; Montrose Environmental; TruStar Energy | I12: Covered lagoon and CSTR | K12: According to press release project is specifically developing fuel for Class 8 vehicles. Montrose Water and Sustainability Services, a division of Montrose Environmental Group, completed design and engineering for the project as well as equipment procurement. Montrose’s subject matter experts will provide construction oversight, along with startup and commissioning support for the project. Industrial Services Company (ISC) will lead the building of the system. Project financing by Live Oak Bank. Telcon Fortistart 9.15.20, they are building both the digesters and the upgrading equipment. There will be a covered lagoon, and they will also have a three tank CSTR from PlanET. Upgrading via Air Liquide membrane system. | L12: 14000 | N12: =O12/0.6 -> 910757.99 | O12: =P12/(0.001*365*0.9) -> 546454.79 | P12: =S12*0.112194 -> 179510.4 | Q12: PIPELINE (For vehicle/other) | R12: No | S12: 1600000 | V12: 89794 | W12: Farm scale | Y12: PlanET | AB12: https://www.businesswire.com/news/home/20200831005436/en/Fortistar-Paloma-Dairy-Construction-Renewable-Natural-Gas https://tucson.com/business/poo-power-renewable-gas-projects-sprout-at-arizona-sewer-plant-dairies/article_56bb567a-b1c9-11eb-98f6-7b59dad30212.html http://biomassmagazine.com/articles/17336/fortistar-paloma-dairy-begin-construction-on-rng-facility http://biomassmagazine.com/articles/18094/southwest-gas-to-source-rng-from-5-projects https://www.naturalgasintel.com/southwest-gas-readies-five-rng-projects/
A13: Wastewater Opportunity Fund Southwest GGP LLC (Green Gas Partners Stanfield Project) | B13: OPERATIONAL | C13: Dairy | D13: Pinal | E13: AZ | F13: 2018 | G13: May 2019 | H13: Green Gas Partners | K13: Co-digestion of manure with fats, oils and grease. At 100%, will produce 6 million CFD. SCFD figure to right is based on 60% ramp-up. As of June 2020, still operating at 60% due to need to replace some equipment. Injecting into pipeline. Project is co-located on T&K Red RIver Dairy, but they have no stake in the project, just supply manure. Upgraded SCFD value based on 6MM * .6. | L13: 55000 | O13: 3600000 | P13: =O13*0.001*365*0.9 -> 1182600 | Q13: PIPELINE (For vehicle/other) | R13: Unknown | S13: =P13/0.112194 -> 10540671 | T13: =S13/6*10 -> 17567784 | AA13: Yes | AB13: https://www.cattlemaps.com/feedlot/tk-red-river-dairy/ http://www.macdon.com/en/performance/story/big-cheese https://impactalpha.com/tapping-the-municipal-bond-market-for-green-distributed-infrastructure/ https://www.prnewswire.com/news-releases/suburban-propane-partners-lp-to-acquire-renewable-natural-gas-rng-production-assets-from-equilibrium-capital-group-and-establishes-partnership-for-the-development-of-additional-rng-projects-301710493.html
A14: 4K Dairy (Calgren Dairy Fuels Cluster) | B14: OPERATIONAL | C14: Dairy | D14: Tulare | E14: CA | G14: 2020 | H14: Calgren/Maas Energy Works | J14: Covered lagoon | K14: 4K Dairy Digester Pipeline Project is a new covered lagoon digester processing dairy manure in Tulare County, California. The project is a part of the Calgren Dairy Fuels Cluster, developed by Maas Energy Works. The Calgren Dairy Fuels Cluster has already laid four miles of pipeline and begun construction of three digesters awarded CDFA funds in late 2017--scheduled to provide the state's first pipeline diary biogas fuel by June of 2018. The methane-rich biogas from the digester will be transported via private, low-pressure pipeline to the cluster's central hub near the Calgren ethanol refinery. Once at the hub, it will be used to fuel partner and public trucks at an on-site compressed natural gas fueling station. The remainder of the gas will be injected into the adjacent SoCalGas utility pipeline for delivery to other CNG fueling stations around the Central Valley and the state. | L14: 5000 | N14: =O14/0.6 -> 298569.89 | O14: =P14/(0.001*365*0.9) -> 179141.94 | P14: =S14*0.112194 -> 58848.126 | Q14: BOTH | R14: Unknown | S14: =4572983/10*1.147 -> 524521.15 | V14: 39196 | AA14: Yes | AB14: https://www.cdfa.ca.gov/oefi/ddrdp/docs/2018_DDRDP_ProjectsAwarded.pdf https://www.cdfa.ca.gov/oefi/DDRDP/docs/DDRDP_Project_Level_Data.pdf https://www.arb.ca.gov/cc/capandtrade/auctionproceeds/historicdata_2020AR.xlsx
A15: ABEC Lakeview Farms Dairy Digester (Kern Cluster) | B15: OPERATIONAL | C15: Dairy | D15: Kern | E15: CA | F15: 42538 | G15: Began 2/13/2018 | H15: California Bioenergy | I15: Covered Lagoon | K15: Part of Kern Dairy Biogas Cluster | L15: 7000 | N15: 360000 | O15: =N15*0.6 -> 216000 | P15: =O15*0.001*365*0.9 -> 70956 | Q15: BOTH | R15: No | S15: =P15/0.112194 -> 632440.24 | U15: 6700 MWh | V15: 60350 | W15: Multiple farm/facility | AB15: http://www.awma-goldenempire.org/store/files/61.pdf https://www.socalgas.com/1443741246975/Meeting-the-Methane-reduction-challenge_WestCoastAdv.pdfhttp://4c-global.com/2017/06/13/lakeview-farms-anaerobic-digester/http://kerncountyenergysummit.com/assets/neil-black-calbio_kern-energy-summit---11-8-17_final.pdfhttps://www.bakersfield.com/news/state-awards-million-to-help-harness-biogas-at-kern-dairies/article_3bdf7a87-223f-5121-bea6-c0365fecd1e1.htmlhttp://calbioenergy.com/projects/ https://www.cdfa.ca.gov/oefi/DDRDP/docs/DDRDP_Project_Level_Data.pdf
A16: Ackerman Dairy (Aemetis Cluster) | B16: OPERATIONAL | C16: Dairy | D16: Stanislaus | E16: CA | F16: 43282 | G16: Planned completion 12/15/2020 | H16: Maas Energy Works | I16: Covered lagoon | K16: Ackerman Dairy Digester Pipeline Project is a new covered lagoon digester processing dairy manure in Stanislaus County, California. The project is a part of the Aemetis Cluster, developed by Maas Energy Works. The methane-rich biogas from the digester will be transported via private, low-pressure pipeline to the cluster's central hub near at the Aemetis ethanol refinery. Once at the hub, most of the biogas will be used to fuel partner trucks at an on-site compressed natural gas fueling station. The remainder of the gas will be used on site to fuel boilers at the Aemetis ethanol refinery to make very low carbon vehicle fuel. | L16: 4300 | N16: =O16/0.6 -> 149269.37 | O16: =P16/(0.001*365*0.9) -> 89561.625 | P16: =S16*0.112194 -> 29420.994 | Q16: BOTH | R16: Private | S16: =2286253/10*1.147 -> 262233.22 | V16: 34137 | W16: Farm | AB16: https://www.cdfa.ca.gov/oefi/ddrdp/docs/2018_DDRDP_ProjectsAwarded.pdf \\ https://www.cdfa.ca.gov/oefi/DDRDP/docs/DDRDP_Project_Level_Data.pdf https://www.arb.ca.gov/cc/capandtrade/auctionproceeds/historicdata_2020AR.xlsx
A17: Ahlem Farms Jerseys AAFK Central Dairy Digester Cluster | B17: OPERATIONAL | C17: Dairy | D17: Stanislaus | E17: CA | F17: 44228 | G17: 44957 | H17: Aemetis Biogas | I17: Covered lagoon | K17: The Aemetis Biogas project team will install a covered lagoon digester at the project site. When complete, the proposed digester will produce biogas, which after being processed to remove hydrogen sulfide (H2S), will be conveyed via private pipeline to the Aemetis Advanced Fuels Keyes facility. There, Aemetis will further upgrade the biogas to pipeline-quality, negative-carbon-intensity renewable natural gas (RNG) suitable for use as transportation fuel. Aemetis will sell a portion of the RNG to local fleets via its onsite RNG fueling station and will direct the remainder to sale to larger fleets such as UPS, PepsiCo, LA Metro, and Toyota via the Pacific Gas & Electric (PG&E) pipeline, or for use as energy at AAFK to produce renewable ethanol, thus replacing carbon-based natural gas. The project will serve as one of 17 foundational digesters in the Aemetis Central Dairy Digester Cluster in Stanislaus and Merced Counties, an area with minimal CDFA investment. Aemetis plans to grow this cluster to 30 dairies by 2023. Aemetis Biogas LLC will complete and commission the first two dairy digester projects in the cluster, and related four-mile private gas pipeline, in May 2020. | O17: =P17/(0.001*365*0.9) -> 323643.84 | P17: 106317 | Q17: BOTH | R17: Public | S17: =P17/0.112194 -> 947617.52 | V17: 11398 | AB17: http://biomassmagazine.com/articles/15849/aemetis-closes-on-dairy-digester-rng-equity-investment http://www.aemetis.com/aemetis-biogas-project-awarded-4-1-million-grant-for-biogas-upgrading/ http://www.aemetis.com/aemetis-closes-non-dilutive-30-million-equity-investment-to-build-biomethane-pipelines-and-dairy-digesters-to-produce-below-zero-carbon-renewable-natural-gas-rng/https://www.cdfa.ca.gov/oefi/ddrdp/docs/DDRDP_Report_March2021.pdf https://www.cdfa.ca.gov/oefi/DDRDP/docs/DDRDP_Project_Level_Data.pdf https://www.cdfa.ca.gov/oefi/DDRDP/docs/DDRDP_Project_Level_Data.pdf https://biomassmagazine.com/articles/19051/aemetis-completes-third-dairy-digester-expands-biogas-production
A18: Albert Goyenetche Dairy Biogas (Buttonwillow cluster) | B18: OPERATIONAL | C18: Dairy | D18: Kern | E18: CA | F18: 12/1/2019 ? | G18: 44530 | H18: California Bioenergy | I18: Covered lagoon | J18: manure pond | K18: Albert Goyenetche Dairy is part of the Buttonwillow dairy biogas to fuel cluster in Kern County, CA. The dairy will install a Tier 1 designed manure only covered lagoon digester with integrated gas storage and pre-treatment. An on-dairy biogas conditioning and compressor station will remove hydrogen sulfide and moisture and then meter and move the clean biogas into a gathering line connected to the centralized biogas upgrading facility and interconnection located nearby. Biomethane, meeting SoCalGas Rule 30, will be injected into the co-located point of receipt. The project's biomethane will be delivered as R-CNG to fleets and CNG fueling stations in California. California Bioenergy is the project developer. | O18: =P18/(0.001*365*0.9) -> 323643.84 | P18: 106317 | Q18: PIPELINE (For vehicle/other) | R18: NO | S18: =P18/0.112194 -> 947617.52 | V18: =199706/10 -> 19970.6 | AB18: https://www.cdfa.ca.gov/oefi/ddrdp/docs/2019-DDRDP_ApplicationsAwarded.pdf || https://www.cdfa.ca.gov/oefi/DDRDP/docs/DDRDP_Project_Level_Data.pdf
A19: Aria Moovers- Costa View (BP, Archaea) | B19: OPERATIONAL | C19: Dairy | D19: Madera | E19: CA | F19: Q4 2020 | G19: Q4 2021 | H19: BP, Aria, Aligned Digesters | I19: Covered Lagoon | J19: Manure Pond | K19: Raw biogas trucked to a cental upgrading point at Soares for pipeline injection | L19: 6097 | N19: =O19/0.6 -> 433282.6 | O19: =P19/(0.001*365*0.9) -> 259969.56 | P19: 85400 | Q19: PIPELINE (for vehicle/other) | R19: N/A | S19: 710000 | U19: N/A | W19: Part of multi-farm | X19: No | Y19: Greenlane | AA19: Yes | AB19: https://www.ariaenergy.com/bp-and-aria-energy-to-capture-methane-at-california-dairy-farms-as-part-of-renewable-natural-gas-project/
A20: Aria RNG Moovers- Soares (BP, Archaea) | B20: OPERATIONAL | C20: Dairy | D20: Merced | E20: CA | F20: Q3 2020 | G20: Q3 2021 | H20: BP, Aria, Aligned Digesters | I20: Covered Lagoon | J20: Manure Pond | K20: Raw biogas from this farm and the two farms trucking biogas are upgraded for pipeline injection. | L20: 4645 | N20: =O20/0.6 -> 329781.84 | O20: =P20/(0.001*365*0.9) -> 197869.1 | P20: 65000 | Q20: PIPELINE (for vehicle/other) | R20: N/A | S20: 540000 | U20: N/A | W20: Part of multi-farm | X20: No | Y20: Greenlane | AA20: Yes | AB20: https://www.ariaenergy.com/bp-and-aria-energy-to-capture-methane-at-california-dairy-farms-as-part-of-renewable-natural-gas-project/
A21: Aukeman Dairy (Tipton Dairy Biogas Cluster) | B21: OPERATIONAL | C21: Dairy | D21: Tulare | E21: CA | F21: 43282 | G21: Q3 2021 | H21: California Bioenergy, 4 Creeks Engineering, Anaergia, 4C Global and SoCalGas. | I21: Covered lagoon | J21: Covered lagoon | K21: Aukeman Farms Dairy, a dairy operation located in Tulare CA will build a Tier 1 designed manure only covered lagoon digester with enhanced gas storage, gas pre-treatment and effluent distribution. The project will include a sand lane, screens and mechanical separator with screw press for solid separation pre-digester. A compressor and meter station will deliver biogas via a biogas gathering line to the centralized "Tipton Dairy Biogas Cluster" shared upgrading facility where CO2, N2, O2, and further H2S removal produces biomethane meeting SoCalGas Rule 30 specifications. A gas compressor lifts the biomethane pressure to SoCalGas's point of receipt acceptance specification. Gas marketing, dairy processor and hauler commitments guarantee 100% delivery of the project's biomethane as RCNG for vehicle fuel use in California. California Bioenergy, 4 Creeks Engineering, Anaergia, 4C Global and SoCalGas comprise the project team. | N21: =O21/0.6 -> 228376.98 | O21: =P21/(0.001*365*0.9) -> 137026.19 | P21: =S21*0.112194 -> 45013.103 | Q21: PIPELINE (For vehicle/other) | R21: No | S21: =3497888/10*1.147 -> 401207.75 | V21: 20770 | AB21: https://www.cdfa.ca.gov/oefi/ddrdp/docs/2018_DDRDP_ProjectsAwarded.pdf || https://www.cdfa.ca.gov/oefi/DDRDP/docs/DDRDP_Project_Level_Data.pdf https://www.arb.ca.gov/cc/capandtrade/auctionproceeds/historicdata_2020AR.xlsx
A22: Belonave Dairy (Kern Cluster) | B22: OPERATIONAL | C22: Dairy | D22: Kern | E22: CA | F22: 43282 | G22: Q3 2021 | H22: California Bioenergy, 4 Creeks Engineering, Anaergia, 4C Global and SoCalGas. | I22: Covered lagoon | J22: Covered lagoon | K22: Belonave, a dairy operation located in Bakersfield, CA will build a Tier 1 designed manure only covered lagoon with enhanced gas storage, gas pre-treatment and effluent distribution. The project will include a sand lane, screens and mechanical separator with screw press for solid separation predigester. A compressor will deliver biogas via a biogas gathering line to a centralized upgrading facility where CO2, N2, O2, and further H2S removal produces biomethane meeting SoCalGas Rule 30 specifications. A gas compressor lifts the gas pressure to SoCalGas's point of receipt acceptance specification. Gas marketing, dairy processor and hauler commitments guarantee 100% delivery of the project's biomethane as R-CNG for vehicle fuel use in California. California Bioenergy, 4 Creeks Engineering, Anaergia, 4C Global and SoCalGas comprise the project team. | N22: =O22/0.6 -> 389593.44 | O22: =P22/(0.001*365*0.9) -> 233756.06 | P22: =S22*0.112194 -> 76788.867 | Q22: PIPELINE (For vehicle/other) | R22: No | S22: =5967126/10*1.147 -> 684429.35 | V22: 22566 | AB22: https://www.cdfa.ca.gov/oefi/ddrdp/docs/2018_DDRDP_ProjectsAwarded.pdf \\ https://www.cdfa.ca.gov/oefi/DDRDP/docs/DDRDP_Project_Level_Data.pdf https://www.arb.ca.gov/cc/capandtrade/auctionproceeds/historicdata_2020AR.xlsx
A23: Bos Farms Dairy (South Tulare Cluster) | B23: OPERATIONAL | C23: Dairy | D23: Tulare | E23: CA | F23: 43009 | G23: Q3 2021 | H23: California Bioenergy, 4 Creeks Engineering, Anaergia, 4C Global and SoCalGas. | I23: Covered Lagoon | J23: Covered lagoon | K23: Bos Farms Dairy Biogas was awarded $1.5 million to support a $12.83 million project in Tulare, California. The dairy proposes to build a Tier 1 designed manure-only covered lagoon digester with enhanced gas storage, gas pretreatment, and effluent distribution. The project will add sand lane and screens for solid separation pre-digester. Blowers will deliver biogas to an adjacent centralized upgrading facility where it will be processed for use as vehicle fuel. The project team includes California Bioenergy, 4 Creeks Engineering, Anaergia, 4C Global and SoCalGas. | N23: =O23/0.6 -> 26416.515 | O23: =P23/(0.001*365*0.9) -> 15849.909 | P23: =S23*0.112194 -> 5206.6951 | Q23: PIPELINE (For vehicle/other) | R23: No | S23: =404603/10*1.147 -> 46407.964 | V23: 16839 | AB23: http://biomassmagazine.com/articles/14827/ https://www.cdfa.ca.gov/oefi/ddrdp/docs/2017_DDRDP_ProjectsAwarded.pdf \\ https://www.cdfa.ca.gov/oefi/DDRDP/docs/DDRDP_Project_Level_Data.pdfhttps://www.cdfa.ca.gov/oefi/DDRDP/docs/DDRDP_Project_Level_Data.pdf https://www.arb.ca.gov/cc/capandtrade/auctionproceeds/historicdata_2020AR.xlsx
A24: BV Dairy (Kern Cluster) | B24: OPERATIONAL | C24: Dairy | D24: Kern | E24: CA | F24: 43282 | G24: Q4 2020 | H24: California Bioenergy, 4 Creeks Engineering, Anaergia, 4C Global and SoCalGas. | I24: Covered Lagoon | J24: Covered lagoon | K24: BV Dairy, a dairy operation located in Bakersfield, CA will build a Tier 1 designed manure only covered lagoon with enhanced gas storage, gas pre-treatment and effluent distribution. The project will include a sand lane, screens and mechanical separator with screw press for solid separation predigester. A compressor will deliver biogas via a biogas gathering line to a centralized upgrading facility where CO2, N2, O2, and further H2S removal produces biomethane meeting SoCalGas Rule 30 specifications. A gas compressor lifts the gas pressure to SoCalGas's point of receipt acceptance specification. Gas marketing, dairy processor and hauler commitments guarantee 100% delivery of the project's biomethane as R-CNG for vehicle fuel use in California. California Bioenergy, 4 Creeks Engineering, Anaergia, 4C Global and SoCalGas comprise the project team. | N24: =O24/0.6 -> 241115.44 | O24: =P24/(0.001*365*0.9) -> 144669.27 | P24: =S24*0.112194 -> 47523.854 | Q24: PIPELINE (For vehicle/other) | R24: No | S24: =3692994/10*1.147 -> 423586.41 | V24: 20584 | AB24: https://www.cdfa.ca.gov/oefi/ddrdp/docs/2018_DDRDP_ProjectsAwarded.pdf \\ https://www.cdfa.ca.gov/oefi/DDRDP/docs/DDRDP_Project_Level_Data.pdf https://www.arb.ca.gov/cc/capandtrade/auctionproceeds/historicdata_2020AR.xlsx
A25: Circle A Dairy Digester Fuel Pipeline Project (Calgren Dairy Fuels Cluster) | B25: OPERATIONAL | C25: Dairy | D25: Tulare | E25: CA | F25: Q1 2019 | G25: December 2018 | H25: Calgren Dairy Fuels LLC | I25: Covered lagoon | J25: Covered lagoon | K25: Calgren was awarded $1.05 million to support the $2.35 million Circle A Dairy Digester Fuel Pipeline Project. The project is a covered lagoon digester processing manure in Tulare County. The project is owned by Calgren, which will construct it at no cost to the dairy and will make guaranteed payments to the dairy. The project is part of the Calgren Dairy Fuels Cluster. Biogas produced at the site will be supplied via a private pipeline to fuel two 5 MW gas turbines that power the Calgren ethanol refinery. The cluster will install a renewable compressed natural gas (RCNG) station and later connect to the utility pipeline to supply more RCNG stations. | L25: 4370 | N25: 330000 | O25: =N25*0.6 -> 198000 | P25: =O25*0.001*365*0.9 -> 65043 | Q25: BOTH | R25: Unknown | S25: =P25/0.112194 -> 579736.88 | V25: 13874 | Y25: Upgrading system Air Liquide | AB25: http://biomassmagazine.com/articles/14827/ https://www.cdfa.ca.gov/oefi/ddrdp/docs/2017_DDRDP_ProjectsAwarded.pdf https://www.cdfa.ca.gov/oefi/DDRDP/docs/DDRDP_Project_Level_Data.pdf https://www.arb.ca.gov/cc/capandtrade/auctionproceeds/historicdata_2020AR.xlsx
A26: Cloverdale Dairy (Hanford Cluster) | B26: OPERATIONAL | C26: Dairy | D26: Kings | E26: CA | F26: 43009 | H26: California Bioenergy, 4 Creeks Engineering, Anaergia, 4C Global and SoCalGas. | I26: Covered Lagoon | J26: Covered lagoon | K26: Cloverdale was awarded $3 million to support a $7.84 million project in Hanford, California. The project aims to build a Tier 1 designed manure-only covered lagoon digester with enhanced gas storage, gas pretreatment, and effluent distribution. The project will add sand lane and screens for solid separation pre-digester. Blowers will deliver biogas to an adjacent centralized upgrading facility where it will be processed for use as vehicle fuel. The project team includes California Bioenergy, 4 Creeks Engineering, Anaergia, 4C Global and SoCalGas. | N26: =O26/0.6 -> 30523.515 | O26: =P26/(0.001*365*0.9) -> 18314.109 | P26: =S26*0.112194 -> 6016.1848 | Q26: PIPELINE (For vehicle/other) | R26: No | S26: =467507/10*1.147 -> 53623.053 | V26: 36085 | AB26: https://www.arb.ca.gov/cc/capandtrade/auctionproceeds/historicdata_2020AR.xlsx
A27: Cornerstone (Calgren Dairy Fuels Cluster) | B27: OPERATIONAL | C27: Dairy | D27: Tulare | E27: CA | F27: 7.1.2018 | G27: Q3 2019 | H27: Calgren/Maas Energy Works | J27: Covered lagoon | K27: Cornerstone Dairy Digester Pipeline Project is a new covered lagoon digester processing dairy manure in Tulare County, California. The project is a part of the Calgren Dairy Fuels Cluster, developed by Maas Energy Works. The Calgren Dairy Fuels Cluster has already laid four miles of pipeline and begun construction of three digesters awarded CDFA funds in late 2017--scheduled to provide the state's first pipeline diary biogas fuel by June of 2018. The methane-rich biogas from the digester will be transported via private, low-pressure pipeline to the cluster's central hub near the Calgren ethanol refinery. Once at the hub, it will be used to fuel partner and public trucks at an on-site compressed natural gas fueling station. The remainder of the gas will be injected into the adjacent SoCalGas utility pipeline for delivery to other CNG fueling stations around the Central Valley and the state | L27: 7425 | N27: =O27/0.6 -> 259825.26 | O27: =P27/(0.001*365*0.9) -> 155895.16 | P27: =S27*0.112194 -> 51211.559 | Q27: BOTH | R27: Public | S27: =3979559/10*1.147 -> 456455.42 | V27: 18523 | AB27: https://www.cdfa.ca.gov/oefi/ddrdp/docs/2018_DDRDP_ProjectsAwarded.pdf https://www.cdfa.ca.gov/oefi/DDRDP/docs/DDRDP_Project_Level_Data.pdf https://www.maasenergy.com/digesters
A28: De Groot South | B28: OPERATIONAL | C28: Dairy | D28: Kings | E28: CA | F28: 43282 | G28: Planned completion 9/30/2020 | H28: California Bioenergy, 4 Creeks Engineering, Anaergia, 4C Global and SoCalGas. | I28: Covered Lagoon | J28: Covered lagoon | K28: South Dairy, LP, a dairy operation located in Hanford, CA will build a Tier 1 designed manure only covered lagoon with enhanced gas storage, gas pre-treatment and effluent distribution. The project will include a sand lane, screens and mechanical separator with screw press for solid separation predigester. A compressor will deliver biogas via a biogas gathering line to a centralized upgrading facility where CO2, N2, O2, and further H2S removal produces biomethane meeting SoCalGas Rule 30 specifications. A gas compressor lifts the gas pressure to SoCalGas's point of receipt acceptance specification. Gas marketing, dairy processor and hauler commitments guarantee 100% delivery of the project's biomethane as R-CNG for vehicle fuel use in California. California Bioenergy, 4 Creeks Engineering, Anaergia, 4C Global and SoCalGas comprise the project team. | N28: =O28/0.6 -> 167561.21 | O28: =P28/(0.001*365*0.9) -> 100536.72 | P28: =S28*0.112194 -> 33026.314 | Q28: PIPELINE (For vehicle/other) | R28: No | S28: =2566416/10*1.147 -> 294367.92 | V28: 18149 | AB28: https://www.cdfa.ca.gov/oefi/ddrdp/docs/2018_DDRDP_ProjectsAwarded.pdf https://www.cdfa.ca.gov/oefi/DDRDP/docs/DDRDP_Project_Level_Data.pdf https://www.arb.ca.gov/cc/capandtrade/auctionproceeds/historicdata_2020AR.xlsx
A29: Decade Centralized (Hanford Lakeside Cluster) | B29: OPERATIONAL | C29: Dairy | D29: Tulare | E29: CA | H29: Maas Energy Works | J29: Covered lagoon | K29: The Decade Centralized Dairy Digester Pipeline Project is a new covered lagoon digester processing dairy manure from two dairies in Tulare County, California. The project is 100% farmer owned by the host dairymen Eric and Clarinda Westra & Richard and Donna Westra. The project is a part of the Hanford-Lakeside Pipeline cluster, developed by Maas Energy Works. The methane-rich biogas from the digester will be transported via private, low-pressure pipeline to the cluster's central hub near River Ranch. Once at the hub, it will be used to fuel partner and public trucks at an on-site compressed natural gas fueling station. The remainder of the gas will be injected into the adjacent SoCalGas utility pipeline for delivery to other CNG fueling stations around the Central Valley and the state. | L29: 10350 | N29: =O29/0.6 -> 273181.83 | O29: =P29/(0.001*365*0.9) -> 163909.1 | P29: =S29*0.112194 -> 53844.138 | Q29: BOTH | R29: Public | S29: =4184132/10*1.147 -> 479919.94 | V29: 19256 | AB29: https://www.cdfa.ca.gov/oefi/ddrdp/docs/2018_DDRDP_ProjectsAwarded.pdf https://www.cdfa.ca.gov/oefi/DDRDP/docs/DDRDP_Project_Level_Data.pdf
A30: Dixie Creek Dairy Digester Pipeline Project (Lakeside Cluster) | B30: OPERATIONAL | C30: Dairy | D30: Kings | E30: CA | F30: 12.1.2019 | H30: Maas Energy Works | I30: Covered lagoon | K30: Dixie Creek Dairy Digester Pipeline Project is a new covered lagoon digester processing in Kings County, California. The project is a part of the Lakeside Pipeline cluster, developed by Maas Energy Works and majority owned by participating dairy families. This cluster was selected as an SB-1383 Pilot Project. This individual digester 100% producer-owned by the host dairy family, and developed and operated by Maas Energy Works. The methane-rich biogas from the digester will be transported via private, low-pressure pipeline to the cluster's central hub near River Ranch dairy. There, the biogas will be used to fuel partner and public trucks at an on-site compressed natural gas fueling station. The remainder of the gas will be injected into the SoCalGas utility pipeline for delivery to contracted CNG fueling stations around the state--similar to the Project Team's and DDRDP's successful Calgren Dairy Fuels cluster, which is currently injecting utility-grade renewable natural gas. | N30: =O30/0.6 -> 1642274.8 | O30: =P30/(0.001*365*0.9) -> 985364.89 | P30: =S30*0.112194 -> 323692.37 | Q30: BOTH | R30: Public | S30: 2885113 | V30: 27000 | AB30: https://www.cdfa.ca.gov/oefi/ddrdp/docs/2019-DDRDP_ApplicationsAwarded.pdf https://www.cdfa.ca.gov/oefi/DDRDP/docs/DDRDP_Project_Level_Data.pdf
A31: DJ South (Merced South Cluster) | B31: OPERATIONAL | C31: Dairy | D31: Madera | E31: CA | F31: 43282 | G31: Planned completion 3/31/2021 | H31: Maas Energy Works | I31: Covered Lagoon | J31: Covered lagoon | K31: DJ South Dairy Digester Pipeline Project is a new covered lagoon digester processing dairy manure in Merced County, California--opening up digester development in California's second largest dairy county. The project is owned by DJ South Dairy Biogas LLC and is a part of the Merced-South cluster, developed by Maas Energy Works. The methane-rich biogas from the digester will be transported via private, low-pressure pipeline to the cluster's central hub at the center of the dairy group. Once at the hub, the biogas will be used to fuel partner and public trucks at a new compressed natural gas fueling station. The remainder of the gas will be injected into the PG&E utility pipeline for delivery to other CNG fueling stations around the Central Valley and the state. | N31: =(O31/6)*10 -> 2412214.3 | O31: =P31/(0.001*365*0.9) -> 1447328.6 | P31: =S31*0.112194 -> 475447.43 | Q31: BOTH | R31: Public | S31: 4237726 | V31: 15018 | AB31: https://www.cdfa.ca.gov/oefi/ddrdp/docs/2018_DDRDP_ProjectsAwarded.pdf https://www.cdfa.ca.gov/oefi/DDRDP/docs/DDRDP_Project_Level_Data.pdf https://www.arb.ca.gov/cc/capandtrade/auctionproceeds/historicdata_2020AR.xlsx
A32: Double D (Aemetis Cluster) | B32: OPERATIONAL | C32: Dairy | D32: Stanislaus | E32: CA | F32: 43349 | G32: Q4 2020 | H32: Maas Energy Works | I32: Covered Lagoon | J32: Covered lagoon | K32: Double D Dairy Digester Pipeline Project is a new covered lagoon digester processing dairy manure in Stanislaus County, California. The project is a part of the Aemetis Cluster, developed by Maas Energy Works. The methane-rich biogas from the digester will be transported via private, low-pressure pipeline to the cluster's central hub near at the Aemetis ethanol refinery. Once at the hub, most of the biogas will be used to fuel partner trucks at an on-site compressed natural gas fueling station. The remainder of the gas will be used on site to fuel boilers at the Aemetis ethanol refinery to make very low carbon vehicle fuel. The project can begin generating greenhouse gas reductions very quickly since it does not require utility pipeline interconnection during this first phase. | L32: 8350 | N32: =(O32/6)*10 -> 313011.25 | O32: =P32/(0.001*365*0.9) -> 187806.75 | P32: =S32*0.112194 -> 61694.517 | Q32: BOTH | R32: Public | S32: =4794171/10*1.147 -> 549891.41 | V32: 18985 | AB32: https://www.cdfa.ca.gov/oefi/ddrdp/docs/2018_DDRDP_ProjectsAwarded.pdf https://www.cdfa.ca.gov/oefi/DDRDP/docs/DDRDP_Project_Level_Data.pdf https://www.arb.ca.gov/cc/capandtrade/auctionproceeds/historicdata_2020AR.xlsx
A33: Double J (North Visalia Cluster) | B33: OPERATIONAL | C33: Dairy | D33: Tulare | E33: CA | F33: 43282 | G33: Q3 2021 | H33: California Bioenergy, 4 Creeks Engineering, Anaergia, 4C Global and SoCalGas. | I33: Covered Lagoon | J33: Covered lagoon | K33: Double J Dairy, a dairy operation located in Visalia, CA will build a Tier 1 designed manure only covered lagoon with enhanced gas storage, gas pre-treatment and effluent distribution. The project will include a sand lane, screens and mechanical separator with screw press for solid separation predigester. A compressor will deliver biogas via a biogas gathering line to a centralized upgrading facility where CO2, N2, O2, and further H2S removal produces biomethane meeting SoCalGas Rule 30 specifications. A gas compressor lifts the gas pressure to SoCalGas's point of receipt acceptance specification. Gas marketing, dairy processor and hauler commitments guarantee 100% delivery of the project's biomethane as R-CNG for vehicle fuel use in California. California Bioenergy, 4 Creeks Engineering, Anaergia, 4C Global and SoCalGas comprise the project team. | N33: =O33/0.6 -> 354419.19 | O33: =P33/(0.001*365*0.9) -> 212651.51 | P33: =S33*0.112194 -> 69856.022 | Q33: PIPELINE (For vehicle/other) | R33: No | S33: =5428387/10*1.147 -> 622635.99 | V33: 28550 | AB33: https://www.cdfa.ca.gov/oefi/ddrdp/docs/2018_DDRDP_ProjectsAwarded.pdf https://www.cdfa.ca.gov/oefi/DDRDP/docs/DDRDP_Project_Level_Data.pdf https://www.arb.ca.gov/cc/capandtrade/auctionproceeds/historicdata_2020AR.xlsx
A34: Double L (Hanford/Lakeside Cluster) | B34: OPERATIONAL | C34: Dairy | D34: Kings | E34: CA | F34: 43282 | G34: Planned completion 3/31/2021 | H34: Maas Energy Works | I34: Covered Lagoon | J34: Covered lagoon | K34: Double L Dairy Digester Pipeline Project is a new covered lagoon digester processing dairy manure in King's County, California. The project is owned by Double L Dairy Biogas LLC and is part of the HanfordLakeside Pipeline cluster, developed by Maas Energy Works. The methane-rich biogas from the digester will be transported via private, low-pressure pipeline to the cluster's central hub near River Ranch. Once at the hub, it will be used to fuel partner and public trucks at an on-site compressed natural gas fueling station. The remainder of the gas will be injected into the adjacent SoCalGas utility pipeline for delivery to other CNG fueling stations around the Central Valley and the state. | N34: =O34/0.6 -> 262373.01 | O34: =P34/(0.001*365*0.9) -> 157423.8 | P34: =S34*0.112194 -> 51713.72 | Q34: BOTH | R34: Public | S34: =4018581/10*1.147 -> 460931.24 | V34: 13615 | AB34: https://www.cdfa.ca.gov/oefi/ddrdp/docs/2018_DDRDP_ProjectsAwarded.pdf https://www.cdfa.ca.gov/oefi/DDRDP/docs/DDRDP_Project_Level_Data.pdf https://www.arb.ca.gov/cc/capandtrade/auctionproceeds/historicdata_2020AR.xlsx
A35: Dykstra (Tipton Dairy Cluster) | B35: OPERATIONAL | C35: Dairy | D35: Tulare | E35: CA | F35: 43282 | G35: Q3 2021 | H35: California Bioenergy, 4 Creeks Engineering, Anaergia, 4C Global and SoCalGas. | I35: Covered Lagoon | J35: Covered lagoon | K35: Dykstra Dairy, a dairy operation located in Tulare, CA will build a Tier 1 designed manure only covered lagoon with enhanced gas storage, gas pre-treatment and effluent distribution. The project will include a sand lane, screens and mechanical separator with screw press for solid separation predigester. A compressor and meter station will deliver biogas via a biogas gathering line to the centralized "Tipton Dairy Cluster" shared upgrading facility where CO2, N2, O2, and further H2S removal produces biomethane meeting SoCalGas Rule 30 specifications. A gas compressor lifts the biomethane pressure to SoCalGas's point of receipt acceptance specification. Gas marketing, dairy processor and hauler commitments guarantee 100% delivery of the project's biomethane as R-CNG for vehicle fuel use in California. California Bioenergy, 4 Creeks Engineering, Anaergia, 4C Global and SoCalGas comprise the project team. | N35: =O35/0.6 -> 290744.5 | O35: =P35/(0.001*365*0.9) -> 174446.7 | P35: =S35*0.112194 -> 57305.741 | Q35: PIPELINE (For vehicle/other) | R35: No | S35: =4453127/10*1.147 -> 510773.67 | V35: 26594 | AB35: https://www.cdfa.ca.gov/oefi/ddrdp/docs/2018_DDRDP_ProjectsAwarded.pdf https://www.cdfa.ca.gov/oefi/DDRDP/docs/DDRDP_Project_Level_Data.pdf https://www.arb.ca.gov/cc/capandtrade/auctionproceeds/historicdata_2020AR.xlsx
A36: El Monte (South Tulare Cluster) | B36: OPERATIONAL | C36: Dairy | D36: Tulare | E36: CA | F36: 43374 | G36: Q3 2021 | H36: California Bioenergy, 4 Creeks Engineering, Anaergia, 4C Global and SoCalGas. | I36: Covered Lagoon | J36: Covered lagoon | K36: The El Monte Dairy, a dairy operation located in Tipton, CA proposes to build a Tier 1 designed manure only covered lagoon with enhanced gas storage, gas pretreatment and effluent distribution. The project will include a sand lane, screens and mechanical separator with screw press for solid separation pre-digester. A compressor will deliver biogas via a biogas gathering line to a centralized upgrading facility where CO2, N2, O2, and further H2S removal produces biomethane meeting SoCalGas Rule 30 specifications. A gas compressor lifts the gas pressure to SoCalGas's point of receipt acceptance specification. Gas marketing, dairy processor and hauler commitments guarantee 100% delivery of the project's biomethane as R-CNG for vehicle fuel use in California. California Bioenergy, 4 Creeks Engineering, Anaergia, 4C Global and SoCalGas comprise the project team. | N36: =O36/0.6 -> 151261.31 | O36: =P36/(0.001*365*0.9) -> 90756.784 | P36: =S36*0.112194 -> 29813.603 | Q36: PIPELINE (For vehicle/other) | R36: No | S36: =2316762/10*1.147 -> 265732.6 | V36: 11890 | AB36: https://www.cdfa.ca.gov/oefi/ddrdp/docs/2018_DDRDP_ProjectsAwarded.pdf https://www.cdfa.ca.gov/oefi/DDRDP/docs/DDRDP_Project_Level_Data.pdf https://www.arb.ca.gov/cc/capandtrade/auctionproceeds/historicdata_2020AR.xlsx
A37: Elk Creek Dairy Biogas (South Tulare cluster) | B37: OPERATIONAL | C37: Dairy | D37: Tulare | E37: CA | F37: 12.1.2019 | H37: California Bioenergy | I37: Covered lagoon | K37: Elk Creek Dairy joins the South Tulare dairy biogas to fuel cluster. The dairy will install a Tier 1 designed manure only covered lagoon digester with integrated gas storage and pre-treatment. An on-dairy biogas conditioning and compressor station will remove hydrogen sulfide and moisture and then meter and move the clean biogas into a gathering line connecting to the centralized biogas upgrading facility. Biomethane, meeting SoCalGas Rule 30, will be injected into co-located point of receipt. The project's biomethane will be delivered as R-CNG to fleets and CNG fueling stations in California. California Bioenergy is the project developer. | O37: =P37/(0.001*365*0.9) -> 323643.84 | P37: 106317 | Q37: PIPELINE (For vehicle/other) | R37: No | S37: =P37/0.112194 -> 947617.52 | V37: 5950 | AB37: https://www.cdfa.ca.gov/oefi/ddrdp/docs/2019-DDRDP_ApplicationsAwarded.pdf https://www.cdfa.ca.gov/oefi/DDRDP/docs/DDRDP_Project_Level_Data.pdf
A38: Elkhorn Dairy Biogas (North Visalia cluster) | B38: OPERATIONAL | C38: Dairy | D38: Tulare | E38: CA | H38: California Bioenergy | I38: Covered lagoon | K38: Elkhorn Dairy is part of the established North Visalia dairy biogas to fuel cluster in Tulare County, CA. The dairy will install a Tier 1 designed manure only covered lagoon igester with integrated gas storage and pre-treatment. An on-dairy biogas conditioning and compressor will remove hydrogen sulfide and moisture and then meter and move the clean biogas into a gathering line extension connecting to centralized biogas upgrading and interconnection facility. Biomethane, meeting SoCalGas Rule 30, will be injected into the co-located point of receipt. The project's biomethane will be delivered as R-CNG to fleets and CNG fueling stations in California. California Bioenergy is the project developer. | N38: 325000 | O38: =N38*0.6 -> 195000 | P38: =O38*0.3285 -> 64057.5 | Q38: PIPELINE (For vehicle/other) | R38: NO | S38: =P38/0.112194 -> 570952.99 | V38: 21200 | AB38: https://www.cdfa.ca.gov/oefi/ddrdp/docs/2019-DDRDP_ApplicationsAwarded.pdf https://www.cdfa.ca.gov/oefi/DDRDP/docs/DDRDP_Project_Level_Data.pdf
A39: Five H (Merced-South Cluster) | B39: OPERATIONAL | C39: Dairy | D39: Merced | E39: CA | F39: 43282 | G39: Planned completion 3/31/2020 | H39: Maas Energy Works | I39: Covered Lagoon | J39: Covered lagoon | K39: Five H Dairy Digester Pipeline Project is a new covered lagoon digester processing dairy manure in Merced County, California--opening up digester development in California's second largest dairy county. The project is owned by Five H Dairy Biogas LLC and is a part of the Merced-South cluster, developed by Maas Energy Works. The methane-rich biogas from the digester will be transported via private, low-pressure pipeline to the cluster's central hub at the center of the dairy group. Once at the hub, the biogas will be used to fuel partner and public trucks at a new compressed natural gas fueling station. The remainder of the gas will be injected into the PG&E utility pipeline for delivery to other CNG fueling stations around the Central Valley and the state | N39: =O39/0.6 -> 205043.06 | O39: =P39/(0.001*365*0.9) -> 123025.84 | P39: =S39*0.112194 -> 40413.988 | Q39: BOTH | R39: Public | S39: =3140499/10*1.147 -> 360215.24 | V39: 12218 | AB39: https://www.cdfa.ca.gov/oefi/ddrdp/docs/2018_DDRDP_ProjectsAwarded.pdf https://www.cdfa.ca.gov/oefi/DDRDP/docs/DDRDP_Project_Level_Data.pdfhttps://www.arb.ca.gov/cc/capandtrade/auctionproceeds/historicdata_2020AR.xlsx
A40: FM Jersey (Calgren Dairy Fuels Cluster) | B40: OPERATIONAL | C40: Dairy | D40: Tulare | E40: CA | H40: Calgren/Maas Energy Works | J40: Covered lagoon | K40: FM Jerseys Dairy Digester Pipeline Project is a new covered lagoon digester processing dairy manure in Tulare County, California. The project is a part of the Calgren Dairy Fuels Cluster, developed by Maas Energy Works. FM Jerseys (located on the opposite of the highway and railroad tracks) will greatly expand the reach of this cluster by delivering gas via virtual pipeline--rapidly growing the geographic area served by the state's first dairy fuels cluster. The methane-rich biogas from the digester will be hauled using clean-burning renewable CNG-fueled trucks and compressed natural gas tube trailers to create a virtual pipeline to the cluster's central hub at the Calgren ethanol refinery. Once at the hub, it will be used to fuel partner and public trucks at an on-site compressed natural gas fueling station. The remainder of the gas will be injected into the adjacent SoCalGas utility pipeline for delivery to other CNG fueling stations around the Central Valley and the state. | L40: 5200 | N40: =O40/0.6 -> 257602.14 | O40: =P40/(0.001*365*0.9) -> 154561.28 | P40: =S40*0.112194 -> 50773.381 | Q40: BOTH | R40: Public | S40: =3945509/10*1.147 -> 452549.88 | V40: 16196 | AB40: https://www.cdfa.ca.gov/oefi/ddrdp/docs/2018_DDRDP_ProjectsAwarded.pdf https://www.cdfa.ca.gov/oefi/DDRDP/docs/DDRDP_Project_Level_Data.pdf https://www.arb.ca.gov/cc/capandtrade/auctionproceeds/historicdata_2020AR.xlsx
A41: Gerben Leyendekker Dairy Biogas (North Visalia cluster) | B41: OPERATIONAL | C41: Dairy | D41: Tulare | E41: CA | H41: California Bioenergy | I41: Covered lagoon | K41: Gerben Leyendekker Dairy joins the North Visalia dairy biogas to fuel cluster in Tulare County, CA. The dairy will install a Tier 1 designed manure-only covered lagoon digester with integrated gas storage and pre-treatment. An on-dairy biogas conditioning and compressor (shared with both the Art Leyendekker and GP Dairy neighboring digester projects) will remove hydrogen sulfide and moisture and then meter and move the clean biogas into a gathering line extension connecting to centralized biogas pgrading and interconnection facility. Biomethane, meeting SoCalGas Rule 30, will be injected into the co-located point of receipt. The project's biomethane will be delivered as R-CNG to fleets and CNG fueling stations in California. California Bioenergy is the project developer. | O41: =P41/(0.001*365*0.9) -> 323643.84 | P41: 106317 | Q41: PIPELINE (For vehicle/other) | R41: NO | S41: =P41/0.112194 -> 947617.52 | V41: 5070 | AB41: https://www.cdfa.ca.gov/oefi/ddrdp/docs/2019-DDRDP_ApplicationsAwarded.pdf https://www.cdfa.ca.gov/oefi/DDRDP/docs/DDRDP_Project_Level_Data.pdf
A42: Hamstra Dairy (West Visalia Cluster) | B42: OPERATIONAL | C42: Dairy | D42: Tulare | E42: CA | F42: 43009 | H42: California Bioenergy, 4 Creeks Engineering, Anaergia, 4C Global and SoCalGas. | I42: Covered Lagoon | J42: Covered lagoon | K42: Hamstra Dairy Biogas was awarded $2 million to support a $6.58 million project in Tulare, California. The dairy proposes to build a Tier 1 designed manure-only covered lagoon digester with enhanced gas storage, gas pretreatment, and effluent distribution. The project will add sand lane and screens for solid separation pre-digester. Blowers will deliver biogas to an adjacent centralized upgrading facility where it will be processed for use as vehicle fuel. The project team includes California Bioenergy, 4 Creeks Engineering, Anaergia, 4C Global and SoCalGas. | N42: =O42/0.6 -> 21425.554 | O42: =P42/(0.001*365*0.9) -> 12855.333 | P42: =S42*0.112194 -> 4222.9768 | Q42: PIPELINE (For vehicle/other) | R42: No | S42: =328160/10*1.147 -> 37639.952 | V42: 20512 | AB42: http://biomassmagazine.com/articles/14827/ https://www.cdfa.ca.gov/oefi/ddrdp/docs/2017_DDRDP_ProjectsAwarded.pdf https://www.arb.ca.gov/cc/capandtrade/auctionproceeds/historicdata_2020AR.xlsx
A43: Hettinga Centralized Dairy Digester Pipeline Project (Calgren Dairy Fuels cluster) | B43: OPERATIONAL | C43: Dairy | D43: Tulare | E43: CA | H43: Calgren Dairy Fuels | I43: Covered lagoon | K43: Hettinga Centralized Dairy Digester Pipeline Project is a new covered lagoon digester processing dairy manure at Hettinga Dairy in Tulare County, California. The project is owned by Calgren Dairy Fuels and will be a part of the Calgren Dairy Fuels (CDF) Cluster, developed by Maas Energy Works. This Cluster is operational, producing biogas from five digesters and injecting renewable natural gas into the SoCalGas pipeline. CDF has started physical construction on all 6 of its DDRDP awards received in 2018 and all are scheduled to be online in 2019. The biogas from this new digester will be transported via the Cluster's private, low-pressure pipeline to the cluster's hub near the Calgren ethanol refinery. Once there, it will be used to fuel partner and public trucks at an on-site compressed natural gas fueling station. The remainder of the gas will be injected into the SoCalGas pipeline for delivery to contracted CNG fueling stations around the Central Valley and the state. | N43: =O43/0.6 -> 1021293.8 | O43: =P43/(0.001*365*0.9) -> 612776.31 | P43: =S43*0.112194 -> 201297.02 | Q43: BOTH | R43: Public | S43: 1794187 | V43: 16730 | AB43: https://www.cdfa.ca.gov/oefi/ddrdp/docs/2019-DDRDP_ApplicationsAwarded.pdf https://www.cdfa.ca.gov/oefi/DDRDP/docs/DDRDP_Project_Level_Data.pdf
A44: High Roller Dairy Digester Pipeline Project (Lakeside Pipeline cluster) | B44: OPERATIONAL | C44: Dairy | D44: Kings | E44: CA | F44: 12.1.2019 | H44: Maas Energy Works | I44: Covered lagoon | K44: High Roller Dairy Digester Pipeline Project is a new covered lagoon digester processing in Kings County, California. The project is a part of the Lakeside Pipeline cluster, developed by Maas Energy Works and majority owned by participating dairy families. This cluster was selected as an SB-1383 Pilot Project. This individual digester 100% producer-owned by the host dairy family, and developed and operated by Maas Energy Works. The methane-rich biogas from the digester will be transported via private, low-pressure pipeline to the cluster's central hub near River Ranch dairy. There, the biogas will be used to fuel partner and public trucks at an on-site compressed natural gas fueling station. The remainder of the gas will be injected into the SoCalGas utility pipeline for delivery to contracted CNG fueling stations around the state--similar to the Project Team's and DDRDP's successful Calgren Dairy Fuels cluster, which is currently injecting utility-grade renewable natural gas. | N44: 266650 | O44: =N44*0.6 -> 159990 | P44: =O44*0.3285 -> 52556.715 | Q44: BOTH | R44: Public | S44: =P44/0.112194 -> 468444.97 | V44: 10000 | AB44: https://www.cdfa.ca.gov/oefi/ddrdp/docs/2019-DDRDP_ApplicationsAwarded.pdf https://www.cdfa.ca.gov/oefi/DDRDP/docs/DDRDP_Project_Level_Data.pdf
A45: Hilarides Dairy | B45: OPERATIONAL | C45: Dairy | D45: Tulare | E45: CA | F45: 2008 | H45: Maas Energy | I45: Covered Lagoon | J45: Storage Lagoon | K45: Generates electricity for on-site use by one lean burn, high efficiency engine. Can also produce CNG for onsite vehicle fueling. | L45: 10000 | O45: 45000 | P45: =O45*0.001*365*0.9 -> 14782.5 | Q45: VEHICLE FUEL (Local) | R45: Yes | S45: =P45/0.112194 -> 131758.38 | T45: 358383 | U45: 5000 MWh/yr | V45: 15000 | W45: Farm Scale | Y45: Environmental Fabrics, Inc., Phase 3 Developments & Investments, LLC, Sharp Energy | AA45: Unknown | AB45: https://www.dairycares.com/families/Hilarides_and_Borba https://www.wired.com/2009/02/milk-trucks-in/ http://www.tularechamber.org/list/member/hilarides-dairy-lindsay-2296 https://www.newkirk-electric.com/projects/biomass-biofuels/hilarides-dairy-biofuel-upgrade-unit#/ https://www.dairybusiness.com/considerations-when-evaluating-renewable-natural-gas-production-on-dairy-farms/
A46: Hollandia Farms Dairy (Hanford Cluster) | B46: OPERATIONAL | C46: Dairy | D46: Kings | E46: CA | F46: 43009 | G46: Q3 2021 | H46: California Bioenergy, 4 Creeks Engineering, Anaergia, 4C Global and SoCalGas | I46: Covered Lagoon | J46: Covered lagoon | K46: Hollandia Farms Dairy Biogas was awarded $1.5 million to support a $7.32 million project in Hanford, California. The dairy proposes to build a Tier 1 designed manure-only covered lagoon digester with enhanced gas storage, gas pretreatment, and effluent distribution. The project will add sand lane and screens for solid separation pre-digester. Blowers will deliver biogas to an adjacent centralized upgrading facility where it will be processed for use as vehicle fuel. The project team includes California Bioenergy, 4 Creeks Engineering, Anaergia, 4C Global and SoCalGas. | L46: 2900 | N46: =O46/0.6 -> 18325.195 | O46: =P46/(0.001*365*0.9) -> 10995.117 | P46: =S46*0.112194 -> 3611.896 | Q46: PIPELINE (For vehicle/other) | R46: No | S46: =280674/10*1.147 -> 32193.308 | V46: 17843 | AB46: http://biomassmagazine.com/articles/14827/ https://www.cdfa.ca.gov/oefi/ddrdp/docs/2017_DDRDP_ProjectsAwarded.pdf https://www.arb.ca.gov/cc/capandtrade/auctionproceeds/historicdata_2020AR.xlsx
